Workbook

Sheet Citește-mă
A1: SOUL — model de cost și break-even: fabrică mică vs lanț de producție
A2: ARTEMIS DIGITAL S.R.L. · model construit 15.10.2026, refăcut pe 22.10.2026 pe mărimea de bază S (AMOLED 1,75″ 466×466, 63×70,8×23 mm, LiPo 750 mAh; docs/size-s.json, docs/12-SIZE-S.md §3) · M (prototipul 2.8C) e comparația din Break-even
A4: Întrebarea: „ce ar însemna să facem efectiv o fabrică? mică, pentru asta, sau un lanț de producție măcar”
A6: Scenarii
A7: A — Lanț de producție, totul externalizat: EMS (Felix EMS / EMS-Electra) face PCBA + asamblare + flash + test; CNC + anodizare + sticlă la parteneri; noi facem QC final și ambalare.
A8: B — Atelier T0 propriu: PCBA și carcasa le cumpărăm; asamblarea, flash-ul, calibrarea, testul funcțional, QC, marcarea laser și ambalarea le facem noi.
A9: C — T1: B + celulă CNC proprie (Haas VF-2, sablare, ultrasunete). Anodizarea rămâne externă (Anorom / Alvi / ARSAT).
A10: D — T2: C + linie SMT proprie (NeoDen FP2636 + NeoDen4 + IN6 + AOI).
A11: Volume: 100 / 1.000 / 5.000 / 20.000 unități pe an.
A13: Foi
A14: Rezultate — tabelul-cheie: cost/unitate pe scenariu × volum, capex, costuri fixe, marjă, break-even CNC și SMT, capex pe treaptă.
A15: Ipoteze — TOATE intrările (albastru = editabil, galben = pârghie-cheie), cu sursă + URL + dată sau [estimare] cu raționament.
... A30: • Simplificări: prețul extern între trepte e interpolat logaritmic; la ≥10k carcasa ar trece pe ambutisare 5052 (nemodelat, ar face CNC-ul propriu și mai puțin atractiv).

Sheet Rezultate
A1: REZULTATE: fabrică SOUL vs lanț de producție (mărimea S, EUR fără TVA)
A2: Totul se calculează din foaia Ipoteze. Multe intrări sunt [estimare] până vin ofertele (RFQ): EMS RO, CNC, anodizare, sticlă, PCB custom. Fabrica (B–D) nu schimbă CE/RED, care e per produs (04-COMPLIANCE.md).
B4: 1. Cost total / unitate (fără NRE produs) | C4: =Scenarii!C7 -> 100 | D4: =Scenarii!D7 -> 1000 | E4: =Scenarii!E7 -> 5000 | F4: =Scenarii!F7 -> 20000
A5: A | B5: A — totul externalizat | C5: =Scenarii!C75 -> 224.82959 | D5: =Scenarii!D75 -> 97.46121 | E5: =Scenarii!E75 -> 70.792364 | F5: =Scenarii!F75 -> 57.953274
A6: B | B6: B — atelier T0 (asamblare + test) | C6: =Scenarii!C98 -> 255.89954 | D6: =Scenarii!D98 -> 104.00553 | E6: =Scenarii!E98 -> 73.191865 | F6: =Scenarii!F98 -> 55.172247
A7: C | B7: C — T0 + CNC propriu | C7: =Scenarii!C121 -> 804.88567 | D7: =Scenarii!D121 -> 137.87148 | E7: =Scenarii!E121 -> 71.799896 | F7: =Scenarii!F121 -> 51.095238
A8: D | B8: D — T0 + CNC + SMT propriu | C8: =Scenarii!C144 -> 1123.4202 | D8: =Scenarii!D144 -> 163.38697 | E8: =Scenarii!E144 -> 75.40723 | F8: =Scenarii!F144 -> 51.013738
B9: Cel mai ieftin scenariu | C9: =INDEX($A$5:$A$8,MATCH(MIN(C5:C8),C5:C8,0)) -> A | D9: =INDEX($A$5:$A$8,MATCH(MIN(D5:D8),D5:D8,0)) -> A | E9: =INDEX($A$5:$A$8,MATCH(MIN(E5:E8),E5:E8,0)) -> A | F9: =INDEX($A$5:$A$8,MATCH(MIN(F5:F8),F5:F8,0)) -> D
B11: 2. Cost total / unitate cu NRE produs (PCB, sticlă, matrițe OU pe 3 ani) | C11: =Scenarii!C7 -> 100 | D11: =Scenarii!D7 -> 1000 | E11: =Scenarii!E7 -> 5000 | F11: =Scenarii!F7 -> 20000
A12: A | B12: A — totul externalizat | C12: =Scenarii!C77 -> 253.82959 | D12: =Scenarii!D77 -> 108.55288 | E12: =Scenarii!E77 -> 73.897364 | F12: =Scenarii!F77 -> 58.729524
A13: B | B13: B — atelier T0 (asamblare + test) | C13: =Scenarii!C100 -> 284.89954 | D13: =Scenarii!D100 -> 115.09719 | E13: =Scenarii!E100 -> 76.296865 | F13: =Scenarii!F100 -> 55.948497
A14: C | B14: C — T0 + CNC propriu | C14: =Scenarii!C123 -> 833.88567 | D14: =Scenarii!D123 -> 148.96315 | E14: =Scenarii!E123 -> 74.904896 | F14: =Scenarii!F123 -> 51.871488
A15: D | B15: D — T0 + CNC + SMT propriu | C15: =Scenarii!C146 -> 1152.4202 | D15: =Scenarii!D146 -> 174.47864 | E15: =Scenarii!E146 -> 78.51223 | F15: =Scenarii!F146 -> 51.789988
B16: Cel mai ieftin scenariu | C16: =INDEX($A$12:$A$15,MATCH(MIN(C12:C15),C12:C15,0)) -> A | D16: =INDEX($A$12:$A$15,MATCH(MIN(D12:D15),D12:D15,0)) -> A | E16: =INDEX($A$12:$A$15,MATCH(MIN(E12:E15),E12:E15,0)) -> A | F16: =INDEX($A$12:$A$15,MATCH(MIN(F12:F15),F12:F15,0)) -> D
B18: 3. Cost variabil / unitate | C18: =Scenarii!C7 -> 100 | D18: =Scenarii!D7 -> 1000 | E18: =Scenarii!E7 -> 5000 | F18: =Scenarii!F7 -> 20000
A19: A | B19: A — totul externalizat | C19: =Scenarii!C73 -> 201.71023 | D19: =Scenarii!D73 -> 93.548833 | E19: =Scenarii!E73 -> 70.009888 | F19: =Scenarii!F73 -> 57.65037
A20: B | B20: B — atelier T0 (asamblare + test) | C20: =Scenarii!C96 -> 182.95715 | D20: =Scenarii!D96 -> 81.745755 | E20: =Scenarii!E96 -> 60.606809 | F20: =Scenarii!F96 -> 49.447291
A21: C | B21: C — T0 + CNC propriu | C21: =Scenarii!C119 -> 106.60504 | D21: =Scenarii!D119 -> 58.804795 | E21: =Scenarii!E119 -> 44.938946 | F21: =Scenarii!F119 -> 37.876969
A22: D | B22: D — T0 + CNC + SMT propriu | C22: =Scenarii!C142 -> 106.60504 | D22: =Scenarii!D142 -> 55.015263 | E22: =Scenarii!E142 -> 42.679629 | F22: =Scenarii!F142 -> 36.327629
B24: 4. Capex (investiție inițială) | C24: =Scenarii!C7 -> 100 | D24: =Scenarii!D7 -> 1000 | E24: =Scenarii!E7 -> 5000 | F24: =Scenarii!F7 -> 20000
A25: A | B25: A — totul externalizat | C25: =Scenarii!C59 -> 2135.8073 | D25: =Scenarii!D59 -> 6937.13 | E25: =Scenarii!E59 -> 6937.13 | F25: =Scenarii!F59 -> 13374.26
A26: B | B26: B — atelier T0 (asamblare + test) | C26: =Scenarii!C83 -> 10236.757 | D26: =Scenarii!D83 -> 23361.13 | E26: =Scenarii!E83 -> 26356.13 | F26: =Scenarii!F83 -> 38783.26
A27: C | B27: C — T0 + CNC propriu | C27: =Scenarii!C106 -> 136312.54 | D27: =Scenarii!D106 -> 127555.99 | E27: =Scenarii!E106 -> 130550.99 | F27: =Scenarii!F106 -> 326215.68
A28: D | B28: D — T0 + CNC + SMT propriu | C28: =Scenarii!C129 -> 180441.74 | D28: =Scenarii!D129 -> 164026.41 | E28: =Scenarii!E129 -> 167021.41 | F28: =Scenarii!F129 -> 362686.1
B30: 5. Costuri fixe anuale (chirie, salarii, amortizare, permise/asigurări) | C30: =Scenarii!C7 -> 100 | D30: =Scenarii!D7 -> 1000 | E30: =Scenarii!E7 -> 5000 | F30: =Scenarii!F7 -> 20000
A31: A | B31: A — totul externalizat | C31: =Scenarii!C64 -> 2311.9358 | D31: =Scenarii!D64 -> 3912.3767 | E31: =Scenarii!E64 -> 3912.3767 | F31: =Scenarii!F64 -> 6058.0867
A32: B | B32: B — atelier T0 (asamblare + test) | C32: =Scenarii!C89 -> 7294.239 | D32: =Scenarii!D89 -> 22259.771 | E32: =Scenarii!E89 -> 62925.279 | F32: =Scenarii!F89 -> 114499.13
A33: C | B33: C — T0 + CNC propriu | C33: =Scenarii!C112 -> 69828.062 | D33: =Scenarii!D112 -> 79066.69 | E33: =Scenarii!E112 -> 134304.75 | F33: =Scenarii!F112 -> 264365.39
A34: D | B34: D — T0 + CNC + SMT propriu | C34: =Scenarii!C135 -> 101681.52 | D34: =Scenarii!D135 -> 108371.71 | E34: =Scenarii!E135 -> 163638 | F34: =Scenarii!F135 -> 293722.17
B36: 6. Marjă brută / unitate la prețul de €249 (cu NRE) | C36: =Scenarii!C7 -> 100 | D36: =Scenarii!D7 -> 1000 | E36: =Scenarii!E7 -> 5000 | F36: =Scenarii!F7 -> 20000
A37: A | B37: A — totul externalizat | C37: =Scenarii!C79 -> -4.829587 | D37: =Scenarii!D79 -> 97.232247 | E37: =Scenarii!E79 -> 131.88776 | F37: =Scenarii!F79 -> 147.0556
A38: B | B38: B — atelier T0 (asamblare + test) | C38: =Scenarii!C102 -> -35.899541 | D38: =Scenarii!D102 -> 90.687932 | E38: =Scenarii!E102 -> 129.48826 | F38: =Scenarii!F102 -> 149.83663
A39: C | B39: C — T0 + CNC propriu | C39: =Scenarii!C125 -> -584.88567 | D39: =Scenarii!D125 -> 56.821973 | E39: =Scenarii!E125 -> 130.88023 | F39: =Scenarii!F125 -> 153.91364
A40: D | B40: D — T0 + CNC + SMT propriu | C40: =Scenarii!C148 -> -903.42025 | D40: =Scenarii!D148 -> 31.306484 | E40: =Scenarii!E148 -> 127.27289 | F40: =Scenarii!F148 -> 153.99514
B42: 7. Break-even: de la ce volum producția proprie bate externalizarea | C42: Grilă | D42: Analitic @1.000 | E42: Analitic @5.000 | F42: Analitic @20.000
B43: CNC mărimea S (seturi/an) | C43: ='Break-even'!$C$54 -> 5000 | D43: ='Break-even'!D32 -> 2586.1696 | E43: ='Break-even'!E32 -> 3799.8095 | F43: ='Break-even'!F32 -> 5165.1064
B44: CNC mărimea M, comparație (seturi/an) | C44: ='Break-even'!$C$72 -> 5000 | D44: ='Break-even'!D34 -> 1846.8163 | E44: ='Break-even'!E34 -> 2846.7273 | F44: ='Break-even'!F34 -> 4095.8148
B45: SMT propriu vs EMS România (plăci/an) | C45: ='Break-even'!$C$90 -> 20000 | D45: ='Break-even'!D36 -> 7979.215 | E45: ='Break-even'!E36 -> 13383.462 | F45: ='Break-even'!F36 -> 19516.375
B46: SMT propriu vs JLCPCB (plăci/an) | C46: ='Break-even'!$C$91 -> peste 60.000 | D46: ='Break-even'!D37 -> 47356.231 | E46: ='Break-even'!E37 -> 85519.708 | F46: ='Break-even'!F37 -> 152647.73
B47: Atelier T0 (B) vs box build la EMS (A), unități/an | C47: – | D47: =IF(Scenarii!D73-Scenarii!D96<=0,"niciodată",(Scenarii!D89-Scenarii!D64)/(Scenarii!D73-Scenarii!D96)) -> 1554.4583 | E47: =IF(Scenarii!E73-Scenarii!E96<=0,"niciodată",(Scenarii!E89-Scenarii!E64)/(Scenarii!E73-Scenarii!E96)) -> 6275.9127 | F47: =IF(Scenarii!F73-Scenarii!F96<=0,"niciodată",(Scenarii!F89-Scenarii!F64)/(Scenarii!F73-Scenarii!F96)) -> 13219.554
B48: Grilă = primul volum (cu trepte reale: al 2-lea schimb, încă o mașină) la care propriul e mai ieftin. Analitic = cost fix pentru 1 mașină/linie pe 1 schimb împărțit la economia per bucată la prețurile treptei respective.
B50: 8. Capex pe treaptă (net de TVA) | C50: Capex € | D50: Capacitate / schimb
B51: T0 atelier (configurația pentru 1.000 buc./an) | C51: =Scenarii!D83 -> 23361.13 | D51: =Capacitate!D14 -> 16.32 | E51: unități/operator/schimb (gâtuire: oamenii)
B52: T0 atelier (configurația pentru 20.000 buc./an) | C52: =Scenarii!F83 -> 38783.26
B53: T1: + 1 mașină CNC Haas VF-2 + scule + echipamente comune | C53: ='Break-even'!$C$17+Ipoteze!$C$118+'Break-even'!$C$18 -> 104194.86 | D53: =Ipoteze!$C$18/Ipoteze!$C$125 -> 17 | E53: seturi S / schimb
B54: T1: fiecare mașină CNC în plus (cu scule) | C54: ='Break-even'!$C$17+Ipoteze!$C$118 -> 91618.78
B55: T2: + 1 linie SMT (NeoDen4 + FP2636 + IN6 + AOI + MSL) | C55: ='Break-even'!$C$25 -> 36470.42 | D55: =Ipoteze!$C$18/(Capacitate!B12) -> 99.512195 | E55: plăci / schimb
B56: Celulă CNC la 20.000 seturi S (mașini × capex) | C56: =Scenarii!F48 -> 287432.42 | D56: =Scenarii!F42 -> 3 | E56: mașini necesare
B58: 9. Praguri de ofertă pentru RFQ: peste aceste prețuri externe, varianta proprie devine mai ieftină | C58: =Scenarii!C7 -> 100 | D58: =Scenarii!D7 -> 1000 | E58: =Scenarii!E7 -> 5000 | F58: =Scenarii!F7 -> 20000
B59: Box build EMS (€/buc.) — ipoteza curentă | C59: =Ipoteze!C$62 -> 15 | D59: =Ipoteze!D$62 -> 10 | E59: =Ipoteze!E$62 -> 8 | F59: =Ipoteze!F$62 -> 7
B60: Box build EMS (€/buc.) — prag peste care atelierul T0 (B) e mai ieftin | C60: =Ipoteze!C$62+(Scenarii!C98-Scenarii!C75)/(1+Scenarii!C11) -> 40.677648 | D60: =Ipoteze!D$62+(Scenarii!D98-Scenarii!D75)/(1+Scenarii!D11) -> 16.544315 | E60: =Ipoteze!E$62+(Scenarii!E98-Scenarii!E75)/(1+Scenarii!E11) -> 10.399502 | F60: =Ipoteze!F$62+(Scenarii!F98-Scenarii!F75)/(1+Scenarii!F11) -> 4.2189732
B61: Carcasă S externă livrată (€/set) — ipoteza curentă | C61: =Scenarii!C25 -> 71.46414 | D61: =Scenarii!D25 -> 31.842824 | E61: =Scenarii!E25 -> 23.47671 | F61: =Scenarii!F25 -> 18.73638
B62: Carcasă S externă livrată (€/set) — prag peste care CNC propriu (C vs B) e mai ieftin | C62: =Scenarii!C25+(Scenarii!C121-Scenarii!C98)/((1+Ipoteze!$C$73)*(1+Scenarii!C11)) -> 511.9569 | D62: =Scenarii!D25+(Scenarii!D121-Scenarii!D98)/((1+Ipoteze!$C$73)*(1+Scenarii!D11)) -> 64.722396 | E62: =Scenarii!E25+(Scenarii!E121-Scenarii!E98)/((1+Ipoteze!$C$73)*(1+Scenarii!E11)) -> 22.125284 | F62: =Scenarii!F25+(Scenarii!F121-Scenarii!F98)/((1+Ipoteze!$C$73)*(1+Scenarii!F11)) -> 14.778118
B63: PCBA EMS (€/placă) — ipoteza curentă | C63: =Scenarii!C23 -> 0 | D63: =Scenarii!D23 -> 4 | E63: =Scenarii!E23 -> 2.5 | F63: =Scenarii!F23 -> 1.8
B64: PCBA EMS (€/placă) — prag peste care SMT propriu (D vs C) e mai ieftin | C64: =IF(Scenarii!C8=2,"fără PCB propriu",Scenarii!C23+(Scenarii!C144-Scenarii!C121)/((1+Ipoteze!$C$73)*(1+Scenarii!C11))) -> fără PCB propriu | D64: =IF(Scenarii!D8=2,"fără PCB propriu",Scenarii!D23+(Scenarii!D144-Scenarii!D121)/((1+Ipoteze!$C$73)*(1+Scenarii!D11))) -> 28.772319 | E64: =IF(Scenarii!E8=2,"fără PCB propriu",Scenarii!E23+(Scenarii!E144-Scenarii!E121)/((1+Ipoteze!$C$73)*(1+Scenarii!E11))) -> 6.0022658 | F64: =IF(Scenarii!F8=2,"fără PCB propriu",Scenarii!F23+(Scenarii!F144-Scenarii!F121)/((1+Ipoteze!$C$73)*(1+Scenarii!F11))) -> 1.7208736
B65: Dacă oferta reală e SUB prag, externalizarea rămâne mai ieftină la acel volum. Pragurile includ toate costurile fixe ale treptei (oameni, chirie, amortizare).
B67: 10. Ce citim din model (se actualizează automat din ipoteze; verifică după RFQ)
B68: ="• Cel mai ieftin la 100 / 1.000 / 5.000 / 20.000 buc./an: "&C9&" / "&D9&" / "&E9&" / "&F9&". Diferențele de câțiva €/buc. sunt sub marja de eroare a estimărilor." -> • Cel mai ieftin la 100 / 1.000 / 5.000 / 20.000 buc./an: A / A / A / D. Diferențele de câțiva €/buc. sunt sub marja de eroare a estimărilor.
B69: ="• Atelierul T0 (B) bate box build-ul la EMS dacă EMS cere peste "&TEXT(D60,"0.0")&" € la 1.000 buc. și peste "&TEXT(E60,"0.0")&" € la 5.000 (ipoteza: "&TEXT(D59,"0.0")&" / "&TEXT(E59,"0.0")&" €). Argumentul real pentru T0 e controlul: flash, calibrare, test, serie, QC." -> • Atelierul T0 (B) bate box build-ul la EMS dacă EMS cere peste 16.5 € la 1.000 buc. și peste 10.4 € la 5.000 (ipoteza: 10.0 / 8.0 €). Argumentul real pentru T0 e controlul: flash, calibrare, test, serie, QC.
B70: ="• CNC propriu S: o mașină plină pe un schimb (~"&TEXT('Break-even'!$C$23,"#,##0")&" seturi/an) e aproape de break-even; în grila cu trepte reale propriul câștigă de la "&IF(ISNUMBER('Break-even'!$C$54),TEXT('Break-even'!$C$54,"#,##0"),'Break-even'!$C$54)&" seturi/an (M, comparație: "&IF(ISNUMBER('Break-even'!$C$72),TEXT('Break-even'!$C$72,"#,##0"),'Break-even'!$C$72)&"). Prima celulă: ~"&TEXT('Break-even'!$C$17+Ipoteze!$C$118+'Break-even'!$C$18,"#,##0")&" € capex." -> • CNC propriu S: o mașină plină pe un schimb (~3,740 seturi/an) e aproape de break-even; în grila cu trepte reale propriul câștigă de la 5,000 seturi/an (M, comparație: 5,000). Prima celulă: ~104,195 € capex.
B71: ="• SMT propriu bate EMS România abia pe la "&IF(ISNUMBER('Break-even'!$C$90),TEXT('Break-even'!$C$90,"#,##0"),'Break-even'!$C$90)&" plăci/an (la limită) și nu bate JLCPCB în grilă ("&IF(ISNUMBER('Break-even'!$C$91),TEXT('Break-even'!$C$91,"#,##0"),'Break-even'!$C$91)&"). Plus: PCB-ul custom încă nu există." -> • SMT propriu bate EMS România abia pe la 20,000 plăci/an (la limită) și nu bate JLCPCB în grilă (peste 60.000). Plus: PCB-ul custom încă nu există.
B72: ="• Anodizarea rămâne externă în toate scenariile: CAEN 2561 cere autorizație de mediu, ape uzate NTPA-002 (Ni 1,0 mg/L), acetat de nichel; culoarea pe 5 nuanțe e riscul principal." -> • Anodizarea rămâne externă în toate scenariile: CAEN 2561 cere autorizație de mediu, ape uzate NTPA-002 (Ni 1,0 mg/L), acetat de nichel; culoarea pe 5 nuanțe e riscul principal.

Sheet Ipoteze
A1: IPOTEZE: toate datele de intrare ale modelului (singurul loc unde se modifică cifre)
A2: Legendă: text albastru = intrare editabilă; fond galben = pârghie-cheie; negru = formulă. Coloanele C–F = valori pe volum (100 / 1.000 / 5.000 / 20.000 unit./an); un singur număr în C = valabil pentru toate volumele. Sumele sunt FĂRĂ TVA, cu excepția celor marcate „cu TVA”. Sursele au URL + dată; [estimare] = raționament propriu, de înlocuit cu oferte (RFQ).
A4: Cheie | B4: Parametru | C4: 100 / valoare | D4: 1.000 | E4: 5.000 | F4: 20.000 | G4: Unitate | H4: Sursă / notă (data accesării) | I4: Încredere
A6: 1. Generale
A7: fx_eur_lei | B7: Curs EUR → lei | C7: 5.1 | G7: lei/€ | H7: Vault: „Finanțare — oferte de preț pentru PoC 1.1” (curs folosit pentru estimare, 12.10.2026) | I7: vault
A8: fx_usd_eur | B8: Curs USD → EUR | C8: 0.87 | G8: €/$ | H8: Vault: idem (1 $ ≈ 0,87 €) | I8: vault
A9: vol | B9: Volum analizat | C9: 100 | D9: 1000 | E9: 5000 | F9: 20000 | G9: unit./an | H9: Cererea fondatorului: pilot → sute → mii → zeci de mii pe an | I9: input
A10: price_retail | B10: Preț de vânzare (include TVA dacă firma e plătitoare) | C10: 249 | G10: € | H10: Plan: preț de la €249 (Planul de bani Micul Șmecher) | I10: input
A11: vat_rate | B11: Cotă TVA România | C11: 0.21 | G11: % | H11: Vault BOM.csv P0-17: TVA import 21 % | I11: vault
A12: vat_threshold_lei | B12: Plafon de scutire TVA (cifra de afaceri anuală) | C12: 395000 | G12: lei | H12: [de verificat cu contabilul] 395.000 lei (art. 310 Cod fiscal, din 1.09.2025, după cunoștințele mele; nu am verificat în această rundă). Sub plafon ARTEMIS nu recuperează TVA → TVA = cost real pe achiziții (aplicat automat). | I12: [estimare]
A13: el_route | B13: Arhitectura electronică: 1 = PCB propriu (ESP32-S3-WROOM-1 + panou AMOLED 1,75″), 2 = placă Waveshare ESP32-S3-Touch-AMOLED-1.75 | C13: 2 | D13: 1 | E13: 1 | F13: 1 | G13: cod | H13: 02-MANUFACTURING §11: PCB custom de la ~1k buc. La 100 buc. NRE-ul PCB (~$15–30k) nu se justifică → placa Waveshare [estimare]. Atenție: cu placa Waveshare corpul e S-P0 (25,65 mm, 500 mAh; docs/12 §2.3), nu produsul de 23 mm | I13: [estimare]
A14: pcba_sel | B14: Referință PCBA externalizat: 1 = JLCPCB (Asia), 2 = EMS România | C14: 2 | G14: cod | H14: Lanțul recomandat în cercetare (15.10.2026): Felix EMS / EMS-Electra fac PCBA + box build + flash/test. JLCPCB = cel mai ieftin reper public. | I14: input
A15: days | B15: Zile lucrătoare pe an | C15: 220 | G15: zile | H15: Cercetare T1 (15.10.2026): 220 zile/an | I15: [estimare]
A16: shift_h | B16: Ore pe schimb | C16: 8 | G16: h | H16: Standard | I16: input
A17: oee | B17: Eficiență (timp productiv din schimb) | C17: 0.85 | G17: % | H17: Cercetare T1: ~408 min productive / schimb (85 %) | I17: [estimare]
A18: shift_min | B18: Minute productive pe schimb | C18: =Ipoteze!$C$16*60*Ipoteze!$C$17 -> 408 | G18: min | H18: Formulă | I18: calcul
A19: hours_fte | B19: Ore productive pe an per normă întreagă (FTE) | C19: =Ipoteze!$C$15*Ipoteze!$C$16*Ipoteze!$C$17 -> 1496 | G19: h | H19: Formulă | I19: calcul
A20: max_shifts | B20: Număr maxim de schimburi pe utilaj | C20: 2 | G20: schimburi | H20: Cercetare: T1 se justifică pe 2 schimburi; al 3-lea schimb nemodelat | I20: [estimare]
A21: target_util | B21: Utilizare țintă a stațiilor (rezervă pentru opriri) | C21: 0.8 | G21: % | H21: [estimare] | I21: [estimare]
A22: batches | B22: Loturi de producție pe an | C22: 1 | D22: 4 | E22: 8 | F22: 12 | G22: loturi | H22: [estimare] 1 lot la pilot, apoi trimestrial → lunar | I22: [estimare]
A23: colours | B23: Culori de anodizare active | C23: 2 | D23: 5 | E23: 5 | F23: 5 | G23: culori | H23: 02-MANUFACTURING §3: Founders = argint + grafit; 5 culori ulterior | I23: vault
A24: thr_vol | B24: Volum de la care atelierul are laser, dulap Li-ion și raft de rodaj proprii | C24: 500 | G24: unit./an | H24: [estimare] sub prag: marcare la furnizor/FabLab | I24: [estimare]
A26: 2. BOM per unitate, mărimea S (AMOLED 1,75″ 466×466, 63×70,8×23 mm; docs/size-s.json)
A27: display_usd | B27: Panou rotund AMOLED 1,75" 466×466 CO5300 (QSPI) + touch on-cell | C27: 17 | D27: 10 | E27: 9.5 | F27: 9 | G27: $/buc | H27: docs/12 §1.2: Tailor-Pixels TOH175XRT-02CG $9–17 la eșantion (https://tailorpixels.com/product/1-75-inch-amoled-round-on-cell-touch-466x466-mipi-qspi/, 20.10.2026); docs/12 §3.1 folosește $10 la 1.000; MOQ doar prin RFQ (NoseDisplay, Lianxun) [estimare] | I27: [estimare]
A28: mcu_usd | B28: Modul ESP32-S3-WROOM-1-N16R8 | C28: 4.6 | D28: 3.46 | E28: 3.4 | F28: 3.3 | G28: $/buc | H28: LCSC C2913202: ~$5,16–5,54 @1, ~$3,46 @650+, ~$3,40 @1.300+ (https://www.lcsc.com/product-detail/WiFi-Modules_Espressif-Systems-ESP32-S3-WROOM-1-N16R8_C2913202.html, 15.10.2026); 100 și 20k [estimare] | I28: listare
A29: other_el_usd | B29: Restul componentelor PCB (PMIC, IMU, codec+amp, 2 mic MEMS, USB-C, pogo, ~120 pasive) | C29: 7 | D29: 5 | E29: 4.2 | F29: 3.6 | G29: $/buc | H29: [estimare] nu există încă BOM pentru PCB-ul custom | I29: [estimare]
A30: pcb_bare_usd | B30: PCB gol 4 straturi rotund ~Ø46 mm | C30: 1.6 | D30: 0.8 | E30: 0.56 | F30: 0.44 | G30: $/buc | H30: [estimare] docs/12 §3.1: $0,8 la 1.000 (M: $1,0); reper prototip AISLER 14 € + 0,13 €/cm² (vault) | I30: [estimare]
A31: ws_board_usd | B31: Placă Waveshare ESP32-S3-Touch-AMOLED-1.75 (doar la arhitectura 2; are 2 microfoane, ES7210 + ES8311, difuzor în kit) | C31: 29.99 | G31: $/buc | H31: docs/12 §1.1: $29,99–39,99 pe waveshare.com, verificat 20.10.2026 (https://www.waveshare.com/esp32-s3-touch-amoled-1.75.htm); split pe variante nepublicat | I31: vault
A32: mic_lei | B32: Microfon extern (arhitectura 2) — la S nu trebuie: placa AMOLED-1.75 are 2 microfoane | C32: 0 | G32: lei cu TVA | H32: docs/12 §1.1 [V]; la M era INMP441, Bitmi 20,99 lei | I32: vault
A33: amp_lei | B33: Amplificator extern (arhitectura 2) — la S nu trebuie: codecul ES8311 e pe placă | C33: 0 | G33: lei cu TVA | H33: docs/12 §1.1 [V]; la M era MAX98357A, Robofun 44,18 lei | I33: vault
A34: battery_usd | B34: Celulă LiPo 603040 750 mAh cu PCM (la 100 buc. cu placa Waveshare: 503035 500 mAh, S-P0) | C34: 3.45 | D34: 1.5 | E34: 1.4 | F34: 1.35 | G34: $/buc | H34: docs/12 §3.1: 503035 ≈ 3,00 € la 100 (S-P0); 603040 $1,5 la 1.000 [estimare]; listarea A&S Power 603040 750 mAh (HKTDC). Cere UN38.3 + IEC 62133. | I34: [estimare]
A35: speaker_eur | B35: Difuzor 15×11 mm (la 100 buc.: difuzorul din kitul plăcii Waveshare) | C35: 0 | D35: 0.8 | E35: 0.6 | F35: 0.5 | G35: €/buc | H35: docs/12 §3.1: la 100 fără difuzor separat (kit); volume mari [estimare] | I35: [estimare]
A36: glass_usd | B36: Sticlă frontală plată Ø52, 2.5D, întărită chimic, print negru | C36: 6 | D36: 2.2 | E36: 1.4 | F36: 0.9 | G36: $/buc | H36: docs/12 §3.1: × ~0,75 față de M (Ø74 → Ø52, setup dominant). Felix Glass $2,88–8,11; Hengping $0,60–1,90 @MOQ 100; Saida $0,20–3,00 @MOQ 100 (https://saidaglass.en.made-in-china.com/product/ZdbJyzMDEYWm/, listări 2–2,5 ani) — ales în interval [estimare] | I36: [estimare]
A37: mech_eur | B37: Mecanice mici (șuruburi, magneți, spumă, monedă PCB contacte) | C37: 3.5 | D37: 2 | E37: 1.5 | F37: 1.25 | G37: €/buc | H37: [estimare] docs/12 §3.1 (−0,5 € față de M); BOM.csv @25 ≈ 4,9 € | I37: [estimare]
A38: cable_eur | B38: Cablu USB-C | C38: 2.2 | D38: 1.2 | E38: 0.9 | F38: 0.8 | G38: €/buc | H38: [estimare] BOM.csv P0-15: 2,5 € @25 | I38: [estimare]
A39: chassis_eur | B39: Șasiu + bază/picior din polimer | C39: 4.5 | D39: 2.6 | E39: 1.1 | F39: 0.6 | G39: €/buc | H39: [estimare] docs/12 §3.1: 4,5 € @100, 2,6 € @1.000 (M: 6 / 3,5); BOM.csv P0-10 | I39: [estimare]
A40: ou_eur | B40: Oul OU (carcasă + electronică de încărcare) | C40: 15 | D40: 10 | E40: 6.7 | F40: 5 | G40: €/buc | H40: [estimare] docs/12 §3.1: 15 € @100, 10 € @1.000 (M: 18 / 12); BOM P0-13/14: 33 € @25 (SLA); 02-MANUFACTURING §9: $8–12 la 10k | I40: [estimare]
A41: pack_eur | B41: Ambalaj (cutie rigidă, certificat, ghid, etichetă) | C41: 9 | D41: 5 | E41: 3 | F41: 2.2 | G41: €/buc | H41: [estimare] docs/12 §3.1: 9 € @100, 5 € @1.000 (cutie mai mică); BOM P0-16 8 € + F-03/F-04 2 € @25; Web2Print București de la 25 buc., preț la cerere | I41: [estimare]
A42: freight_pct | B42: Transport din Asia (% din valoarea mărfii) | C42: 0.1 | D42: 0.06 | E42: 0.04 | F42: 0.03 | G42: % | H42: [estimare] BOM P0-17: DHL ~$14/kg; la volum maritim/feroviar | I42: [estimare]
A43: duty_el_pct | B43: Taxă vamală medie componente electronice | C43: 0.02 | G43: % | H43: [estimare] multe componente au 0 % | I43: [estimare]
A44: duty_shell_pct | B44: Taxă vamală carcase aluminiu | C44: 0.06 | G44: % | H44: 02-MANUFACTURING §2 / BOM P0-17: ~6 % (HS 7616/8529 după broker; risc antidumping 7616 99 90) | I44: vault
A46: 3. Procese externalizate (scenariul A și reperele de comparație)
A47: jlc_setup_usd | B47: JLCPCB taxă setup PCBA (Standard, două fețe) | C47: 51.12 | G47: $/lot | H47: https://jlcpcb.com/help/article/pcb-assembly-price (15.10.2026) | I47: oficial
A48: jlc_stencil_usd | B48: JLCPCB stencil | C48: 8.21 | G48: $/lot | H48: idem | I48: oficial
A49: jlc_feeder_usd | B49: JLCPCB taxă feeder per piesă „extended” | C49: 3.07 | G49: $/piesă/lot | H49: idem (Economic; aplicat și la Standard [estimare]) | I49: oficial
A50: ext_parts | B50: Piese „extended” distincte pe placă | C50: 10 | G50: buc | H50: [estimare] | I50: [estimare]
A51: joints | B51: Puncte de lipire pe placă | C51: 400 | G51: puncte | H51: [estimare] ~150 componente | I51: [estimare]
A52: comps | B52: Componente plasate pe placă | C52: 150 | G52: buc | H52: [estimare] cercetare T2: 150–250 | I52: [estimare]
A53: jlc_joint_usd | B53: JLCPCB preț per punct de lipire | C53: 0.0016 | D53: 0.0016 | E53: 0.0014 | F53: 0.0012 | G53: $/punct | H53: JLCPCB: $0,0016/punct, Standard scade până la $0,0012 (tierul exact [estimare]) | I53: oficial
A54: ems_pcba_eur | B54: EMS România: asamblare PCBA per placă (fără componente) | C54: 12 | D54: 4 | E54: 2.5 | F54: 1.8 | G54: €/placă | H54: [estimare] Felix EMS / EMS-Electra / ICCO nu publică prețuri; o ofertă UE de 6 plăci = €312,81 (forum, cercetare). Cere RFQ cu Gerber+BOM+CPL. | I54: [estimare]
A55: cnc_buy_eur | B55: Prelucrare CNC set S (față + spate), externalizat, fără finisaj | C55: 55 | D55: 23 | E55: 17.5 | F55: 14.3 | G55: €/set | H55: [estimare] = valorile M (85 / 35 / 27 / 22) × 0,65, factorul carcasei S externe din docs/12 §3.1 (suprafață × 0,50, semifabricat × 0,40, taxe fixe); Vault: S @25 = 92 €/set cu finisaj (BOM P0-12); 1k China $25–45/set pentru S (02-MANUFACTURING §11); curba PREMSA 6061 ~100×70×40: $118 @1 / $61 @25 / $54 @100 (https://premsaindustries.com/en/aluminum-machining). La ≥10k dosarul trece pe ambutisare 5052 (nemodelat). | I55: [estimare]
A56: blast_buy_eur | B56: Sablare externalizată (glass bead) per set S | C56: 1.3 | D56: 1 | E56: 0.8 | F56: 0.65 | G56: €/set | H56: [estimare] M × 0,65 (docs/12 §3.1) | I56: [estimare]
A57: anod_base_eur | B57: Anodizare tip II colorată + sigilare, per set S (fără taxa de lot) | C57: 3.25 | D57: 2.6 | E57: 2.3 | F57: 1.95 | G57: €/set | H57: [estimare] M (5 / 4 / 3,5 / 3) × 0,65 (docs/12 §3.1); Anorom/Alvi/ARSAT nu publică prețuri | I57: [estimare]
A58: anod_lot_usd | B58: Taxă minimă per lot de anodizare (per culoare) | C58: 100 | G58: $/lot | H58: Regulă din industrie: minim ≥$100 per lot (cercetare 15.10.2026) [estimare] | I58: [estimare]
A59: golden_eur | B59: Golden sample per culoare | C59: 100 | G59: €/culoare | H59: Vault BOM B-11: 100 € [E] | I59: [estimare]
A60: laser_buy_eur | B60: Marcare laser externalizată (serie + CE/WEEE) | C60: 2 | D60: 1.2 | E60: 0.8 | F60: 0.6 | G60: €/buc | H60: Vault BOM F-01: 2 € @25 [E]; FabLab Jilava 0,20 €/cm² (vault) | I60: [estimare]
A61: transport_anod_eur | B61: Transport intern la anodizator RO și retur (scenariile C, D) | C61: 0.5 | G61: €/set | H61: [estimare] | I61: [estimare]
A62: bb_eur | B62: EMS România: box build (asamblare + flash + test funcțional + ambalare) | C62: 15 | D62: 10 | E62: 8 | F62: 7 | G62: €/buc | H62: [estimare] ~20–30 min la ~20–25 €/h; fără preț public. RFQ: Felix EMS (office@felix-ems.ro), EMS-Electra (office@ems-electra.ro) | I62: [estimare]
A63: a_int_min | B63: Scenariul A: minute interne per unitate (QC final + ambalare/expediere) | C63: 5 | G63: min | H63: [estimare] | I63: [estimare]
A65: 4. Atelier T0: asamblare, flash, calibrare, test, QC, ambalare
A66: asm_min | B66: Manoperă internă per unitate (toți pașii manuali) | C66: 45 | D66: 25 | E66: 20 | F66: 15 | G66: min/unit. | H66: 02-MANUFACTURING §6: ~45 min în serie la început; cercetare: 15–25 min cu fixturi [estimare] | I66: [estimare]
A67: test_min | B67: Ciclu jig de test funcțional | C67: 4 | G67: min | H67: [estimare] cercetare: 3–5 min | I67: [estimare]
A68: flash_min | B68: Ciclu flash (per port) | C68: 2 | G68: min | H68: [estimare]; Espressif Flash Download Tool mod Factory, multi-canal (https://docs.espressif.com/projects/esp-test-tools/en/latest/esp8266/production_stage/tools/flash_download_tool.html) | I68: [estimare]
A69: flash_ports | B69: Porturi flash în paralel | C69: 4 | G69: porturi | H69: [estimare] 4–8 porturi | I69: [estimare]
A70: burnin_min | B70: Rodaj (burn-in) per unitate | C70: 10 | G70: min | H70: 02-MANUFACTURING §7: 10 min demo fără reboot | I70: vault
A71: burnin_slots | B71: Locuri pe raftul de rodaj | C71: 20 | G71: locuri | H71: [estimare] | I71: [estimare]
A72: laser_min | B72: Ciclu marcare laser | C72: 1 | G72: min | H72: [estimare] cercetare: 30–90 s | I72: [estimare]
A73: scrap_base | B73: Rebut / rezervă pe materiale cumpărate | C73: 0.03 | G73: % | H73: [estimare] vault folosește +10 % la 25 buc.; la serie 3 % | I73: [estimare]
A74: qc_tech | B74: Tehnician QC/test (normă) | C74: 0 | D74: 0 | E74: 1 | F74: 1 | G74: FTE | H74: [estimare] cercetare: la 10k/an 2–3 operatori + 1 QC | I74: [estimare]
A75: warehouse_n | B75: Gestionar/logistică (normă) | C75: 0 | D75: 0 | E75: 0 | F75: 1 | G75: FTE | H75: [estimare] | I75: [estimare]
A76: space_B | B76: Suprafață atelier T0 (incl. stoc) | C76: 0 | D76: 60 | E76: 150 | F76: 300 | G76: m² | H76: Cercetare: T0 40–60 m²; faza 2 ~200 m² pentru 5–6k/an; pilotul pe bancul fondatorului, fără hală [estimare] | I76: [estimare]
A77: kwh_B | B77: Consum electric atelier T0 | C77: 0 | D77: 1000 | E77: 2000 | F77: 3000 | G77: kWh/lună | H77: Cercetare: 1.000–3.000 kWh/lună [estimare] | I77: [estimare]
A78: bench_eur | B78: Banc de lucru ESD (Treston Concept Ergo) | C78: 2495 | G78: €/buc | H78: €1.595–3.395 (https://www.wrepair.com/product/esd-workstation-180x75cm/) — mijlocul intervalului | I78: listare
A79: jig_dev_usd | B79: Jig de test pogo Fixturfab Dev Pro (sub prag) | C79: 1799 | G79: $ | H79: https://fixturfab.com/fixtures (15.10.2026) | I79: listare
A80: jig_prod_usd | B80: Jig de test pogo Fixturfab Production (peste prag) | C80: 7399 | G80: $ | H80: idem | I80: listare
A81: flash_eur | B81: Stație flash (hub USB + cabluri + jig) | C81: 300 | G81: € | H81: [estimare] software Espressif gratuit | I81: [estimare]
A82: laser_eur | B82: Laser fibră MOPA Gweike G6 | C82: 4469 | G82: € | H82: https://shop.gweikecloud.com/products/g6-mopa-30w-60w-100w-fiber-laser-marking-engraving-machine | I82: listare
A83: liion_cab_eur | B83: Dulap Li-ion tip 90 Düperthal XL | C83: 4660 | G83: € | H83: https://www.lion-care.com/en/Dueperthal-BATTERY-standard-line-XL-storage-cabinet/DUPSHSBLSXL1 (fără TVA) | I83: listare
A84: liion_small_eur | B84: Container ignifug mic pentru celule (sub prag) | C84: 400 | G84: € | H84: [estimare] | I84: [estimare]
A85: burnin_eur | B85: Raft de rodaj + surse USB | C85: 1000 | G85: € | H85: [estimare] | I85: [estimare]
A86: tools_base_eur | B86: Scule, IT, imprimantă etichete, cântar 0,1 g | C86: 1500 | G86: € | H86: [estimare] | I86: [estimare]
A87: tools_bench_eur | B87: Accesorii ESD + scule per banc | C87: 500 | G87: €/banc | H87: Kit ESD 386–702 lei (https://www.electronic-mag.ro/statii-de-lucru-esd/19582-...) + brățări, ionizator [estimare] | I87: [estimare]
A88: setup_eur | B88: Înființare (autorizație mediu + consultant, dosar SSM/PSI) | C88: 1500 | G88: € | H88: Autorizație mediu 500 lei (Ord. 1108/2007), SSM 450 lei/funcție + PSI 500 lei (ZOTAS); restul consultant [estimare] | I88: [estimare]
A89: dep_light | B89: Amortizare echipamente ușoare (T0) | C89: 3 | G89: ani | H89: [estimare] | I89: [estimare]
A90: dep_heavy | B90: Amortizare utilaje (CNC, SMT) | C90: 5 | G90: ani | H90: [estimare] cercetare: 5 ani | I90: [estimare]
A92: 5. Personal și spațiu
A93: sal_op_lei | B93: Salariu operator asamblare (brut) | C93: 4500 | G93: lei/lună | H93: Paylab 4.050–6.785; minim 4.325 brut din 1.07.2026 (HG 146/2026) | I93: listare
A94: sal_tech_lei | B94: Salariu tehnician electronică / QC / SMT (brut) | C94: 6500 | G94: lei/lună | H94: WageIndicator 2026: 5.303–7.714 brut | I94: listare
A95: sal_prog_lei | B95: Salariu programator CNC (brut), primul operator CNC | C95: 10800 | G95: lei/lună | H95: [estimare] Indeed: de la 6.500 net → ~10.500–11.100 brut | I95: [estimare]
A96: sal_cncop_lei | B96: Salariu operator CNC (brut) | C96: 6000 | G96: lei/lună | H96: meseriile.ro / Jooble București 2026: ~4.000–7.000 | I96: listare
A97: sal_wh_lei | B97: Salariu gestionar depozit | C97: 4150 | G97: lei/lună | H97: OLX Sector 4 (30.09.2026): 4.000–4.300 | I97: listare
A98: cam_rate | B98: Contribuția asiguratorie pentru muncă (angajator) | C98: 0.0225 | G98: % | H98: [de verificat] CAM 2,25 % (Cod fiscal art. 220^1) | I98: [estimare]
A99: rent_m2 | B99: Chirie spațiu mic de producție | C99: 6 | G99: €/m²/lună | H99: [estimare] cercetare 6–8 €/m²; publi24 Ilfov 13–15.10.2026: 3,5–8,5 €/m² (https://www.publi24.ro/anunturi/imobiliare/de-inchiriat/spatii-comerciale/hala-industriala/ilfov/) | I99: [estimare]
A100: service_m2 | B100: Servicii / mentenanță spațiu | C100: 0.7 | G100: €/m²/lună | H100: [estimare] 0,5–0,9 €/m² | I100: [estimare]
A101: elec_lei_kwh | B101: Energie electrică all-in (fără TVA) | C101: 1.4 | G101: lei/kWh | H101: [estimare] 1,2–1,6; POSF 792,93 lei/MWh doar energie, S1 2026 (https://posf.ro/comparator/files/furnizori/1767174801Oferta-noncasnici-Business-Stabil-01.01.2026.pdf) | I101: [estimare]
A103: 6. Permise, asigurări, SSM
A104: ins_A | B104: Asigurări scenariul A (RC produs) | C104: 1000 | G104: €/an | H104: [estimare] 500–2.000 €/an; doar Groupama RC generală de la €160/an (2022) | I104: [estimare]
A105: ins_B | B105: Asigurări scenariile B–D (RC produs + bunuri) | C105: 1500 | G105: €/an | H105: [estimare] | I105: [estimare]
A106: epr_fixed | B106: EPR: OIREP + declarații AFM (fix) | C106: 600 | G106: €/an | H106: [estimare] înregistrări ANMAP 2 × 500 lei (EEE + baterii) | I106: [estimare]
A107: env_visa_lei | B107: Viză anuală autorizație de mediu (CAEN 2640 e pe lista Ord. 1798/2007) | C107: 100 | G107: lei/an | H107: Ord. 1150/2020 art. 8(1) | I107: oficial
...

Sheet Scenarii
A1: SCENARII: cost per unitate, capex și costuri fixe (mărimea S, EUR fără TVA; TVA apare ca cost doar sub plafonul de scutire)
A2: A = totul externalizat (EMS face PCBA + box build, CNC + anodizare + sticlă la parteneri; noi QC final + ambalare). B = atelier T0 propriu (asamblare, flash, calibrare, test, QC, ambalare). C = B + celulă CNC proprie. D = C + linie SMT proprie. Anodizarea rămâne externă în toate.
A4: Cheie | B4: Linie | C4: =Ipoteze!C$9 -> 100 | D4: =Ipoteze!D$9 -> 1000 | E4: =Ipoteze!E$9 -> 5000 | F4: =Ipoteze!F$9 -> 20000 | G4: Explicație
A6: Comun tuturor scenariilor
A7: vol | B7: Volum | C7: =Ipoteze!C$9 -> 100 | D7: =Ipoteze!D$9 -> 1000 | E7: =Ipoteze!E$9 -> 5000 | F7: =Ipoteze!F$9 -> 20000
A8: route | B8: Arhitectura electronică (1 = PCB propriu, 2 = placă Waveshare) | C8: =Ipoteze!C$13 -> 2 | D8: =Ipoteze!D$13 -> 1 | E8: =Ipoteze!E$13 -> 1 | F8: =Ipoteze!F$13 -> 1
A9: turnover_lei | B9: Cifră de afaceri estimată | C9: =C7*Ipoteze!$C$10*Ipoteze!$C$7 -> 126990 | D9: =D7*Ipoteze!$C$10*Ipoteze!$C$7 -> 1269900 | E9: =E7*Ipoteze!$C$10*Ipoteze!$C$7 -> 6349500 | F9: =F7*Ipoteze!$C$10*Ipoteze!$C$7 -> 25398000
A10: vatflag | B10: Firma e plătitoare de TVA? (1 = da) | C10: =IF(C9>Ipoteze!$C$12,1,0) -> 0 | D10: =IF(D9>Ipoteze!$C$12,1,0) -> 1 | E10: =IF(E9>Ipoteze!$C$12,1,0) -> 1 | F10: =IF(F9>Ipoteze!$C$12,1,0) -> 1 | G10: peste plafon înregistrarea e obligatorie → TVA deductibil
A11: vatcost | B11: TVA nerecuperabil aplicat achizițiilor | C11: =Ipoteze!$C$11*(1-C10) -> 0.21 | D11: =Ipoteze!$C$11*(1-D10) -> 0 | E11: =Ipoteze!$C$11*(1-E10) -> 0 | F11: =Ipoteze!$C$11*(1-F10) -> 0
A12: hourly_op | B12: Cost operator per oră productivă | C12: =Ipoteze!$C$93*(1+Ipoteze!$C$98)*12/Ipoteze!$C$7/Ipoteze!$C$19 -> 7.2369456 | D12: =Ipoteze!$C$93*(1+Ipoteze!$C$98)*12/Ipoteze!$C$7/Ipoteze!$C$19 -> 7.2369456 | E12: =Ipoteze!$C$93*(1+Ipoteze!$C$98)*12/Ipoteze!$C$7/Ipoteze!$C$19 -> 7.2369456 | F12: =Ipoteze!$C$93*(1+Ipoteze!$C$98)*12/Ipoteze!$C$7/Ipoteze!$C$19 -> 7.2369456
A13: el_comp | B13: Electronică (panou + modul + componente + PCB gol, sau placa Waveshare AMOLED-1.75) | C13: =IF(C8=1,(Ipoteze!C$27+Ipoteze!C$28+Ipoteze!C$29+Ipoteze!C$30)*Ipoteze!$C$8,Ipoteze!$C$31*Ipoteze!$C$8+(Ipoteze!$C$32+Ipoteze!$C$33)/(1+Ipoteze!$C$11)/Ipoteze!$C$7) -> 26.0913 | D13: =IF(D8=1,(Ipoteze!D$27+Ipoteze!D$28+Ipoteze!D$29+Ipoteze!D$30)*Ipoteze!$C$8,Ipoteze!$C$31*Ipoteze!$C$8+(Ipoteze!$C$32+Ipoteze!$C$33)/(1+Ipoteze!$C$11)/Ipoteze!$C$7) -> 16.7562 | E13: =IF(E8=1,(Ipoteze!E$27+Ipoteze!E$28+Ipoteze!E$29+Ipoteze!E$30)*Ipoteze!$C$8,Ipoteze!$C$31*Ipoteze!$C$8+(Ipoteze!$C$32+Ipoteze!$C$33)/(1+Ipoteze!$C$11)/Ipoteze!$C$7) -> 15.3642 | F13: =IF(F8=1,(Ipoteze!F$27+Ipoteze!F$28+Ipoteze!F$29+Ipoteze!F$30)*Ipoteze!$C$8,Ipoteze!$C$31*Ipoteze!$C$8+(Ipoteze!$C$32+Ipoteze!$C$33)/(1+Ipoteze!$C$11)/Ipoteze!$C$7) -> 14.2158
A14: batt | B14: Baterie LiPo 750 mAh (500 mAh la S-P0) | C14: =Ipoteze!C$34*Ipoteze!$C$8 -> 3.0015 | D14: =Ipoteze!D$34*Ipoteze!$C$8 -> 1.305 | E14: =Ipoteze!E$34*Ipoteze!$C$8 -> 1.218 | F14: =Ipoteze!F$34*Ipoteze!$C$8 -> 1.1745
A15: glass | B15: Sticlă frontală 2.5D | C15: =Ipoteze!C$36*Ipoteze!$C$8 -> 5.22 | D15: =Ipoteze!D$36*Ipoteze!$C$8 -> 1.914 | E15: =Ipoteze!E$36*Ipoteze!$C$8 -> 1.218 | F15: =Ipoteze!F$36*Ipoteze!$C$8 -> 0.783
A16: small | B16: Difuzor + mecanice mici + cablu | C16: =Ipoteze!C$35+Ipoteze!C$37+Ipoteze!C$38 -> 5.7 | D16: =Ipoteze!D$35+Ipoteze!D$37+Ipoteze!D$38 -> 4 | E16: =Ipoteze!E$35+Ipoteze!E$37+Ipoteze!E$38 -> 3 | F16: =Ipoteze!F$35+Ipoteze!F$37+Ipoteze!F$38 -> 2.55
A17: imp_el | B17: Subtotal piese importate | C17: =C13+C14+C15+C16 -> 40.0128 | D17: =D13+D14+D15+D16 -> 23.9752 | E17: =E13+E14+E15+E16 -> 20.8002 | F17: =F13+F14+F15+F16 -> 18.7233
A18: log_el | B18: Transport + taxă vamală piese importate | C18: =C17*((1+Ipoteze!C$42)*(1+Ipoteze!$C$43)-1) -> 4.8815616 | D18: =D17*((1+Ipoteze!D$42)*(1+Ipoteze!$C$43)-1) -> 1.9467862 | E18: =E17*((1+Ipoteze!E$42)*(1+Ipoteze!$C$43)-1) -> 1.2646522 | F18: =F17*((1+Ipoteze!F$42)*(1+Ipoteze!$C$43)-1) -> 0.94739898
A19: local | B19: Piese locale (OU, ambalaj, șasiu/bază) | C19: =Ipoteze!C$40+Ipoteze!C$41+Ipoteze!C$39 -> 28.5 | D19: =Ipoteze!D$40+Ipoteze!D$41+Ipoteze!D$39 -> 17.6 | E19: =Ipoteze!E$40+Ipoteze!E$41+Ipoteze!E$39 -> 10.8 | F19: =Ipoteze!F$40+Ipoteze!F$41+Ipoteze!F$39 -> 7.8
A20: bom | B20: BOM total livrat (fără carcasă Al și fără manoperă) | C20: =C17+C18+C19 -> 73.394362 | D20: =D17+D18+D19 -> 43.521986 | E20: =E17+E18+E19 -> 32.864852 | F20: =F17+F18+F19 -> 27.470699
A21: pcba_jlc | B21: PCBA la JLCPCB per placă (manoperă + setup/lot, livrat) | C21: =IF(C8=1,(Ipoteze!$C$51*Ipoteze!C$53+(Ipoteze!$C$47+Ipoteze!$C$48+Ipoteze!$C$49*Ipoteze!$C$50)*Ipoteze!C$22/C7)*Ipoteze!$C$8*(1+Ipoteze!C$42)*(1+Ipoteze!$C$43),0) -> 0 | D21: =IF(D8=1,(Ipoteze!$C$51*Ipoteze!D$53+(Ipoteze!$C$47+Ipoteze!$C$48+Ipoteze!$C$49*Ipoteze!$C$50)*Ipoteze!D$22/D7)*Ipoteze!$C$8*(1+Ipoteze!D$42)*(1+Ipoteze!$C$43),0) -> 0.94075688 | E21: =IF(E8=1,(Ipoteze!$C$51*Ipoteze!E$53+(Ipoteze!$C$47+Ipoteze!$C$48+Ipoteze!$C$49*Ipoteze!$C$50)*Ipoteze!E$22/E7)*Ipoteze!$C$8*(1+Ipoteze!E$42)*(1+Ipoteze!$C$43),0) -> 0.64976308 | F21: =IF(F8=1,(Ipoteze!$C$51*Ipoteze!F$53+(Ipoteze!$C$47+Ipoteze!$C$48+Ipoteze!$C$49*Ipoteze!$C$50)*Ipoteze!F$22/F7)*Ipoteze!$C$8*(1+Ipoteze!F$42)*(1+Ipoteze!$C$43),0) -> 0.4881042
A22: pcba_ems | B22: PCBA la EMS România per placă | C22: =IF(C8=1,Ipoteze!C$54,0) -> 0 | D22: =IF(D8=1,Ipoteze!D$54,0) -> 4 | E22: =IF(E8=1,Ipoteze!E$54,0) -> 2.5 | F22: =IF(F8=1,Ipoteze!F$54,0) -> 1.8
A23: pcba_buy | B23: PCBA externalizat folosit (după selector) | C23: =IF(Ipoteze!$C$14=1,C21,C22) -> 0 | D23: =IF(Ipoteze!$C$14=1,D21,D22) -> 4 | E23: =IF(Ipoteze!$C$14=1,E21,E22) -> 2.5 | F23: =IF(Ipoteze!$C$14=1,F21,F22) -> 1.8
A24: anod_set | B24: Anodizare per set (bază + taxe de lot × culori × loturi / volum) | C24: =Ipoteze!C$57+Ipoteze!$C$58*Ipoteze!$C$8*Ipoteze!C$23*Ipoteze!C$22/C7 -> 4.99 | D24: =Ipoteze!D$57+Ipoteze!$C$58*Ipoteze!$C$8*Ipoteze!D$23*Ipoteze!D$22/D7 -> 4.34 | E24: =Ipoteze!E$57+Ipoteze!$C$58*Ipoteze!$C$8*Ipoteze!E$23*Ipoteze!E$22/E7 -> 2.996 | F24: =Ipoteze!F$57+Ipoteze!$C$58*Ipoteze!$C$8*Ipoteze!F$23*Ipoteze!F$22/F7 -> 2.211
A25: shell_buy | B25: Carcasă S externalizată (CNC + sablare + anodizare, livrată) | C25: =(Ipoteze!C$55+Ipoteze!C$56+C24)*(1+Ipoteze!C$42)*(1+Ipoteze!$C$44) -> 71.46414 | D25: =(Ipoteze!D$55+Ipoteze!D$56+D24)*(1+Ipoteze!D$42)*(1+Ipoteze!$C$44) -> 31.842824 | E25: =(Ipoteze!E$55+Ipoteze!E$56+E24)*(1+Ipoteze!E$42)*(1+Ipoteze!$C$44) -> 23.47671 | F25: =(Ipoteze!F$55+Ipoteze!F$56+F24)*(1+Ipoteze!F$42)*(1+Ipoteze!$C$44) -> 18.73638
A26: mat_eur_kg | B26: Aluminiu net de TVA | C26: =Ipoteze!$C$129/(1+Ipoteze!$C$11)/Ipoteze!$C$7 -> 6.7250041 | D26: =Ipoteze!$C$129/(1+Ipoteze!$C$11)/Ipoteze!$C$7 -> 6.7250041 | E26: =Ipoteze!$C$129/(1+Ipoteze!$C$11)/Ipoteze!$C$7 -> 6.7250041 | F26: =Ipoteze!$C$129/(1+Ipoteze!$C$11)/Ipoteze!$C$7 -> 6.7250041 | G26: €/kg
A27: shell_make_cnc | B27: CNC în casă: material + scule + energie + sablare, cu rebut | C27: =(Ipoteze!$C$127*C26+Ipoteze!$C$130+Ipoteze!$C$131*Ipoteze!$C$125/60*Ipoteze!$C$101/Ipoteze!$C$7+Ipoteze!$C$132)*(1+Ipoteze!$C$133) -> 5.0171488 | D27: =(Ipoteze!$C$127*D26+Ipoteze!$C$130+Ipoteze!$C$131*Ipoteze!$C$125/60*Ipoteze!$C$101/Ipoteze!$C$7+Ipoteze!$C$132)*(1+Ipoteze!$C$133) -> 5.0171488 | E27: =(Ipoteze!$C$127*E26+Ipoteze!$C$130+Ipoteze!$C$131*Ipoteze!$C$125/60*Ipoteze!$C$101/Ipoteze!$C$7+Ipoteze!$C$132)*(1+Ipoteze!$C$133) -> 5.0171488 | F27: =(Ipoteze!$C$127*F26+Ipoteze!$C$130+Ipoteze!$C$131*Ipoteze!$C$125/60*Ipoteze!$C$101/Ipoteze!$C$7+Ipoteze!$C$132)*(1+Ipoteze!$C$133) -> 5.0171488
A28: shell_make | B28: Carcasă S în casă: variabil (CNC propriu + anodizare RO + transport) | C28: =C27+C24+Ipoteze!$C$61 -> 10.507149 | D28: =D27+D24+Ipoteze!$C$61 -> 9.8571488 | E28: =E27+E24+Ipoteze!$C$61 -> 8.5131488 | F28: =F27+F24+Ipoteze!$C$61 -> 7.7281488
A29: board_val | B29: Valoarea componentelor de pe PCB (pentru pierderi SMT) | C29: =IF(C8=1,(Ipoteze!C$28+Ipoteze!C$29+Ipoteze!C$30)*Ipoteze!$C$8,0) -> 0 | D29: =IF(D8=1,(Ipoteze!D$28+Ipoteze!D$29+Ipoteze!D$30)*Ipoteze!$C$8,0) -> 8.0562 | E29: =IF(E8=1,(Ipoteze!E$28+Ipoteze!E$29+Ipoteze!E$30)*Ipoteze!$C$8,0) -> 7.0992 | F29: =IF(F8=1,(Ipoteze!F$28+Ipoteze!F$29+Ipoteze!F$30)*Ipoteze!$C$8,0) -> 6.3858
A30: smt_make | B30: SMT în casă: variabil per placă (consumabile + pierderi suplimentare) | C30: =IF(C8=1,Ipoteze!$C$151+(Ipoteze!$C$152-Ipoteze!$C$153)*C29,0) -> 0 | D30: =IF(D8=1,Ipoteze!$C$151+(Ipoteze!$C$152-Ipoteze!$C$153)*D29,0) -> 0.320843 | E30: =IF(E8=1,Ipoteze!$C$151+(Ipoteze!$C$152-Ipoteze!$C$153)*E29,0) -> 0.306488 | F30: =IF(F8=1,Ipoteze!$C$151+(Ipoteze!$C$152-Ipoteze!$C$153)*F29,0) -> 0.295787
A32: Capacitate și personal (calculat din volum)
A33: asm_h | B33: Ore de manoperă internă T0 pe an | C33: =C7*Ipoteze!C$66/60 -> 75 | D33: =D7*Ipoteze!D$66/60 -> 416.66667 | E33: =E7*Ipoteze!E$66/60 -> 1666.6667 | F33: =F7*Ipoteze!F$66/60 -> 5000
A34: asm_fte_raw | B34: Operatori asamblare necesari (FTE exact) | C34: =C33/Ipoteze!$C$19 -> 0.05013369 | D34: =D33/Ipoteze!$C$19 -> 0.2785205 | E34: =E33/Ipoteze!$C$19 -> 1.114082 | F34: =F33/Ipoteze!$C$19 -> 3.342246
A35: asm_fte | B35: Operatori plătiți (sub 0,5 = part-time/fondator plătit la oră; altfel rotunjit la 0,5) | C35: =IF(C34<0.5,C34,CEILING(C34,0.5)) -> 0.05013369 | D35: =IF(D34<0.5,D34,CEILING(D34,0.5)) -> 0.2785205 | E35: =IF(E34<0.5,E34,CEILING(E34,0.5)) -> 1.5 | F35: =IF(F34<0.5,F34,CEILING(F34,0.5)) -> 3.5
A36: benches | B36: Bancuri ESD | C36: =MAX(1,CEILING(C34,1)) -> 1 | D36: =MAX(1,CEILING(D34,1)) -> 1 | E36: =MAX(1,CEILING(E34,1)) -> 2 | F36: =MAX(1,CEILING(F34,1)) -> 4
A37: jigs | B37: Jig-uri de test | C37: =MAX(1,CEILING(C7*Ipoteze!$C$67/60/Ipoteze!$C$19/Ipoteze!$C$21,1)) -> 1 | D37: =MAX(1,CEILING(D7*Ipoteze!$C$67/60/Ipoteze!$C$19/Ipoteze!$C$21,1)) -> 1 | E37: =MAX(1,CEILING(E7*Ipoteze!$C$67/60/Ipoteze!$C$19/Ipoteze!$C$21,1)) -> 1 | F37: =MAX(1,CEILING(F7*Ipoteze!$C$67/60/Ipoteze!$C$19/Ipoteze!$C$21,1)) -> 2
A38: hc_B | B38: Angajați T0 (număr de persoane) | C38: =CEILING(C35,1)+Ipoteze!C$74+Ipoteze!C$75 -> 1 | D38: =CEILING(D35,1)+Ipoteze!D$74+Ipoteze!D$75 -> 1 | E38: =CEILING(E35,1)+Ipoteze!E$74+Ipoteze!E$75 -> 3 | F38: =CEILING(F35,1)+Ipoteze!F$74+Ipoteze!F$75 -> 6
A39: jig_price | B39: Preț jig de test | C39: =IF(C7<Ipoteze!$C$24,Ipoteze!$C$79,Ipoteze!$C$80)*Ipoteze!$C$8 -> 1565.13 | D39: =IF(D7<Ipoteze!$C$24,Ipoteze!$C$79,Ipoteze!$C$80)*Ipoteze!$C$8 -> 6437.13 | E39: =IF(E7<Ipoteze!$C$24,Ipoteze!$C$79,Ipoteze!$C$80)*Ipoteze!$C$8 -> 6437.13 | F39: =IF(F7<Ipoteze!$C$24,Ipoteze!$C$79,Ipoteze!$C$80)*Ipoteze!$C$8 -> 6437.13
A40: golden | B40: Golden samples (per culoare) | C40: =Ipoteze!C$23*Ipoteze!$C$59 -> 200 | D40: =Ipoteze!D$23*Ipoteze!$C$59 -> 500 | E40: =Ipoteze!E$23*Ipoteze!$C$59 -> 500 | F40: =Ipoteze!F$23*Ipoteze!$C$59 -> 500
A41: cnc_cap | B41: Capacitate CNC: seturi S / mașină / schimb / an | C41: =Ipoteze!$C$18/Ipoteze!$C$125*Ipoteze!$C$15 -> 3740 | D41: =Ipoteze!$C$18/Ipoteze!$C$125*Ipoteze!$C$15 -> 3740 | E41: =Ipoteze!$C$18/Ipoteze!$C$125*Ipoteze!$C$15 -> 3740 | F41: =Ipoteze!$C$18/Ipoteze!$C$125*Ipoteze!$C$15 -> 3740
A42: cnc_m | B42: Mașini CNC necesare | C42: =CEILING(C7/(C41*Ipoteze!$C$20),1) -> 1 | D42: =CEILING(D7/(D41*Ipoteze!$C$20),1) -> 1 | E42: =CEILING(E7/(E41*Ipoteze!$C$20),1) -> 1 | F42: =CEILING(F7/(F41*Ipoteze!$C$20),1) -> 3
A43: cnc_sh | B43: Schimburi CNC | C43: =MIN(Ipoteze!$C$20,CEILING(C7/(C41*C42),1)) -> 1 | D43: =MIN(Ipoteze!$C$20,CEILING(D7/(D41*D42),1)) -> 1 | E43: =MIN(Ipoteze!$C$20,CEILING(E7/(E41*E42),1)) -> 2 | F43: =MIN(Ipoteze!$C$20,CEILING(F7/(F41*F42),1)) -> 2
A44: cnc_ops | B44: Operatori CNC (primul = programator) | C44: =C43*CEILING(C42/Ipoteze!$C$137,1) -> 1 | D44: =D43*CEILING(D42/Ipoteze!$C$137,1) -> 1 | E44: =E43*CEILING(E42/Ipoteze!$C$137,1) -> 2 | F44: =F43*CEILING(F42/Ipoteze!$C$137,1) -> 4
A45: cnc_util | B45: Utilizare CNC | C45: =C7/(C41*C42*C43) -> 0.026737968 | D45: =D7/(D41*D42*D43) -> 0.26737968 | E45: =E7/(E41*E42*E43) -> 0.6684492 | F45: =F7/(F41*F42*F43) -> 0.8912656
A46: cnc_machine_eur | B46: Cost mașină CNC instalată | C46: =Ipoteze!$C$116*Ipoteze!$C$8*(1+Ipoteze!$C$117) -> 74118.78 | D46: =Ipoteze!$C$116*Ipoteze!$C$8*(1+Ipoteze!$C$117) -> 74118.78 | E46: =Ipoteze!$C$116*Ipoteze!$C$8*(1+Ipoteze!$C$117) -> 74118.78 | F46: =Ipoteze!$C$116*Ipoteze!$C$8*(1+Ipoteze!$C$117) -> 74118.78
A47: cnc_common | B47: Echipamente comune CNC (sablare, compresor, ultrasunete, instalare) | C47: =(Ipoteze!$C$119+Ipoteze!$C$120)/Ipoteze!$C$7+Ipoteze!$C$121+Ipoteze!$C$122 -> 12576.078 | D47: =(Ipoteze!$C$119+Ipoteze!$C$120)/Ipoteze!$C$7+Ipoteze!$C$121+Ipoteze!$C$122 -> 12576.078 | E47: =(Ipoteze!$C$119+Ipoteze!$C$120)/Ipoteze!$C$7+Ipoteze!$C$121+Ipoteze!$C$122 -> 12576.078 | F47: =(Ipoteze!$C$119+Ipoteze!$C$120)/Ipoteze!$C$7+Ipoteze!$C$121+Ipoteze!$C$122 -> 12576.078
A48: cnc_capex | B48: Capex celulă CNC (net) | C48: =C42*(C46+Ipoteze!$C$118)+C47 -> 104194.86 | D48: =D42*(D46+Ipoteze!$C$118)+D47 -> 104194.86 | E48: =E42*(E46+Ipoteze!$C$118)+E47 -> 104194.86 | F48: =F42*(F46+Ipoteze!$C$118)+F47 -> 287432.42
A49: smt_cap | B49: Capacitate SMT: plăci / linie / schimb / an | C49: =Ipoteze!$C$18/(Ipoteze!$C$52/Ipoteze!$C$149*60+Ipoteze!$C$150)*Ipoteze!$C$15 -> 21892.683 | D49: =Ipoteze!$C$18/(Ipoteze!$C$52/Ipoteze!$C$149*60+Ipoteze!$C$150)*Ipoteze!$C$15 -> 21892.683 | E49: =Ipoteze!$C$18/(Ipoteze!$C$52/Ipoteze!$C$149*60+Ipoteze!$C$150)*Ipoteze!$C$15 -> 21892.683 | F49: =Ipoteze!$C$18/(Ipoteze!$C$52/Ipoteze!$C$149*60+Ipoteze!$C$150)*Ipoteze!$C$15 -> 21892.683
A50: smt_lines | B50: Linii SMT | C50: =IF(C8=1,CEILING(C7/(C49*Ipoteze!$C$20),1),1) -> 1 | D50: =IF(D8=1,CEILING(D7/(D49*Ipoteze!$C$20),1),1) -> 1 | E50: =IF(E8=1,CEILING(E7/(E49*Ipoteze!$C$20),1),1) -> 1 | F50: =IF(F8=1,CEILING(F7/(F49*Ipoteze!$C$20),1),1) -> 1
A51: smt_sh | B51: Schimburi SMT | C51: =IF(C8=1,MIN(Ipoteze!$C$20,CEILING(C7/(C49*C50),1)),1) -> 1 | D51: =IF(D8=1,MIN(Ipoteze!$C$20,CEILING(D7/(D49*D50),1)),1) -> 1 | E51: =IF(E8=1,MIN(Ipoteze!$C$20,CEILING(E7/(E49*E50),1)),1) -> 1 | F51: =IF(F8=1,MIN(Ipoteze!$C$20,CEILING(F7/(F49*F50),1)),1) -> 1
A52: smt_techs | B52: Tehnicieni SMT | C52: =C51*C50 -> 1 | D52: =D51*D50 -> 1 | E52: =E51*E50 -> 1 | F52: =F51*F50 -> 1
A53: smt_capex_line | B53: Capex per linie SMT (net) | C53: =Ipoteze!$C$142+Ipoteze!$C$143+(Ipoteze!$C$144+Ipoteze!$C$145)*Ipoteze!$C$8+Ipoteze!$C$146+Ipoteze!$C$147+Ipoteze!$C$148 -> 36470.42 | D53: =Ipoteze!$C$142+Ipoteze!$C$143+(Ipoteze!$C$144+Ipoteze!$C$145)*Ipoteze!$C$8+Ipoteze!$C$146+Ipoteze!$C$147+Ipoteze!$C$148 -> 36470.42 | E53: =Ipoteze!$C$142+Ipoteze!$C$143+(Ipoteze!$C$144+Ipoteze!$C$145)*Ipoteze!$C$8+Ipoteze!$C$146+Ipoteze!$C$147+Ipoteze!$C$148 -> 36470.42 | F53: =Ipoteze!$C$142+Ipoteze!$C$143+(Ipoteze!$C$144+Ipoteze!$C$145)*Ipoteze!$C$8+Ipoteze!$C$146+Ipoteze!$C$147+Ipoteze!$C$148 -> 36470.42
A54: smt_capex | B54: Capex SMT (net) | C54: =C50*C53 -> 36470.42 | D54: =D50*D53 -> 36470.42 | E54: =E50*E53 -> 36470.42 | F54: =F50*F53 -> 36470.42
A55: hc_C | B55: Angajați scenariul C | C55: =C38+C44 -> 2 | D55: =D38+D44 -> 2 | E55: =E38+E44 -> 5 | F55: =F38+F44 -> 10
A56: hc_D | B56: Angajați scenariul D | C56: =C55+C52 -> 3 | D56: =D55+D52 -> 3 | E56: =E55+E52 -> 6 | F56: =F55+F52 -> 11
A58: Scenariul A — totul externalizat (lanț de producție)
A59: A_capex | B59: CAPEX (jig de test predat la EMS + golden samples) | C59: =(C37*C39+C40)*(1+C11) -> 2135.8073 | D59: =(D37*D39+D40)*(1+D11) -> 6937.13 | E59: =(E37*E39+E40)*(1+E11) -> 6937.13 | F59: =(F37*F39+F40)*(1+F11) -> 13374.26
A60: A_rent | B60: Chirie + utilități | C60: =0 -> 0 | D60: =0 -> 0 | E60: =0 -> 0 | F60: =0 -> 0 | G60: fără hală: stocul stă la EMS / 3PL
A61: A_sal | B61: Salarii | C61: =0 -> 0 | D61: =0 -> 0 | E61: =0 -> 0 | F61: =0 -> 0 | G61: QC final plătit la oră, în costul variabil
A62: A_dep | B62: Amortizare | C62: =C59/Ipoteze!$C$89 -> 711.93577 | D62: =D59/Ipoteze!$C$89 -> 2312.3767 | E62: =E59/Ipoteze!$C$89 -> 2312.3767 | F62: =F59/Ipoteze!$C$89 -> 4458.0867
A63: A_perm | B63: Asigurări, EPR | C63: =Ipoteze!$C$104+Ipoteze!$C$106 -> 1600 | D63: =Ipoteze!$C$104+Ipoteze!$C$106 -> 1600 | E63: =Ipoteze!$C$104+Ipoteze!$C$106 -> 1600 | F63: =Ipoteze!$C$104+Ipoteze!$C$106 -> 1600
A64: A_fixed | B64: COSTURI FIXE / an | C64: =C60+C61+C62+C63 -> 2311.9358 | D64: =D60+D61+D62+D63 -> 3912.3767 | E64: =E60+E61+E62+E63 -> 3912.3767 | F64: =F60+F61+F62+F63 -> 6058.0867
A65: A_v_bom | B65: BOM livrat | C65: =C20 -> 73.394362 | D65: =D20 -> 43.521986 | E65: =E20 -> 32.864852 | F65: =F20 -> 27.470699
A66: A_v_pcba | B66: PCBA externalizat | C66: =C23 -> 0 | D66: =D23 -> 4 | E66: =E23 -> 2.5 | F66: =F23 -> 1.8
A67: A_v_shell | B67: Carcasă externalizată | C67: =C25 -> 71.46414 | D67: =D25 -> 31.842824 | E67: =E25 -> 23.47671 | F67: =F25 -> 18.73638
A68: A_v_laser | B68: Marcare laser la furnizor | C68: =Ipoteze!C$60 -> 2 | D68: =Ipoteze!D$60 -> 1.2 | E68: =Ipoteze!E$60 -> 0.8 | F68: =Ipoteze!F$60 -> 0.6
A69: A_v_bb | B69: Box build la EMS (asamblare + flash + test + ambalare) | C69: =Ipoteze!C$62 -> 15 | D69: =Ipoteze!D$62 -> 10 | E69: =Ipoteze!E$62 -> 8 | F69: =Ipoteze!F$62 -> 7
A70: A_v_lab | B70: QC final + expediere internă | C70: =Ipoteze!$C$63/60*C12 -> 0.6030788 | D70: =Ipoteze!$C$63/60*D12 -> 0.6030788 | E70: =Ipoteze!$C$63/60*E12 -> 0.6030788 | F70: =Ipoteze!$C$63/60*F12 -> 0.6030788
A71: A_scrap | B71: Rebut / rezervă | C71: =(C65+C66+C67)*Ipoteze!$C$73 -> 4.345755 | D71: =(D65+D66+D67)*Ipoteze!$C$73 -> 2.3809443 | E71: =(E65+E66+E67)*Ipoteze!$C$73 -> 1.7652469 | F71: =(F65+F66+F67)*Ipoteze!$C$73 -> 1.4402124
A72: A_vat | B72: TVA nerecuperabil pe achiziții (doar sub plafon) | C72: =(C65+C66+C67+C68+C69+C71)*C11 -> 34.902894 | D72: =(D65+D66+D67+D68+D69+D71)*D11 -> 0 | E72: =(E65+E66+E67+E68+E69+E71)*E11 -> 0 | F72: =(F65+F66+F67+F68+F69+F71)*F11 -> 0
A73: A_var | B73: COST VARIABIL / unitate | C73: =C65+C66+C67+C68+C69+C70+C71+C72 -> 201.71023 | D73: =D65+D66+D67+D68+D69+D70+D71+D72 -> 93.548833 | E73: =E65+E66+E67+E68+E69+E70+E71+E72 -> 70.009888 | F73: =F65+F66+F67+F68+F69+F70+F71+F72 -> 57.65037
A74: A_fix_u | B74: Cost fix / unitate | C74: =C64/C7 -> 23.119358 | D74: =D64/D7 -> 3.9123767 | E74: =E64/E7 -> 0.78247533 | F74: =F64/F7 -> 0.30290433
A75: A_total | B75: COST TOTAL / unitate (fără NRE produs) | C75: =C73+C74 -> 224.82959 | D75: =D73+D74 -> 97.46121 | E75: =E73+E74 -> 70.792364 | F75: =F73+F74 -> 57.953274
A76: A_nre | B76: NRE produs / unitate (comun: PCB, sticlă, matrițe OU, pe 3 ani) | C76: =((IF(C8=1,Ipoteze!$C$159,0)+Ipoteze!$C$160)*Ipoteze!$C$8+Ipoteze!C$161)/(Ipoteze!$C$162*C7) -> 29 | D76: =((IF(D8=1,Ipoteze!$C$159,0)+Ipoteze!$C$160)*Ipoteze!$C$8+Ipoteze!D$161)/(Ipoteze!$C$162*D7) -> 11.091667 | E76: =((IF(E8=1,Ipoteze!$C$159,0)+Ipoteze!$C$160)*Ipoteze!$C$8+Ipoteze!E$161)/(Ipoteze!$C$162*E7) -> 3.105 | F76: =((IF(F8=1,Ipoteze!$C$159,0)+Ipoteze!$C$160)*Ipoteze!$C$8+Ipoteze!F$161)/(Ipoteze!$C$162*F7) -> 0.77625
A77: A_total_nre | B77: COST TOTAL / unitate cu NRE | C77: =C75+C76 -> 253.82959 | D77: =D75+D76 -> 108.55288 | E77: =E75+E76 -> 73.897364 | F77: =F75+F76 -> 58.729524
A78: A_price | B78: Preț net încasat (fără TVA dacă firma e plătitoare) | C78: =IF(C10=1,Ipoteze!$C$10/(1+Ipoteze!$C$11),Ipoteze!$C$10) -> 249 | D78: =IF(D10=1,Ipoteze!$C$10/(1+Ipoteze!$C$11),Ipoteze!$C$10) -> 205.78512 | E78: =IF(E10=1,Ipoteze!$C$10/(1+Ipoteze!$C$11),Ipoteze!$C$10) -> 205.78512 | F78: =IF(F10=1,Ipoteze!$C$10/(1+Ipoteze!$C$11),Ipoteze!$C$10) -> 205.78512
A79: A_margin | B79: Marjă brută / unitate (cu NRE) | C79: =C78-C77 -> -4.829587 | D79: =D78-D77 -> 97.232247 | E79: =E78-E77 -> 131.88776 | F79: =F78-F77 -> 147.0556
A80: A_margin_pct | B80: Marjă brută % | C80: =IF(C78=0,0,C79/C78) -> -0.019395932 | D80: =IF(D78=0,0,D79/D78) -> 0.47249405 | E80: =IF(E78=0,0,E79/E78) -> 0.64090036 | F80: =IF(F78=0,0,F79/F78) -> 0.71460753
A82: Scenariul B — atelier T0 propriu (asamblare + flash + calibrare + test + QC + ambalare)
A83: B_capex | B83: CAPEX T0 | C83: =(C36*Ipoteze!$C$78+C37*C39+Ipoteze!$C$81+IF(C7>=Ipoteze!$C$24,Ipoteze!$C$82+Ipoteze!$C$83+Ipoteze!$C$85,Ipoteze!$C$84)+Ipoteze!$C$86+Ipoteze!$C$87*C36+Ipoteze!$C$88+C40)*(1+C11) -> 10236.757 | D83: =(D36*Ipoteze!$C$78+D37*D39+Ipoteze!$C$81+IF(D7>=Ipoteze!$C$24,Ipoteze!$C$82+Ipoteze!$C$83+Ipoteze!$C$85,Ipoteze!$C$84)+Ipoteze!$C$86+Ipoteze!$C$87*D36+Ipoteze!$C$88+D40)*(1+D11) -> 23361.13 | E83: =(E36*Ipoteze!$C$78+E37*E39+Ipoteze!$C$81+IF(E7>=Ipoteze!$C$24,Ipoteze!$C$82+Ipoteze!$C$83+Ipoteze!$C$85,Ipoteze!$C$84)+Ipoteze!$C$86+Ipoteze!$C$87*E36+Ipoteze!$C$88+E40)*(1+E11) -> 26356.13 | F83: =(F36*Ipoteze!$C$78+F37*F39+Ipoteze!$C$81+IF(F7>=Ipoteze!$C$24,Ipoteze!$C$82+Ipoteze!$C$83+Ipoteze!$C$85,Ipoteze!$C$84)+Ipoteze!$C$86+Ipoteze!$C$87*F36+Ipoteze!$C$88+F40)*(1+F11) -> 38783.26
A84: B_rent | B84: Chirie + servicii | C84: =Ipoteze!C$76*(Ipoteze!$C$99+Ipoteze!$C$100)*12*(1+C11) -> 0 | D84: =Ipoteze!D$76*(Ipoteze!$C$99+Ipoteze!$C$100)*12*(1+D11) -> 4824 | E84: =Ipoteze!E$76*(Ipoteze!$C$99+Ipoteze!$C$100)*12*(1+E11) -> 12060 | F84: =Ipoteze!F$76*(Ipoteze!$C$99+Ipoteze!$C$100)*12*(1+F11) -> 24120
A85: B_util | B85: Energie atelier | C85: =Ipoteze!C$77*12*Ipoteze!$C$101/Ipoteze!$C$7*(1+C11) -> 0 | D85: =Ipoteze!D$77*12*Ipoteze!$C$101/Ipoteze!$C$7*(1+D11) -> 3294.1176 | E85: =Ipoteze!E$77*12*Ipoteze!$C$101/Ipoteze!$C$7*(1+E11) -> 6588.2353 | F85: =Ipoteze!F$77*12*Ipoteze!$C$101/Ipoteze!$C$7*(1+F11) -> 9882.3529
A86: B_sal | B86: Salarii (operatori + QC + gestionar, cu CAM) | C86: =(C35*Ipoteze!$C$93+Ipoteze!C$74*Ipoteze!$C$94+Ipoteze!C$75*Ipoteze!$C$97)*(1+Ipoteze!$C$98)*12/Ipoteze!$C$7 -> 542.77092 | D86: =(D35*Ipoteze!$C$93+Ipoteze!D$74*Ipoteze!$C$94+Ipoteze!D$75*Ipoteze!$C$97)*(1+Ipoteze!$C$98)*12/Ipoteze!$C$7 -> 3015.394 | E86: =(E35*Ipoteze!$C$93+Ipoteze!E$74*Ipoteze!$C$94+Ipoteze!E$75*Ipoteze!$C$97)*(1+Ipoteze!$C$98)*12/Ipoteze!$C$7 -> 31877.941 | F86: =(F35*Ipoteze!$C$93+Ipoteze!F$74*Ipoteze!$C$94+Ipoteze!F$75*Ipoteze!$C$97)*(1+Ipoteze!$C$98)*12/Ipoteze!$C$7 -> 63515.294
A87: B_dep | B87: Amortizare | C87: =C83/Ipoteze!$C$89 -> 3412.2524 | D87: =D83/Ipoteze!$C$89 -> 7787.0433 | E87: =E83/Ipoteze!$C$89 -> 8785.3767 | F87: =F83/Ipoteze!$C$89 -> 12927.753
A88: B_perm | B88: Permise, asigurări, SSM, medicina muncii, EPR, software | C88: =Ipoteze!$C$105+Ipoteze!$C$106+Ipoteze!$C$107/Ipoteze!$C$7+(IF(C38<=5,Ipoteze!$C$108*12,Ipoteze!$C$109*12*C38)+Ipoteze!$C$110*C38+Ipoteze!$C$111*12*C38)/Ipoteze!$C$7+Ipoteze!$C$112+Ipoteze!$C$113 -> 3339.2157 | D88: =Ipoteze!$C$105+Ipoteze!$C$106+Ipoteze!$C$107/Ipoteze!$C$7+(IF(D38<=5,Ipoteze!$C$108*12,Ipoteze!$C$109*12*D38)+Ipoteze!$C$110*D38+Ipoteze!$C$111*12*D38)/Ipoteze!$C$7+Ipoteze!$C$112+Ipoteze!$C$113 -> 3339.2157 | E88: =Ipoteze!$C$105+Ipoteze!$C$106+Ipoteze!$C$107/Ipoteze!$C$7+(IF(E38<=5,Ipoteze!$C$108*12,Ipoteze!$C$109*12*E38)+Ipoteze!$C$110*E38+Ipoteze!$C$111*12*E38)/Ipoteze!$C$7+Ipoteze!$C$112+Ipoteze!$C$113 -> 3613.7255 | F88: =Ipoteze!$C$105+Ipoteze!$C$106+Ipoteze!$C$107/Ipoteze!$C$7+(IF(F38<=5,Ipoteze!$C$108*12,Ipoteze!$C$109*12*F38)+Ipoteze!$C$110*F38+Ipoteze!$C$111*12*F38)/Ipoteze!$C$7+Ipoteze!$C$112+Ipoteze!$C$113 -> 4053.7255
A89: B_fixed | B89: COSTURI FIXE / an | C89: =C84+C85+C86+C87+C88 -> 7294.239 | D89: =D84+D85+D86+D87+D88 -> 22259.771 | E89: =E84+E85+E86+E87+E88 -> 62925.279 | F89: =F84+F85+F86+F87+F88 -> 114499.13
A90: B_v_bom | B90: BOM livrat | C90: =C20 -> 73.394362 | D90: =D20 -> 43.521986 | E90: =E20 -> 32.864852 | F90: =F20 -> 27.470699
A91: B_v_pcba | B91: PCBA externalizat | C91: =C23 -> 0 | D91: =D23 -> 4 | E91: =E23 -> 2.5 | F91: =F23 -> 1.8
A92: B_v_shell | B92: Carcasă externalizată | C92: =C25 -> 71.46414 | D92: =D25 -> 31.842824 | E92: =E25 -> 23.47671 | F92: =F25 -> 18.73638
A93: B_v_laser | B93: Marcare laser (externă sub prag, apoi laser propriu) | C93: =IF(C7>=Ipoteze!$C$24,0,Ipoteze!C$60) -> 2 | D93: =IF(D7>=Ipoteze!$C$24,0,Ipoteze!D$60) -> 0 | E93: =IF(E7>=Ipoteze!$C$24,0,Ipoteze!E$60) -> 0 | F93: =IF(F7>=Ipoteze!$C$24,0,Ipoteze!F$60) -> 0
A94: B_scrap | B94: Rebut / rezervă | C94: =(C90+C91+C92)*Ipoteze!$C$73 -> 4.345755 | D94: =(D90+D91+D92)*Ipoteze!$C$73 -> 2.3809443 | E94: =(E90+E91+E92)*Ipoteze!$C$73 -> 1.7652469 | F94: =(F90+F91+F92)*Ipoteze!$C$73 -> 1.4402124
A95: B_vat | B95: TVA nerecuperabil pe achiziții (doar sub plafon) | C95: =(C90+C91+C92+C93+C94)*C11 -> 31.752894 | D95: =(D90+D91+D92+D93+D94)*D11 -> 0 | E95: =(E90+E91+E92+E93+E94)*E11 -> 0 | F95: =(F90+F91+F92+F93+F94)*F11 -> 0
A96: B_var | B96: COST VARIABIL / unitate | C96: =C90+C91+C92+C93+C94+C95 -> 182.95715 | D96: =D90+D91+D92+D93+D94+D95 -> 81.745755 | E96: =E90+E91+E92+E93+E94+E95 -> 60.606809 | F96: =F90+F91+F92+F93+F94+F95 -> 49.447291
A97: B_fix_u | B97: Cost fix / unitate | C97: =C89/C7 -> 72.94239 | D97: =D89/D7 -> 22.259771 | E97: =E89/E7 -> 12.585056 | F97: =F89/F7 -> 5.7249563
A98: B_total | B98: COST TOTAL / unitate (fără NRE produs) | C98: =C96+C97 -> 255.89954 | D98: =D96+D97 -> 104.00553 | E98: =E96+E97 -> 73.191865 | F98: =F96+F97 -> 55.172247
A99: B_nre | B99: NRE produs / unitate (comun: PCB, sticlă, matrițe OU, pe 3 ani) | C99: =((IF(C8=1,Ipoteze!$C$159,0)+Ipoteze!$C$160)*Ipoteze!$C$8+Ipoteze!C$161)/(Ipoteze!$C$162*C7) -> 29 | D99: =((IF(D8=1,Ipoteze!$C$159,0)+Ipoteze!$C$160)*Ipoteze!$C$8+Ipoteze!D$161)/(Ipoteze!$C$162*D7) -> 11.091667 | E99: =((IF(E8=1,Ipoteze!$C$159,0)+Ipoteze!$C$160)*Ipoteze!$C$8+Ipoteze!E$161)/(Ipoteze!$C$162*E7) -> 3.105 | F99: =((IF(F8=1,Ipoteze!$C$159,0)+Ipoteze!$C$160)*Ipoteze!$C$8+Ipoteze!F$161)/(Ipoteze!$C$162*F7) -> 0.77625
A100: B_total_nre | B100: COST TOTAL / unitate cu NRE | C100: =C98+C99 -> 284.89954 | D100: =D98+D99 -> 115.09719 | E100: =E98+E99 -> 76.296865 | F100: =F98+F99 -> 55.948497
A101: B_price | B101: Preț net încasat (fără TVA dacă firma e plătitoare) | C101: =IF(C10=1,Ipoteze!$C$10/(1+Ipoteze!$C$11),Ipoteze!$C$10) -> 249 | D101: =IF(D10=1,Ipoteze!$C$10/(1+Ipoteze!$C$11),Ipoteze!$C$10) -> 205.78512 | E101: =IF(E10=1,Ipoteze!$C$10/(1+Ipoteze!$C$11),Ipoteze!$C$10) -> 205.78512 | F101: =IF(F10=1,Ipoteze!$C$10/(1+Ipoteze!$C$11),Ipoteze!$C$10) -> 205.78512
A102: B_margin | B102: Marjă brută / unitate (cu NRE) | C102: =C101-C100 -> -35.899541 | D102: =D101-D100 -> 90.687932 | E102: =E101-E100 -> 129.48826 | F102: =F101-F100 -> 149.83663
A103: B_margin_pct | B103: Marjă brută % | C103: =IF(C101=0,0,C102/C101) -> -0.14417486 | D103: =IF(D101=0,0,D102/D101) -> 0.44069236 | E103: =IF(E101=0,0,E102/E101) -> 0.62924013 | F103: =IF(F101=0,0,F102/F101) -> 0.72812176
A105: Scenariul C — T0 + celulă CNC proprie (anodizare externă)
A106: C_capex | B106: CAPEX T0 + CNC | C106: =C83+C48*(1+C11) -> 136312.54 | D106: =D83+D48*(1+D11) -> 127555.99 | E106: =E83+E48*(1+E11) -> 130550.99 | F106: =F83+F48*(1+F11) -> 326215.68
...

Sheet Break-even
A1: BREAK-EVEN: de la ce volum bate producția proprie externalizarea (CNC și SMT)
A2: Comparație pe proces izolat, cu firma plătitoare de TVA (la aceste volume e obligatoriu). Prețul de cumpărare între volumele din Ipoteze e interpolat logaritmic; peste 20.000 rămâne la valoarea de 20.000. Costul fix propriu crește în trepte (a doua tură, încă o mașină/linie, încă un operator).
A5: 1. Valori pe treptele de volum
A6: tv | B6: Volum (treaptă) | C6: =Ipoteze!C$9 -> 100 | D6: =Ipoteze!D$9 -> 1000 | E6: =Ipoteze!E$9 -> 5000 | F6: =Ipoteze!F$9 -> 20000
A7: S_buy | B7: CNC S: carcasă externalizată livrată (€/set) | C7: =Scenarii!C25 -> 71.46414 | D7: =Scenarii!D25 -> 31.842824 | E7: =Scenarii!E25 -> 23.47671 | F7: =Scenarii!F25 -> 18.73638
A8: S_make | B8: CNC S: carcasă în casă, variabil (€/set) | C8: =Scenarii!C28 -> 10.507149 | D8: =Scenarii!D28 -> 9.8571488 | E8: =Scenarii!E28 -> 8.5131488 | F8: =Scenarii!F28 -> 7.7281488
A9: anod_set | B9: Anodizare per set S | C9: =Scenarii!C24 -> 4.99 | D9: =Scenarii!D24 -> 4.34 | E9: =Scenarii!E24 -> 2.996 | F9: =Scenarii!F24 -> 2.211
A10: Mc_buy | B10: CNC M (comparație): carcasă externalizată livrată (€/set) | C10: =(Ipoteze!C$55*Ipoteze!$C$138+(Ipoteze!C$56+C9)*Ipoteze!$C$139)*(1+Ipoteze!C$42)*(1+Ipoteze!$C$44) -> 110.05478 | D10: =(Ipoteze!D$55*Ipoteze!$C$138+(Ipoteze!D$56+D9)*Ipoteze!$C$139)*(1+Ipoteze!D$42)*(1+Ipoteze!$C$44) -> 49.037949 | E10: =(Ipoteze!E$55*Ipoteze!$C$138+(Ipoteze!E$56+E9)*Ipoteze!$C$139)*(1+Ipoteze!E$42)*(1+Ipoteze!$C$44) -> 36.154134 | F10: =(Ipoteze!F$55*Ipoteze!$C$138+(Ipoteze!F$56+F9)*Ipoteze!$C$139)*(1+Ipoteze!F$42)*(1+Ipoteze!$C$44) -> 28.854025
A11: Mc_make | B11: CNC M (comparație): carcasă în casă, variabil (€/set) | C11: =(Ipoteze!$C$128*Scenarii!C26+Ipoteze!$C$130*Ipoteze!$C$126/Ipoteze!$C$125+Ipoteze!$C$131*Ipoteze!$C$126/60*Ipoteze!$C$101/Ipoteze!$C$7+Ipoteze!$C$132*Ipoteze!$C$139)*(1+Ipoteze!$C$133)+C9*Ipoteze!$C$139+Ipoteze!$C$61 -> 19.251542 | D11: =(Ipoteze!$C$128*Scenarii!D26+Ipoteze!$C$130*Ipoteze!$C$126/Ipoteze!$C$125+Ipoteze!$C$131*Ipoteze!$C$126/60*Ipoteze!$C$101/Ipoteze!$C$7+Ipoteze!$C$132*Ipoteze!$C$139)*(1+Ipoteze!$C$133)+D9*Ipoteze!$C$139+Ipoteze!$C$61 -> 18.250542 | E11: =(Ipoteze!$C$128*Scenarii!E26+Ipoteze!$C$130*Ipoteze!$C$126/Ipoteze!$C$125+Ipoteze!$C$131*Ipoteze!$C$126/60*Ipoteze!$C$101/Ipoteze!$C$7+Ipoteze!$C$132*Ipoteze!$C$139)*(1+Ipoteze!$C$133)+E9*Ipoteze!$C$139+Ipoteze!$C$61 -> 16.180782 | F11: =(Ipoteze!$C$128*Scenarii!F26+Ipoteze!$C$130*Ipoteze!$C$126/Ipoteze!$C$125+Ipoteze!$C$131*Ipoteze!$C$126/60*Ipoteze!$C$101/Ipoteze!$C$7+Ipoteze!$C$132*Ipoteze!$C$139)*(1+Ipoteze!$C$133)+F9*Ipoteze!$C$139+Ipoteze!$C$61 -> 14.971882
A12: ems | B12: SMT: PCBA la EMS România (€/placă) | C12: =Ipoteze!C$54 -> 12 | D12: =Ipoteze!D$54 -> 4 | E12: =Ipoteze!E$54 -> 2.5 | F12: =Ipoteze!F$54 -> 1.8
A13: jlc | B13: SMT: PCBA la JLCPCB livrat (€/placă) | C13: =(Ipoteze!$C$51*Ipoteze!C$53+(Ipoteze!$C$47+Ipoteze!$C$48+Ipoteze!$C$49*Ipoteze!$C$50)*Ipoteze!C$22/C6)*Ipoteze!$C$8*(1+Ipoteze!C$42)*(1+Ipoteze!$C$43) -> 1.5035484 | D13: =(Ipoteze!$C$51*Ipoteze!D$53+(Ipoteze!$C$47+Ipoteze!$C$48+Ipoteze!$C$49*Ipoteze!$C$50)*Ipoteze!D$22/D6)*Ipoteze!$C$8*(1+Ipoteze!D$42)*(1+Ipoteze!$C$43) -> 0.94075688 | E13: =(Ipoteze!$C$51*Ipoteze!E$53+(Ipoteze!$C$47+Ipoteze!$C$48+Ipoteze!$C$49*Ipoteze!$C$50)*Ipoteze!E$22/E6)*Ipoteze!$C$8*(1+Ipoteze!E$42)*(1+Ipoteze!$C$43) -> 0.64976308 | F13: =(Ipoteze!$C$51*Ipoteze!F$53+(Ipoteze!$C$47+Ipoteze!$C$48+Ipoteze!$C$49*Ipoteze!$C$50)*Ipoteze!F$22/F6)*Ipoteze!$C$8*(1+Ipoteze!F$42)*(1+Ipoteze!$C$43) -> 0.4881042
A14: smt_make | B14: SMT: în casă, variabil (€/placă) | C14: =Ipoteze!$C$151+(Ipoteze!$C$152-Ipoteze!$C$153)*(Ipoteze!C$28+Ipoteze!C$29+Ipoteze!C$30)*Ipoteze!$C$8 -> 0.37226 | D14: =Ipoteze!$C$151+(Ipoteze!$C$152-Ipoteze!$C$153)*(Ipoteze!D$28+Ipoteze!D$29+Ipoteze!D$30)*Ipoteze!$C$8 -> 0.320843 | E14: =Ipoteze!$C$151+(Ipoteze!$C$152-Ipoteze!$C$153)*(Ipoteze!E$28+Ipoteze!E$29+Ipoteze!E$30)*Ipoteze!$C$8 -> 0.306488 | F14: =Ipoteze!$C$151+(Ipoteze!$C$152-Ipoteze!$C$153)*(Ipoteze!F$28+Ipoteze!F$29+Ipoteze!F$30)*Ipoteze!$C$8 -> 0.295787
A16: 2. Costuri fixe de bază (o mașină / o linie, un schimb)
A17: mach | B17: Mașină CNC instalată | C17: =Ipoteze!$C$116*Ipoteze!$C$8*(1+Ipoteze!$C$117) -> 74118.78
A18: cnc_common | B18: Echipamente comune CNC | C18: =(Ipoteze!$C$119+Ipoteze!$C$120)/Ipoteze!$C$7+Ipoteze!$C$121+Ipoteze!$C$122 -> 12576.078
A19: emp_over | B19: Cost SSM + medicina muncii + salarizare per angajat suplimentar / an | C19: =(Ipoteze!$C$109*12+Ipoteze!$C$110+Ipoteze!$C$111*12)/Ipoteze!$C$7 -> 189.01961
A20: op_prog | B20: Programator CNC, cost anual | C20: =Ipoteze!$C$95*(1+Ipoteze!$C$98)*12/Ipoteze!$C$7 -> 25983.529
A21: op_cnc | B21: Operator CNC, cost anual | C21: =Ipoteze!$C$96*(1+Ipoteze!$C$98)*12/Ipoteze!$C$7 -> 14435.294
A22: space_cost | B22: Chirie + servicii per m² / an | C22: =(Ipoteze!$C$99+Ipoteze!$C$100)*12 -> 80.4
A23: capS | B23: Capacitate CNC S: seturi / mașină / schimb / an | C23: =Ipoteze!$C$18/Ipoteze!$C$125*Ipoteze!$C$15 -> 3740
A24: capMc | B24: Capacitate CNC M (comparație): seturi / mașină / schimb / an | C24: =Ipoteze!$C$18/Ipoteze!$C$126*Ipoteze!$C$15 -> 1994.6667
A25: smt_line | B25: Capex linie SMT | C25: =Ipoteze!$C$142+Ipoteze!$C$143+(Ipoteze!$C$144+Ipoteze!$C$145)*Ipoteze!$C$8+Ipoteze!$C$146+Ipoteze!$C$147+Ipoteze!$C$148 -> 36470.42
A26: smt_cap | B26: Capacitate SMT: plăci / linie / schimb / an | C26: =Ipoteze!$C$18/(Ipoteze!$C$52/Ipoteze!$C$149*60+Ipoteze!$C$150)*Ipoteze!$C$15 -> 21892.683
A27: tech | B27: Tehnician SMT, cost anual | C27: =Ipoteze!$C$94*(1+Ipoteze!$C$98)*12/Ipoteze!$C$7 -> 15638.235
A28: F_cnc1 | B28: Cost fix anual celulă CNC (1 mașină, 1 schimb, 1 programator) | C28: =(1*('Break-even'!$C$17+Ipoteze!$C$118)+'Break-even'!$C$18)/Ipoteze!$C$90+'Break-even'!$C$20+(1-1)*'Break-even'!$C$21+1*'Break-even'!$C$19+(1*Ipoteze!$C$134+Ipoteze!$C$135)*'Break-even'!$C$22+Ipoteze!$C$124*1*'Break-even'!$C$17+Ipoteze!$C$123*Ipoteze!$C$8+Ipoteze!$C$136 -> 56858.684
A29: F_smt1 | B29: Cost fix anual linie SMT (1 linie, 1 schimb, 1 tehnician) | C29: =1*'Break-even'!$C$25/Ipoteze!$C$90+1*('Break-even'!$C$27+'Break-even'!$C$19)+1*Ipoteze!$C$155*'Break-even'!$C$22+Ipoteze!$C$124*1*'Break-even'!$C$25+Ipoteze!$C$154*Ipoteze!$C$16*Ipoteze!$C$15*1*1*Ipoteze!$C$101/Ipoteze!$C$7+Ipoteze!$C$156 -> 29356.785
A31: 3. Break-even analitic pe trepte (o mașină / o linie, un schimb): N* = cost fix / (preț cumpărare − variabil propriu)
A32: be_S | B32: CNC S: volum de break-even (seturi/an) | C32: =IF(C7-C8<=0,"niciodată",'Break-even'!$C$28/(C7-C8)) -> 932.76723 | D32: =IF(D7-D8<=0,"niciodată",'Break-even'!$C$28/(D7-D8)) -> 2586.1696 | E32: =IF(E7-E8<=0,"niciodată",'Break-even'!$C$28/(E7-E8)) -> 3799.8095 | F32: =IF(F7-F8<=0,"niciodată",'Break-even'!$C$28/(F7-F8)) -> 5165.1064
A33: be_S_ok | B33: … încape într-o mașină pe un schimb? (1 = da) | C33: =IF(ISNUMBER(C32),IF(C32<='Break-even'!$C$23,1,0),0) -> 1 | D33: =IF(ISNUMBER(D32),IF(D32<='Break-even'!$C$23,1,0),0) -> 1 | E33: =IF(ISNUMBER(E32),IF(E32<='Break-even'!$C$23,1,0),0) -> 0 | F33: =IF(ISNUMBER(F32),IF(F32<='Break-even'!$C$23,1,0),0) -> 0
A34: be_Mc | B34: CNC M (comparație): volum de break-even (seturi/an) | C34: =IF(C10-C11<=0,"niciodată",'Break-even'!$C$28/(C10-C11)) -> 626.17467 | D34: =IF(D10-D11<=0,"niciodată",'Break-even'!$C$28/(D10-D11)) -> 1846.8163 | E34: =IF(E10-E11<=0,"niciodată",'Break-even'!$C$28/(E10-E11)) -> 2846.7273 | F34: =IF(F10-F11<=0,"niciodată",'Break-even'!$C$28/(F10-F11)) -> 4095.8148
A35: be_Mc_ok | B35: … încape într-o mașină pe un schimb? (1 = da) | C35: =IF(ISNUMBER(C34),IF(C34<='Break-even'!$C$24,1,0),0) -> 1 | D35: =IF(ISNUMBER(D34),IF(D34<='Break-even'!$C$24,1,0),0) -> 1 | E35: =IF(ISNUMBER(E34),IF(E34<='Break-even'!$C$24,1,0),0) -> 0 | F35: =IF(ISNUMBER(F34),IF(F34<='Break-even'!$C$24,1,0),0) -> 0
A36: be_ems | B36: SMT vs EMS România: volum de break-even (plăci/an) | C36: =IF(C12-C14<=0,"niciodată",'Break-even'!$C$29/(C12-C14)) -> 2524.7198 | D36: =IF(D12-D14<=0,"niciodată",'Break-even'!$C$29/(D12-D14)) -> 7979.215 | E36: =IF(E12-E14<=0,"niciodată",'Break-even'!$C$29/(E12-E14)) -> 13383.462 | F36: =IF(F12-F14<=0,"niciodată",'Break-even'!$C$29/(F12-F14)) -> 19516.375
A37: be_jlc | B37: SMT vs JLCPCB: volum de break-even (plăci/an) | C37: =IF(C13-C14<=0,"niciodată",'Break-even'!$C$29/(C13-C14)) -> 25949.867 | D37: =IF(D13-D14<=0,"niciodată",'Break-even'!$C$29/(D13-D14)) -> 47356.231 | E37: =IF(E13-E14<=0,"niciodată",'Break-even'!$C$29/(E13-E14)) -> 85519.708 | F37: =IF(F13-F14<=0,"niciodată",'Break-even'!$C$29/(F13-F14)) -> 152647.73
A39: 4. Grilă CNC mărimea S (Haas VF-2 nou; anodizare externă în ambele variante)
A40: Volum (seturi/an) | B40: Treaptă | C40: Cumpărat €/set | D40: Cumpărat €/an | E40: Mașini | F40: Schimburi | G40: Operatori | H40: Fix propriu €/an | I40: Variabil propriu €/set | J40: Propriu €/an | K40: Propriu €/set | L40: Economie €/an | M40: Propriu mai ieftin?
A41: 250 | B41: =MATCH(A41,'Break-even'!$C$6:$F$6,1) -> 1 | C41: =IF(B41>=4,INDEX('Break-even'!$C$7:$F$7,1,4),INDEX('Break-even'!$C$7:$F$7,1,B41)+(INDEX('Break-even'!$C$7:$F$7,1,B41+1)-INDEX('Break-even'!$C$7:$F$7,1,B41))*LN(A41/INDEX('Break-even'!$C$6:$F$6,1,B41))/LN(INDEX('Break-even'!$C$6:$F$6,1,B41+1)/INDEX('Break-even'!$C$6:$F$6,1,B41))) -> 55.697233 | D41: =A41*C41 -> 13924.308 | E41: =CEILING(A41/('Break-even'!$C$23*Ipoteze!$C$20),1) -> 1 | F41: =MIN(Ipoteze!$C$20,CEILING(A41/('Break-even'!$C$23*E41),1)) -> 1 | G41: =F41*CEILING(E41/Ipoteze!$C$137,1) -> 1 | H41: =(E41*('Break-even'!$C$17+Ipoteze!$C$118)+'Break-even'!$C$18)/Ipoteze!$C$90+'Break-even'!$C$20+(G41-1)*'Break-even'!$C$21+G41*'Break-even'!$C$19+(E41*Ipoteze!$C$134+Ipoteze!$C$135)*'Break-even'!$C$22+Ipoteze!$C$124*E41*'Break-even'!$C$17+Ipoteze!$C$123*Ipoteze!$C$8+Ipoteze!$C$136 -> 56858.684 | I41: =IF(B41>=4,INDEX('Break-even'!$C$8:$F$8,1,4),INDEX('Break-even'!$C$8:$F$8,1,B41)+(INDEX('Break-even'!$C$8:$F$8,1,B41+1)-INDEX('Break-even'!$C$8:$F$8,1,B41))*LN(A41/INDEX('Break-even'!$C$6:$F$6,1,B41))/LN(INDEX('Break-even'!$C$6:$F$6,1,B41+1)/INDEX('Break-even'!$C$6:$F$6,1,B41))) -> 10.248488 | J41: =H41+A41*I41 -> 59420.806 | K41: =J41/A41 -> 237.68322 | L41: =D41-J41 -> -45496.498 | M41: =IF(J41<D41,1,0) -> 0
A42: 500 | B42: =MATCH(A42,'Break-even'!$C$6:$F$6,1) -> 1 | C42: =IF(B42>=4,INDEX('Break-even'!$C$7:$F$7,1,4),INDEX('Break-even'!$C$7:$F$7,1,B42)+(INDEX('Break-even'!$C$7:$F$7,1,B42+1)-INDEX('Break-even'!$C$7:$F$7,1,B42))*LN(A42/INDEX('Break-even'!$C$6:$F$6,1,B42))/LN(INDEX('Break-even'!$C$6:$F$6,1,B42+1)/INDEX('Break-even'!$C$6:$F$6,1,B42))) -> 43.770029 | D42: =A42*C42 -> 21885.014 | E42: =CEILING(A42/('Break-even'!$C$23*Ipoteze!$C$20),1) -> 1 | F42: =MIN(Ipoteze!$C$20,CEILING(A42/('Break-even'!$C$23*E42),1)) -> 1 | G42: =F42*CEILING(E42/Ipoteze!$C$137,1) -> 1 | H42: =(E42*('Break-even'!$C$17+Ipoteze!$C$118)+'Break-even'!$C$18)/Ipoteze!$C$90+'Break-even'!$C$20+(G42-1)*'Break-even'!$C$21+G42*'Break-even'!$C$19+(E42*Ipoteze!$C$134+Ipoteze!$C$135)*'Break-even'!$C$22+Ipoteze!$C$124*E42*'Break-even'!$C$17+Ipoteze!$C$123*Ipoteze!$C$8+Ipoteze!$C$136 -> 56858.684 | I42: =IF(B42>=4,INDEX('Break-even'!$C$8:$F$8,1,4),INDEX('Break-even'!$C$8:$F$8,1,B42)+(INDEX('Break-even'!$C$8:$F$8,1,B42+1)-INDEX('Break-even'!$C$8:$F$8,1,B42))*LN(A42/INDEX('Break-even'!$C$6:$F$6,1,B42))/LN(INDEX('Break-even'!$C$6:$F$6,1,B42+1)/INDEX('Break-even'!$C$6:$F$6,1,B42))) -> 10.052818 | J42: =H42+A42*I42 -> 61885.093 | K42: =J42/A42 -> 123.77019 | L42: =D42-J42 -> -40000.079 | M42: =IF(J42<D42,1,0) -> 0
A43: 1000 | B43: =MATCH(A43,'Break-even'!$C$6:$F$6,1) -> 2 | C43: =IF(B43>=4,INDEX('Break-even'!$C$7:$F$7,1,4),INDEX('Break-even'!$C$7:$F$7,1,B43)+(INDEX('Break-even'!$C$7:$F$7,1,B43+1)-INDEX('Break-even'!$C$7:$F$7,1,B43))*LN(A43/INDEX('Break-even'!$C$6:$F$6,1,B43))/LN(INDEX('Break-even'!$C$6:$F$6,1,B43+1)/INDEX('Break-even'!$C$6:$F$6,1,B43))) -> 31.842824 | D43: =A43*C43 -> 31842.824 | E43: =CEILING(A43/('Break-even'!$C$23*Ipoteze!$C$20),1) -> 1 | F43: =MIN(Ipoteze!$C$20,CEILING(A43/('Break-even'!$C$23*E43),1)) -> 1 | G43: =F43*CEILING(E43/Ipoteze!$C$137,1) -> 1 | H43: =(E43*('Break-even'!$C$17+Ipoteze!$C$118)+'Break-even'!$C$18)/Ipoteze!$C$90+'Break-even'!$C$20+(G43-1)*'Break-even'!$C$21+G43*'Break-even'!$C$19+(E43*Ipoteze!$C$134+Ipoteze!$C$135)*'Break-even'!$C$22+Ipoteze!$C$124*E43*'Break-even'!$C$17+Ipoteze!$C$123*Ipoteze!$C$8+Ipoteze!$C$136 -> 56858.684 | I43: =IF(B43>=4,INDEX('Break-even'!$C$8:$F$8,1,4),INDEX('Break-even'!$C$8:$F$8,1,B43)+(INDEX('Break-even'!$C$8:$F$8,1,B43+1)-INDEX('Break-even'!$C$8:$F$8,1,B43))*LN(A43/INDEX('Break-even'!$C$6:$F$6,1,B43))/LN(INDEX('Break-even'!$C$6:$F$6,1,B43+1)/INDEX('Break-even'!$C$6:$F$6,1,B43))) -> 9.8571488 | J43: =H43+A43*I43 -> 66715.833 | K43: =J43/A43 -> 66.715833 | L43: =D43-J43 -> -34873.009 | M43: =IF(J43<D43,1,0) -> 0
A44: 1500 | B44: =MATCH(A44,'Break-even'!$C$6:$F$6,1) -> 2 | C44: =IF(B44>=4,INDEX('Break-even'!$C$7:$F$7,1,4),INDEX('Break-even'!$C$7:$F$7,1,B44)+(INDEX('Break-even'!$C$7:$F$7,1,B44+1)-INDEX('Break-even'!$C$7:$F$7,1,B44))*LN(A44/INDEX('Break-even'!$C$6:$F$6,1,B44))/LN(INDEX('Break-even'!$C$6:$F$6,1,B44+1)/INDEX('Break-even'!$C$6:$F$6,1,B44))) -> 29.735152 | D44: =A44*C44 -> 44602.728 | E44: =CEILING(A44/('Break-even'!$C$23*Ipoteze!$C$20),1) -> 1 | F44: =MIN(Ipoteze!$C$20,CEILING(A44/('Break-even'!$C$23*E44),1)) -> 1 | G44: =F44*CEILING(E44/Ipoteze!$C$137,1) -> 1 | H44: =(E44*('Break-even'!$C$17+Ipoteze!$C$118)+'Break-even'!$C$18)/Ipoteze!$C$90+'Break-even'!$C$20+(G44-1)*'Break-even'!$C$21+G44*'Break-even'!$C$19+(E44*Ipoteze!$C$134+Ipoteze!$C$135)*'Break-even'!$C$22+Ipoteze!$C$124*E44*'Break-even'!$C$17+Ipoteze!$C$123*Ipoteze!$C$8+Ipoteze!$C$136 -> 56858.684 | I44: =IF(B44>=4,INDEX('Break-even'!$C$8:$F$8,1,4),INDEX('Break-even'!$C$8:$F$8,1,B44)+(INDEX('Break-even'!$C$8:$F$8,1,B44+1)-INDEX('Break-even'!$C$8:$F$8,1,B44))*LN(A44/INDEX('Break-even'!$C$6:$F$6,1,B44))/LN(INDEX('Break-even'!$C$6:$F$6,1,B44+1)/INDEX('Break-even'!$C$6:$F$6,1,B44))) -> 9.5185553 | J44: =H44+A44*I44 -> 71136.517 | K44: =J44/A44 -> 47.424345 | L44: =D44-J44 -> -26533.789 | M44: =IF(J44<D44,1,0) -> 0
A45: 2000 | B45: =MATCH(A45,'Break-even'!$C$6:$F$6,1) -> 2 | C45: =IF(B45>=4,INDEX('Break-even'!$C$7:$F$7,1,4),INDEX('Break-even'!$C$7:$F$7,1,B45)+(INDEX('Break-even'!$C$7:$F$7,1,B45+1)-INDEX('Break-even'!$C$7:$F$7,1,B45))*LN(A45/INDEX('Break-even'!$C$6:$F$6,1,B45))/LN(INDEX('Break-even'!$C$6:$F$6,1,B45+1)/INDEX('Break-even'!$C$6:$F$6,1,B45))) -> 28.239735 | D45: =A45*C45 -> 56479.47 | E45: =CEILING(A45/('Break-even'!$C$23*Ipoteze!$C$20),1) -> 1 | F45: =MIN(Ipoteze!$C$20,CEILING(A45/('Break-even'!$C$23*E45),1)) -> 1 | G45: =F45*CEILING(E45/Ipoteze!$C$137,1) -> 1 | H45: =(E45*('Break-even'!$C$17+Ipoteze!$C$118)+'Break-even'!$C$18)/Ipoteze!$C$90+'Break-even'!$C$20+(G45-1)*'Break-even'!$C$21+G45*'Break-even'!$C$19+(E45*Ipoteze!$C$134+Ipoteze!$C$135)*'Break-even'!$C$22+Ipoteze!$C$124*E45*'Break-even'!$C$17+Ipoteze!$C$123*Ipoteze!$C$8+Ipoteze!$C$136 -> 56858.684 | I45: =IF(B45>=4,INDEX('Break-even'!$C$8:$F$8,1,4),INDEX('Break-even'!$C$8:$F$8,1,B45)+(INDEX('Break-even'!$C$8:$F$8,1,B45+1)-INDEX('Break-even'!$C$8:$F$8,1,B45))*LN(A45/INDEX('Break-even'!$C$6:$F$6,1,B45))/LN(INDEX('Break-even'!$C$6:$F$6,1,B45+1)/INDEX('Break-even'!$C$6:$F$6,1,B45))) -> 9.2783195 | J45: =H45+A45*I45 -> 75415.323 | K45: =J45/A45 -> 37.707662 | L45: =D45-J45 -> -18935.853 | M45: =IF(J45<D45,1,0) -> 0
A46: 2500 | B46: =MATCH(A46,'Break-even'!$C$6:$F$6,1) -> 2 | C46: =IF(B46>=4,INDEX('Break-even'!$C$7:$F$7,1,4),INDEX('Break-even'!$C$7:$F$7,1,B46)+(INDEX('Break-even'!$C$7:$F$7,1,B46+1)-INDEX('Break-even'!$C$7:$F$7,1,B46))*LN(A46/INDEX('Break-even'!$C$6:$F$6,1,B46))/LN(INDEX('Break-even'!$C$6:$F$6,1,B46+1)/INDEX('Break-even'!$C$6:$F$6,1,B46))) -> 27.079799 | D46: =A46*C46 -> 67699.499 | E46: =CEILING(A46/('Break-even'!$C$23*Ipoteze!$C$20),1) -> 1 | F46: =MIN(Ipoteze!$C$20,CEILING(A46/('Break-even'!$C$23*E46),1)) -> 1 | G46: =F46*CEILING(E46/Ipoteze!$C$137,1) -> 1 | H46: =(E46*('Break-even'!$C$17+Ipoteze!$C$118)+'Break-even'!$C$18)/Ipoteze!$C$90+'Break-even'!$C$20+(G46-1)*'Break-even'!$C$21+G46*'Break-even'!$C$19+(E46*Ipoteze!$C$134+Ipoteze!$C$135)*'Break-even'!$C$22+Ipoteze!$C$124*E46*'Break-even'!$C$17+Ipoteze!$C$123*Ipoteze!$C$8+Ipoteze!$C$136 -> 56858.684 | I46: =IF(B46>=4,INDEX('Break-even'!$C$8:$F$8,1,4),INDEX('Break-even'!$C$8:$F$8,1,B46)+(INDEX('Break-even'!$C$8:$F$8,1,B46+1)-INDEX('Break-even'!$C$8:$F$8,1,B46))*LN(A46/INDEX('Break-even'!$C$6:$F$6,1,B46))/LN(INDEX('Break-even'!$C$6:$F$6,1,B46+1)/INDEX('Break-even'!$C$6:$F$6,1,B46))) -> 9.0919781 | J46: =H46+A46*I46 -> 79588.629 | K46: =J46/A46 -> 31.835452 | L46: =D46-J46 -> -11889.131 | M46: =IF(J46<D46,1,0) -> 0
A47: 3000 | B47: =MATCH(A47,'Break-even'!$C$6:$F$6,1) -> 2 | C47: =IF(B47>=4,INDEX('Break-even'!$C$7:$F$7,1,4),INDEX('Break-even'!$C$7:$F$7,1,B47)+(INDEX('Break-even'!$C$7:$F$7,1,B47+1)-INDEX('Break-even'!$C$7:$F$7,1,B47))*LN(A47/INDEX('Break-even'!$C$6:$F$6,1,B47))/LN(INDEX('Break-even'!$C$6:$F$6,1,B47+1)/INDEX('Break-even'!$C$6:$F$6,1,B47))) -> 26.132063 | D47: =A47*C47 -> 78396.189 | E47: =CEILING(A47/('Break-even'!$C$23*Ipoteze!$C$20),1) -> 1 | F47: =MIN(Ipoteze!$C$20,CEILING(A47/('Break-even'!$C$23*E47),1)) -> 1 | G47: =F47*CEILING(E47/Ipoteze!$C$137,1) -> 1 | H47: =(E47*('Break-even'!$C$17+Ipoteze!$C$118)+'Break-even'!$C$18)/Ipoteze!$C$90+'Break-even'!$C$20+(G47-1)*'Break-even'!$C$21+G47*'Break-even'!$C$19+(E47*Ipoteze!$C$134+Ipoteze!$C$135)*'Break-even'!$C$22+Ipoteze!$C$124*E47*'Break-even'!$C$17+Ipoteze!$C$123*Ipoteze!$C$8+Ipoteze!$C$136 -> 56858.684 | I47: =IF(B47>=4,INDEX('Break-even'!$C$8:$F$8,1,4),INDEX('Break-even'!$C$8:$F$8,1,B47)+(INDEX('Break-even'!$C$8:$F$8,1,B47+1)-INDEX('Break-even'!$C$8:$F$8,1,B47))*LN(A47/INDEX('Break-even'!$C$6:$F$6,1,B47))/LN(INDEX('Break-even'!$C$6:$F$6,1,B47+1)/INDEX('Break-even'!$C$6:$F$6,1,B47))) -> 8.939726 | J47: =H47+A47*I47 -> 83677.862 | K47: =J47/A47 -> 27.892621 | L47: =D47-J47 -> -5281.6731 | M47: =IF(J47<D47,1,0) -> 0
A48: 4000 | B48: =MATCH(A48,'Break-even'!$C$6:$F$6,1) -> 2 | C48: =IF(B48>=4,INDEX('Break-even'!$C$7:$F$7,1,4),INDEX('Break-even'!$C$7:$F$7,1,B48)+(INDEX('Break-even'!$C$7:$F$7,1,B48+1)-INDEX('Break-even'!$C$7:$F$7,1,B48))*LN(A48/INDEX('Break-even'!$C$6:$F$6,1,B48))/LN(INDEX('Break-even'!$C$6:$F$6,1,B48+1)/INDEX('Break-even'!$C$6:$F$6,1,B48))) -> 24.636646 | D48: =A48*C48 -> 98546.584 | E48: =CEILING(A48/('Break-even'!$C$23*Ipoteze!$C$20),1) -> 1 | F48: =MIN(Ipoteze!$C$20,CEILING(A48/('Break-even'!$C$23*E48),1)) -> 2 | G48: =F48*CEILING(E48/Ipoteze!$C$137,1) -> 2 | H48: =(E48*('Break-even'!$C$17+Ipoteze!$C$118)+'Break-even'!$C$18)/Ipoteze!$C$90+'Break-even'!$C$20+(G48-1)*'Break-even'!$C$21+G48*'Break-even'!$C$19+(E48*Ipoteze!$C$134+Ipoteze!$C$135)*'Break-even'!$C$22+Ipoteze!$C$124*E48*'Break-even'!$C$17+Ipoteze!$C$123*Ipoteze!$C$8+Ipoteze!$C$136 -> 71482.998 | I48: =IF(B48>=4,INDEX('Break-even'!$C$8:$F$8,1,4),INDEX('Break-even'!$C$8:$F$8,1,B48)+(INDEX('Break-even'!$C$8:$F$8,1,B48+1)-INDEX('Break-even'!$C$8:$F$8,1,B48))*LN(A48/INDEX('Break-even'!$C$6:$F$6,1,B48))/LN(INDEX('Break-even'!$C$6:$F$6,1,B48+1)/INDEX('Break-even'!$C$6:$F$6,1,B48))) -> 8.6994902 | J48: =H48+A48*I48 -> 106280.96 | K48: =J48/A48 -> 26.57024 | L48: =D48-J48 -> -7734.3746 | M48: =IF(J48<D48,1,0) -> 0
A49: 5000 | B49: =MATCH(A49,'Break-even'!$C$6:$F$6,1) -> 3 | C49: =IF(B49>=4,INDEX('Break-even'!$C$7:$F$7,1,4),INDEX('Break-even'!$C$7:$F$7,1,B49)+(INDEX('Break-even'!$C$7:$F$7,1,B49+1)-INDEX('Break-even'!$C$7:$F$7,1,B49))*LN(A49/INDEX('Break-even'!$C$6:$F$6,1,B49))/LN(INDEX('Break-even'!$C$6:$F$6,1,B49+1)/INDEX('Break-even'!$C$6:$F$6,1,B49))) -> 23.47671 | D49: =A49*C49 -> 117383.55 | E49: =CEILING(A49/('Break-even'!$C$23*Ipoteze!$C$20),1) -> 1 | F49: =MIN(Ipoteze!$C$20,CEILING(A49/('Break-even'!$C$23*E49),1)) -> 2 | G49: =F49*CEILING(E49/Ipoteze!$C$137,1) -> 2 | H49: =(E49*('Break-even'!$C$17+Ipoteze!$C$118)+'Break-even'!$C$18)/Ipoteze!$C$90+'Break-even'!$C$20+(G49-1)*'Break-even'!$C$21+G49*'Break-even'!$C$19+(E49*Ipoteze!$C$134+Ipoteze!$C$135)*'Break-even'!$C$22+Ipoteze!$C$124*E49*'Break-even'!$C$17+Ipoteze!$C$123*Ipoteze!$C$8+Ipoteze!$C$136 -> 71482.998 | I49: =IF(B49>=4,INDEX('Break-even'!$C$8:$F$8,1,4),INDEX('Break-even'!$C$8:$F$8,1,B49)+(INDEX('Break-even'!$C$8:$F$8,1,B49+1)-INDEX('Break-even'!$C$8:$F$8,1,B49))*LN(A49/INDEX('Break-even'!$C$6:$F$6,1,B49))/LN(INDEX('Break-even'!$C$6:$F$6,1,B49+1)/INDEX('Break-even'!$C$6:$F$6,1,B49))) -> 8.5131488 | J49: =H49+A49*I49 -> 114048.74 | K49: =J49/A49 -> 22.809748 | L49: =D49-J49 -> 3334.8104 | M49: =IF(J49<D49,1,0) -> 1
A50: 7500 | B50: =MATCH(A50,'Break-even'!$C$6:$F$6,1) -> 3 | C50: =IF(B50>=4,INDEX('Break-even'!$C$7:$F$7,1,4),INDEX('Break-even'!$C$7:$F$7,1,B50)+(INDEX('Break-even'!$C$7:$F$7,1,B50+1)-INDEX('Break-even'!$C$7:$F$7,1,B50))*LN(A50/INDEX('Break-even'!$C$6:$F$6,1,B50))/LN(INDEX('Break-even'!$C$6:$F$6,1,B50+1)/INDEX('Break-even'!$C$6:$F$6,1,B50))) -> 22.090253 | D50: =A50*C50 -> 165676.89 | E50: =CEILING(A50/('Break-even'!$C$23*Ipoteze!$C$20),1) -> 2 | F50: =MIN(Ipoteze!$C$20,CEILING(A50/('Break-even'!$C$23*E50),1)) -> 2 | G50: =F50*CEILING(E50/Ipoteze!$C$137,1) -> 2 | H50: =(E50*('Break-even'!$C$17+Ipoteze!$C$118)+'Break-even'!$C$18)/Ipoteze!$C$90+'Break-even'!$C$20+(G50-1)*'Break-even'!$C$21+G50*'Break-even'!$C$19+(E50*Ipoteze!$C$134+Ipoteze!$C$135)*'Break-even'!$C$22+Ipoteze!$C$124*E50*'Break-even'!$C$17+Ipoteze!$C$123*Ipoteze!$C$8+Ipoteze!$C$136 -> 96050.317 | I50: =IF(B50>=4,INDEX('Break-even'!$C$8:$F$8,1,4),INDEX('Break-even'!$C$8:$F$8,1,B50)+(INDEX('Break-even'!$C$8:$F$8,1,B50+1)-INDEX('Break-even'!$C$8:$F$8,1,B50))*LN(A50/INDEX('Break-even'!$C$6:$F$6,1,B50))/LN(INDEX('Break-even'!$C$6:$F$6,1,B50+1)/INDEX('Break-even'!$C$6:$F$6,1,B50))) -> 8.283551 | J50: =H50+A50*I50 -> 158176.95 | K50: =J50/A50 -> 21.09026 | L50: =D50-J50 -> 7499.9448 | M50: =IF(J50<D50,1,0) -> 1
A51: 10000 | B51: =MATCH(A51,'Break-even'!$C$6:$F$6,1) -> 3 | C51: =IF(B51>=4,INDEX('Break-even'!$C$7:$F$7,1,4),INDEX('Break-even'!$C$7:$F$7,1,B51)+(INDEX('Break-even'!$C$7:$F$7,1,B51+1)-INDEX('Break-even'!$C$7:$F$7,1,B51))*LN(A51/INDEX('Break-even'!$C$6:$F$6,1,B51))/LN(INDEX('Break-even'!$C$6:$F$6,1,B51+1)/INDEX('Break-even'!$C$6:$F$6,1,B51))) -> 21.106545 | D51: =A51*C51 -> 211065.45 | E51: =CEILING(A51/('Break-even'!$C$23*Ipoteze!$C$20),1) -> 2 | F51: =MIN(Ipoteze!$C$20,CEILING(A51/('Break-even'!$C$23*E51),1)) -> 2 | G51: =F51*CEILING(E51/Ipoteze!$C$137,1) -> 2 | H51: =(E51*('Break-even'!$C$17+Ipoteze!$C$118)+'Break-even'!$C$18)/Ipoteze!$C$90+'Break-even'!$C$20+(G51-1)*'Break-even'!$C$21+G51*'Break-even'!$C$19+(E51*Ipoteze!$C$134+Ipoteze!$C$135)*'Break-even'!$C$22+Ipoteze!$C$124*E51*'Break-even'!$C$17+Ipoteze!$C$123*Ipoteze!$C$8+Ipoteze!$C$136 -> 96050.317 | I51: =IF(B51>=4,INDEX('Break-even'!$C$8:$F$8,1,4),INDEX('Break-even'!$C$8:$F$8,1,B51)+(INDEX('Break-even'!$C$8:$F$8,1,B51+1)-INDEX('Break-even'!$C$8:$F$8,1,B51))*LN(A51/INDEX('Break-even'!$C$6:$F$6,1,B51))/LN(INDEX('Break-even'!$C$6:$F$6,1,B51+1)/INDEX('Break-even'!$C$6:$F$6,1,B51))) -> 8.1206488 | J51: =H51+A51*I51 -> 177256.8 | K51: =J51/A51 -> 17.72568 | L51: =D51-J51 -> 33808.646 | M51: =IF(J51<D51,1,0) -> 1
A52: 15000 | B52: =MATCH(A52,'Break-even'!$C$6:$F$6,1) -> 3 | C52: =IF(B52>=4,INDEX('Break-even'!$C$7:$F$7,1,4),INDEX('Break-even'!$C$7:$F$7,1,B52)+(INDEX('Break-even'!$C$7:$F$7,1,B52+1)-INDEX('Break-even'!$C$7:$F$7,1,B52))*LN(A52/INDEX('Break-even'!$C$6:$F$6,1,B52))/LN(INDEX('Break-even'!$C$6:$F$6,1,B52+1)/INDEX('Break-even'!$C$6:$F$6,1,B52))) -> 19.720087 | D52: =A52*C52 -> 295801.31 | E52: =CEILING(A52/('Break-even'!$C$23*Ipoteze!$C$20),1) -> 3 | F52: =MIN(Ipoteze!$C$20,CEILING(A52/('Break-even'!$C$23*E52),1)) -> 2 | G52: =F52*CEILING(E52/Ipoteze!$C$137,1) -> 4 | H52: =(E52*('Break-even'!$C$17+Ipoteze!$C$118)+'Break-even'!$C$18)/Ipoteze!$C$90+'Break-even'!$C$20+(G52-1)*'Break-even'!$C$21+G52*'Break-even'!$C$19+(E52*Ipoteze!$C$134+Ipoteze!$C$135)*'Break-even'!$C$22+Ipoteze!$C$124*E52*'Break-even'!$C$17+Ipoteze!$C$123*Ipoteze!$C$8+Ipoteze!$C$136 -> 149866.26 | I52: =IF(B52>=4,INDEX('Break-even'!$C$8:$F$8,1,4),INDEX('Break-even'!$C$8:$F$8,1,B52)+(INDEX('Break-even'!$C$8:$F$8,1,B52+1)-INDEX('Break-even'!$C$8:$F$8,1,B52))*LN(A52/INDEX('Break-even'!$C$6:$F$6,1,B52))/LN(INDEX('Break-even'!$C$6:$F$6,1,B52+1)/INDEX('Break-even'!$C$6:$F$6,1,B52))) -> 7.891051 | J52: =H52+A52*I52 -> 268232.03 | K52: =J52/A52 -> 17.882135 | L52: =D52-J52 -> 27569.28 | M52: =IF(J52<D52,1,0) -> 1
A53: 20000 | B53: =MATCH(A53,'Break-even'!$C$6:$F$6,1) -> 4 | C53: =IF(B53>=4,INDEX('Break-even'!$C$7:$F$7,1,4),INDEX('Break-even'!$C$7:$F$7,1,B53)+(INDEX('Break-even'!$C$7:$F$7,1,B53+1)-INDEX('Break-even'!$C$7:$F$7,1,B53))*LN(A53/INDEX('Break-even'!$C$6:$F$6,1,B53))/LN(INDEX('Break-even'!$C$6:$F$6,1,B53+1)/INDEX('Break-even'!$C$6:$F$6,1,B53))) -> 18.73638 | D53: =A53*C53 -> 374727.6 | E53: =CEILING(A53/('Break-even'!$C$23*Ipoteze!$C$20),1) -> 3 | F53: =MIN(Ipoteze!$C$20,CEILING(A53/('Break-even'!$C$23*E53),1)) -> 2 | G53: =F53*CEILING(E53/Ipoteze!$C$137,1) -> 4 | H53: =(E53*('Break-even'!$C$17+Ipoteze!$C$118)+'Break-even'!$C$18)/Ipoteze!$C$90+'Break-even'!$C$20+(G53-1)*'Break-even'!$C$21+G53*'Break-even'!$C$19+(E53*Ipoteze!$C$134+Ipoteze!$C$135)*'Break-even'!$C$22+Ipoteze!$C$124*E53*'Break-even'!$C$17+Ipoteze!$C$123*Ipoteze!$C$8+Ipoteze!$C$136 -> 149866.26 | I53: =IF(B53>=4,INDEX('Break-even'!$C$8:$F$8,1,4),INDEX('Break-even'!$C$8:$F$8,1,B53)+(INDEX('Break-even'!$C$8:$F$8,1,B53+1)-INDEX('Break-even'!$C$8:$F$8,1,B53))*LN(A53/INDEX('Break-even'!$C$6:$F$6,1,B53))/LN(INDEX('Break-even'!$C$6:$F$6,1,B53+1)/INDEX('Break-even'!$C$6:$F$6,1,B53))) -> 7.7281488 | J53: =H53+A53*I53 -> 304429.24 | K53: =J53/A53 -> 15.221462 | L53: =D53-J53 -> 70298.357 | M53: =IF(J53<D53,1,0) -> 1
B54: Primul volum din grilă la care producția proprie e mai ieftină | C54: =IFERROR(INDEX(A41:A53,MATCH(1,M41:M53,0)),"peste 20.000") -> 5000
B55: Volume din grilă unde e mai ieftin (număr din 13) | C55: =SUM(M41:M53) -> 5
A57: 5. Grilă CNC mărimea M, prototipul (comparație: ciclu 45 min, 1,0 kg, preț extern ×1,54)
A58: Volum (seturi/an) | B58: Treaptă | C58: Cumpărat €/set | D58: Cumpărat €/an | E58: Mașini | F58: Schimburi | G58: Operatori | H58: Fix propriu €/an | I58: Variabil propriu €/set | J58: Propriu €/an | K58: Propriu €/set | L58: Economie €/an | M58: Propriu mai ieftin?
A59: 250 | B59: =MATCH(A59,'Break-even'!$C$6:$F$6,1) -> 1 | C59: =IF(B59>=4,INDEX('Break-even'!$C$10:$F$10,1,4),INDEX('Break-even'!$C$10:$F$10,1,B59)+(INDEX('Break-even'!$C$10:$F$10,1,B59+1)-INDEX('Break-even'!$C$10:$F$10,1,B59))*LN(A59/INDEX('Break-even'!$C$6:$F$6,1,B59))/LN(INDEX('Break-even'!$C$6:$F$6,1,B59+1)/INDEX('Break-even'!$C$6:$F$6,1,B59))) -> 85.773739 | D59: =A59*C59 -> 21443.435 | E59: =CEILING(A59/('Break-even'!$C$24*Ipoteze!$C$20),1) -> 1 | F59: =MIN(Ipoteze!$C$20,CEILING(A59/('Break-even'!$C$24*E59),1)) -> 1 | G59: =F59*CEILING(E59/Ipoteze!$C$137,1) -> 1 | H59: =(E59*('Break-even'!$C$17+Ipoteze!$C$118)+'Break-even'!$C$18)/Ipoteze!$C$90+'Break-even'!$C$20+(G59-1)*'Break-even'!$C$21+G59*'Break-even'!$C$19+(E59*Ipoteze!$C$134+Ipoteze!$C$135)*'Break-even'!$C$22+Ipoteze!$C$124*E59*'Break-even'!$C$17+Ipoteze!$C$123*Ipoteze!$C$8+Ipoteze!$C$136 -> 56858.684 | I59: =IF(B59>=4,INDEX('Break-even'!$C$11:$F$11,1,4),INDEX('Break-even'!$C$11:$F$11,1,B59)+(INDEX('Break-even'!$C$11:$F$11,1,B59+1)-INDEX('Break-even'!$C$11:$F$11,1,B59))*LN(A59/INDEX('Break-even'!$C$6:$F$6,1,B59))/LN(INDEX('Break-even'!$C$6:$F$6,1,B59+1)/INDEX('Break-even'!$C$6:$F$6,1,B59))) -> 18.853205 | J59: =H59+A59*I59 -> 61571.985 | K59: =J59/A59 -> 246.28794 | L59: =D59-J59 -> -40128.55 | M59: =IF(J59<D59,1,0) -> 0
A60: 500 | B60: =MATCH(A60,'Break-even'!$C$6:$F$6,1) -> 1 | C60: =IF(B60>=4,INDEX('Break-even'!$C$10:$F$10,1,4),INDEX('Break-even'!$C$10:$F$10,1,B60)+(INDEX('Break-even'!$C$10:$F$10,1,B60+1)-INDEX('Break-even'!$C$10:$F$10,1,B60))*LN(A60/INDEX('Break-even'!$C$6:$F$6,1,B60))/LN(INDEX('Break-even'!$C$6:$F$6,1,B60+1)/INDEX('Break-even'!$C$6:$F$6,1,B60))) -> 67.405844 | D60: =A60*C60 -> 33702.922 | E60: =CEILING(A60/('Break-even'!$C$24*Ipoteze!$C$20),1) -> 1 | F60: =MIN(Ipoteze!$C$20,CEILING(A60/('Break-even'!$C$24*E60),1)) -> 1 | G60: =F60*CEILING(E60/Ipoteze!$C$137,1) -> 1 | H60: =(E60*('Break-even'!$C$17+Ipoteze!$C$118)+'Break-even'!$C$18)/Ipoteze!$C$90+'Break-even'!$C$20+(G60-1)*'Break-even'!$C$21+G60*'Break-even'!$C$19+(E60*Ipoteze!$C$134+Ipoteze!$C$135)*'Break-even'!$C$22+Ipoteze!$C$124*E60*'Break-even'!$C$17+Ipoteze!$C$123*Ipoteze!$C$8+Ipoteze!$C$136 -> 56858.684 | I60: =IF(B60>=4,INDEX('Break-even'!$C$11:$F$11,1,4),INDEX('Break-even'!$C$11:$F$11,1,B60)+(INDEX('Break-even'!$C$11:$F$11,1,B60+1)-INDEX('Break-even'!$C$11:$F$11,1,B60))*LN(A60/INDEX('Break-even'!$C$6:$F$6,1,B60))/LN(INDEX('Break-even'!$C$6:$F$6,1,B60+1)/INDEX('Break-even'!$C$6:$F$6,1,B60))) -> 18.551874 | J60: =H60+A60*I60 -> 66134.621 | K60: =J60/A60 -> 132.26924 | L60: =D60-J60 -> -32431.699 | M60: =IF(J60<D60,1,0) -> 0
A61: 1000 | B61: =MATCH(A61,'Break-even'!$C$6:$F$6,1) -> 2 | C61: =IF(B61>=4,INDEX('Break-even'!$C$10:$F$10,1,4),INDEX('Break-even'!$C$10:$F$10,1,B61)+(INDEX('Break-even'!$C$10:$F$10,1,B61+1)-INDEX('Break-even'!$C$10:$F$10,1,B61))*LN(A61/INDEX('Break-even'!$C$6:$F$6,1,B61))/LN(INDEX('Break-even'!$C$6:$F$6,1,B61+1)/INDEX('Break-even'!$C$6:$F$6,1,B61))) -> 49.037949 | D61: =A61*C61 -> 49037.949 | E61: =CEILING(A61/('Break-even'!$C$24*Ipoteze!$C$20),1) -> 1 | F61: =MIN(Ipoteze!$C$20,CEILING(A61/('Break-even'!$C$24*E61),1)) -> 1 | G61: =F61*CEILING(E61/Ipoteze!$C$137,1) -> 1 | H61: =(E61*('Break-even'!$C$17+Ipoteze!$C$118)+'Break-even'!$C$18)/Ipoteze!$C$90+'Break-even'!$C$20+(G61-1)*'Break-even'!$C$21+G61*'Break-even'!$C$19+(E61*Ipoteze!$C$134+Ipoteze!$C$135)*'Break-even'!$C$22+Ipoteze!$C$124*E61*'Break-even'!$C$17+Ipoteze!$C$123*Ipoteze!$C$8+Ipoteze!$C$136 -> 56858.684 | I61: =IF(B61>=4,INDEX('Break-even'!$C$11:$F$11,1,4),INDEX('Break-even'!$C$11:$F$11,1,B61)+(INDEX('Break-even'!$C$11:$F$11,1,B61+1)-INDEX('Break-even'!$C$11:$F$11,1,B61))*LN(A61/INDEX('Break-even'!$C$6:$F$6,1,B61))/LN(INDEX('Break-even'!$C$6:$F$6,1,B61+1)/INDEX('Break-even'!$C$6:$F$6,1,B61))) -> 18.250542 | J61: =H61+A61*I61 -> 75109.227 | K61: =J61/A61 -> 75.109227 | L61: =D61-J61 -> -26071.278 | M61: =IF(J61<D61,1,0) -> 0
A62: 1500 | B62: =MATCH(A62,'Break-even'!$C$6:$F$6,1) -> 2 | C62: =IF(B62>=4,INDEX('Break-even'!$C$10:$F$10,1,4),INDEX('Break-even'!$C$10:$F$10,1,B62)+(INDEX('Break-even'!$C$10:$F$10,1,B62+1)-INDEX('Break-even'!$C$10:$F$10,1,B62))*LN(A62/INDEX('Break-even'!$C$6:$F$6,1,B62))/LN(INDEX('Break-even'!$C$6:$F$6,1,B62+1)/INDEX('Break-even'!$C$6:$F$6,1,B62))) -> 45.792134 | D62: =A62*C62 -> 68688.201 | E62: =CEILING(A62/('Break-even'!$C$24*Ipoteze!$C$20),1) -> 1 | F62: =MIN(Ipoteze!$C$20,CEILING(A62/('Break-even'!$C$24*E62),1)) -> 1 | G62: =F62*CEILING(E62/Ipoteze!$C$137,1) -> 1 | H62: =(E62*('Break-even'!$C$17+Ipoteze!$C$118)+'Break-even'!$C$18)/Ipoteze!$C$90+'Break-even'!$C$20+(G62-1)*'Break-even'!$C$21+G62*'Break-even'!$C$19+(E62*Ipoteze!$C$134+Ipoteze!$C$135)*'Break-even'!$C$22+Ipoteze!$C$124*E62*'Break-even'!$C$17+Ipoteze!$C$123*Ipoteze!$C$8+Ipoteze!$C$136 -> 56858.684 | I62: =IF(B62>=4,INDEX('Break-even'!$C$11:$F$11,1,4),INDEX('Break-even'!$C$11:$F$11,1,B62)+(INDEX('Break-even'!$C$11:$F$11,1,B62+1)-INDEX('Break-even'!$C$11:$F$11,1,B62))*LN(A62/INDEX('Break-even'!$C$6:$F$6,1,B62))/LN(INDEX('Break-even'!$C$6:$F$6,1,B62+1)/INDEX('Break-even'!$C$6:$F$6,1,B62))) -> 17.729109 | J62: =H62+A62*I62 -> 83452.347 | K62: =J62/A62 -> 55.634898 | L62: =D62-J62 -> -14764.146 | M62: =IF(J62<D62,1,0) -> 0
A63: 2000 | B63: =MATCH(A63,'Break-even'!$C$6:$F$6,1) -> 2 | C63: =IF(B63>=4,INDEX('Break-even'!$C$10:$F$10,1,4),INDEX('Break-even'!$C$10:$F$10,1,B63)+(INDEX('Break-even'!$C$10:$F$10,1,B63+1)-INDEX('Break-even'!$C$10:$F$10,1,B63))*LN(A63/INDEX('Break-even'!$C$6:$F$6,1,B63))/LN(INDEX('Break-even'!$C$6:$F$6,1,B63+1)/INDEX('Break-even'!$C$6:$F$6,1,B63))) -> 43.489192 | D63: =A63*C63 -> 86978.384 | E63: =CEILING(A63/('Break-even'!$C$24*Ipoteze!$C$20),1) -> 1 | F63: =MIN(Ipoteze!$C$20,CEILING(A63/('Break-even'!$C$24*E63),1)) -> 2 | G63: =F63*CEILING(E63/Ipoteze!$C$137,1) -> 2 | H63: =(E63*('Break-even'!$C$17+Ipoteze!$C$118)+'Break-even'!$C$18)/Ipoteze!$C$90+'Break-even'!$C$20+(G63-1)*'Break-even'!$C$21+G63*'Break-even'!$C$19+(E63*Ipoteze!$C$134+Ipoteze!$C$135)*'Break-even'!$C$22+Ipoteze!$C$124*E63*'Break-even'!$C$17+Ipoteze!$C$123*Ipoteze!$C$8+Ipoteze!$C$136 -> 71482.998 | I63: =IF(B63>=4,INDEX('Break-even'!$C$11:$F$11,1,4),INDEX('Break-even'!$C$11:$F$11,1,B63)+(INDEX('Break-even'!$C$11:$F$11,1,B63+1)-INDEX('Break-even'!$C$11:$F$11,1,B63))*LN(A63/INDEX('Break-even'!$C$6:$F$6,1,B63))/LN(INDEX('Break-even'!$C$6:$F$6,1,B63+1)/INDEX('Break-even'!$C$6:$F$6,1,B63))) -> 17.359145 | J63: =H63+A63*I63 -> 106201.29 | K63: =J63/A63 -> 53.100644 | L63: =D63-J63 -> -19222.905 | M63: =IF(J63<D63,1,0) -> 0
A64: 2500 | B64: =MATCH(A64,'Break-even'!$C$6:$F$6,1) -> 2 | C64: =IF(B64>=4,INDEX('Break-even'!$C$10:$F$10,1,4),INDEX('Break-even'!$C$10:$F$10,1,B64)+(INDEX('Break-even'!$C$10:$F$10,1,B64+1)-INDEX('Break-even'!$C$10:$F$10,1,B64))*LN(A64/INDEX('Break-even'!$C$6:$F$6,1,B64))/LN(INDEX('Break-even'!$C$6:$F$6,1,B64+1)/INDEX('Break-even'!$C$6:$F$6,1,B64))) -> 41.702891 | D64: =A64*C64 -> 104257.23 | E64: =CEILING(A64/('Break-even'!$C$24*Ipoteze!$C$20),1) -> 1 | F64: =MIN(Ipoteze!$C$20,CEILING(A64/('Break-even'!$C$24*E64),1)) -> 2 | G64: =F64*CEILING(E64/Ipoteze!$C$137,1) -> 2 | H64: =(E64*('Break-even'!$C$17+Ipoteze!$C$118)+'Break-even'!$C$18)/Ipoteze!$C$90+'Break-even'!$C$20+(G64-1)*'Break-even'!$C$21+G64*'Break-even'!$C$19+(E64*Ipoteze!$C$134+Ipoteze!$C$135)*'Break-even'!$C$22+Ipoteze!$C$124*E64*'Break-even'!$C$17+Ipoteze!$C$123*Ipoteze!$C$8+Ipoteze!$C$136 -> 71482.998 | I64: =IF(B64>=4,INDEX('Break-even'!$C$11:$F$11,1,4),INDEX('Break-even'!$C$11:$F$11,1,B64)+(INDEX('Break-even'!$C$11:$F$11,1,B64+1)-INDEX('Break-even'!$C$11:$F$11,1,B64))*LN(A64/INDEX('Break-even'!$C$6:$F$6,1,B64))/LN(INDEX('Break-even'!$C$6:$F$6,1,B64+1)/INDEX('Break-even'!$C$6:$F$6,1,B64))) -> 17.07218 | J64: =H64+A64*I64 -> 114163.45 | K64: =J64/A64 -> 45.665379 | L64: =D64-J64 -> -9906.2191 | M64: =IF(J64<D64,1,0) -> 0
A65: 3000 | B65: =MATCH(A65,'Break-even'!$C$6:$F$6,1) -> 2 | C65: =IF(B65>=4,INDEX('Break-even'!$C$10:$F$10,1,4),INDEX('Break-even'!$C$10:$F$10,1,B65)+(INDEX('Break-even'!$C$10:$F$10,1,B65+1)-INDEX('Break-even'!$C$10:$F$10,1,B65))*LN(A65/INDEX('Break-even'!$C$6:$F$6,1,B65))/LN(INDEX('Break-even'!$C$6:$F$6,1,B65+1)/INDEX('Break-even'!$C$6:$F$6,1,B65))) -> 40.243377 | D65: =A65*C65 -> 120730.13 | E65: =CEILING(A65/('Break-even'!$C$24*Ipoteze!$C$20),1) -> 1 | F65: =MIN(Ipoteze!$C$20,CEILING(A65/('Break-even'!$C$24*E65),1)) -> 2 | G65: =F65*CEILING(E65/Ipoteze!$C$137,1) -> 2 | H65: =(E65*('Break-even'!$C$17+Ipoteze!$C$118)+'Break-even'!$C$18)/Ipoteze!$C$90+'Break-even'!$C$20+(G65-1)*'Break-even'!$C$21+G65*'Break-even'!$C$19+(E65*Ipoteze!$C$134+Ipoteze!$C$135)*'Break-even'!$C$22+Ipoteze!$C$124*E65*'Break-even'!$C$17+Ipoteze!$C$123*Ipoteze!$C$8+Ipoteze!$C$136 -> 71482.998 | I65: =IF(B65>=4,INDEX('Break-even'!$C$11:$F$11,1,4),INDEX('Break-even'!$C$11:$F$11,1,B65)+(INDEX('Break-even'!$C$11:$F$11,1,B65+1)-INDEX('Break-even'!$C$11:$F$11,1,B65))*LN(A65/INDEX('Break-even'!$C$6:$F$6,1,B65))/LN(INDEX('Break-even'!$C$6:$F$6,1,B65+1)/INDEX('Break-even'!$C$6:$F$6,1,B65))) -> 16.837711 | J65: =H65+A65*I65 -> 121996.13 | K65: =J65/A65 -> 40.665377 | L65: =D65-J65 -> -1266.0011 | M65: =IF(J65<D65,1,0) -> 0
A66: 4000 | B66: =MATCH(A66,'Break-even'!$C$6:$F$6,1) -> 2 | C66: =IF(B66>=4,INDEX('Break-even'!$C$10:$F$10,1,4),INDEX('Break-even'!$C$10:$F$10,1,B66)+(INDEX('Break-even'!$C$10:$F$10,1,B66+1)-INDEX('Break-even'!$C$10:$F$10,1,B66))*LN(A66/INDEX('Break-even'!$C$6:$F$6,1,B66))/LN(INDEX('Break-even'!$C$6:$F$6,1,B66+1)/INDEX('Break-even'!$C$6:$F$6,1,B66))) -> 37.940435 | D66: =A66*C66 -> 151761.74 | E66: =CEILING(A66/('Break-even'!$C$24*Ipoteze!$C$20),1) -> 2 | F66: =MIN(Ipoteze!$C$20,CEILING(A66/('Break-even'!$C$24*E66),1)) -> 2 | G66: =F66*CEILING(E66/Ipoteze!$C$137,1) -> 2 | H66: =(E66*('Break-even'!$C$17+Ipoteze!$C$118)+'Break-even'!$C$18)/Ipoteze!$C$90+'Break-even'!$C$20+(G66-1)*'Break-even'!$C$21+G66*'Break-even'!$C$19+(E66*Ipoteze!$C$134+Ipoteze!$C$135)*'Break-even'!$C$22+Ipoteze!$C$124*E66*'Break-even'!$C$17+Ipoteze!$C$123*Ipoteze!$C$8+Ipoteze!$C$136 -> 96050.317 | I66: =IF(B66>=4,INDEX('Break-even'!$C$11:$F$11,1,4),INDEX('Break-even'!$C$11:$F$11,1,B66)+(INDEX('Break-even'!$C$11:$F$11,1,B66+1)-INDEX('Break-even'!$C$11:$F$11,1,B66))*LN(A66/INDEX('Break-even'!$C$6:$F$6,1,B66))/LN(INDEX('Break-even'!$C$6:$F$6,1,B66+1)/INDEX('Break-even'!$C$6:$F$6,1,B66))) -> 16.467748 | J66: =H66+A66*I66 -> 161921.31 | K66: =J66/A66 -> 40.480328 | L66: =D66-J66 -> -10159.571 | M66: =IF(J66<D66,1,0) -> 0
A67: 5000 | B67: =MATCH(A67,'Break-even'!$C$6:$F$6,1) -> 3 | C67: =IF(B67>=4,INDEX('Break-even'!$C$10:$F$10,1,4),INDEX('Break-even'!$C$10:$F$10,1,B67)+(INDEX('Break-even'!$C$10:$F$10,1,B67+1)-INDEX('Break-even'!$C$10:$F$10,1,B67))*LN(A67/INDEX('Break-even'!$C$6:$F$6,1,B67))/LN(INDEX('Break-even'!$C$6:$F$6,1,B67+1)/INDEX('Break-even'!$C$6:$F$6,1,B67))) -> 36.154134 | D67: =A67*C67 -> 180770.67 | E67: =CEILING(A67/('Break-even'!$C$24*Ipoteze!$C$20),1) -> 2 | F67: =MIN(Ipoteze!$C$20,CEILING(A67/('Break-even'!$C$24*E67),1)) -> 2 | G67: =F67*CEILING(E67/Ipoteze!$C$137,1) -> 2 | H67: =(E67*('Break-even'!$C$17+Ipoteze!$C$118)+'Break-even'!$C$18)/Ipoteze!$C$90+'Break-even'!$C$20+(G67-1)*'Break-even'!$C$21+G67*'Break-even'!$C$19+(E67*Ipoteze!$C$134+Ipoteze!$C$135)*'Break-even'!$C$22+Ipoteze!$C$124*E67*'Break-even'!$C$17+Ipoteze!$C$123*Ipoteze!$C$8+Ipoteze!$C$136 -> 96050.317 | I67: =IF(B67>=4,INDEX('Break-even'!$C$11:$F$11,1,4),INDEX('Break-even'!$C$11:$F$11,1,B67)+(INDEX('Break-even'!$C$11:$F$11,1,B67+1)-INDEX('Break-even'!$C$11:$F$11,1,B67))*LN(A67/INDEX('Break-even'!$C$6:$F$6,1,B67))/LN(INDEX('Break-even'!$C$6:$F$6,1,B67+1)/INDEX('Break-even'!$C$6:$F$6,1,B67))) -> 16.180782 | J67: =H67+A67*I67 -> 176954.23 | K67: =J67/A67 -> 35.390846 | L67: =D67-J67 -> 3816.4404 | M67: =IF(J67<D67,1,0) -> 1
A68: 7500 | B68: =MATCH(A68,'Break-even'!$C$6:$F$6,1) -> 3 | C68: =IF(B68>=4,INDEX('Break-even'!$C$10:$F$10,1,4),INDEX('Break-even'!$C$10:$F$10,1,B68)+(INDEX('Break-even'!$C$10:$F$10,1,B68+1)-INDEX('Break-even'!$C$10:$F$10,1,B68))*LN(A68/INDEX('Break-even'!$C$6:$F$6,1,B68))/LN(INDEX('Break-even'!$C$6:$F$6,1,B68+1)/INDEX('Break-even'!$C$6:$F$6,1,B68))) -> 34.018989 | D68: =A68*C68 -> 255142.42 | E68: =CEILING(A68/('Break-even'!$C$24*Ipoteze!$C$20),1) -> 2 | F68: =MIN(Ipoteze!$C$20,CEILING(A68/('Break-even'!$C$24*E68),1)) -> 2 | G68: =F68*CEILING(E68/Ipoteze!$C$137,1) -> 2 | H68: =(E68*('Break-even'!$C$17+Ipoteze!$C$118)+'Break-even'!$C$18)/Ipoteze!$C$90+'Break-even'!$C$20+(G68-1)*'Break-even'!$C$21+G68*'Break-even'!$C$19+(E68*Ipoteze!$C$134+Ipoteze!$C$135)*'Break-even'!$C$22+Ipoteze!$C$124*E68*'Break-even'!$C$17+Ipoteze!$C$123*Ipoteze!$C$8+Ipoteze!$C$136 -> 96050.317 | I68: =IF(B68>=4,INDEX('Break-even'!$C$11:$F$11,1,4),INDEX('Break-even'!$C$11:$F$11,1,B68)+(INDEX('Break-even'!$C$11:$F$11,1,B68+1)-INDEX('Break-even'!$C$11:$F$11,1,B68))*LN(A68/INDEX('Break-even'!$C$6:$F$6,1,B68))/LN(INDEX('Break-even'!$C$6:$F$6,1,B68+1)/INDEX('Break-even'!$C$6:$F$6,1,B68))) -> 15.827202 | J68: =H68+A68*I68 -> 214754.33 | K68: =J68/A68 -> 28.633911 | L68: =D68-J68 -> 40388.086 | M68: =IF(J68<D68,1,0) -> 1
A69: 10000 | B69: =MATCH(A69,'Break-even'!$C$6:$F$6,1) -> 3 | C69: =IF(B69>=4,INDEX('Break-even'!$C$10:$F$10,1,4),INDEX('Break-even'!$C$10:$F$10,1,B69)+(INDEX('Break-even'!$C$10:$F$10,1,B69+1)-INDEX('Break-even'!$C$10:$F$10,1,B69))*LN(A69/INDEX('Break-even'!$C$6:$F$6,1,B69))/LN(INDEX('Break-even'!$C$6:$F$6,1,B69+1)/INDEX('Break-even'!$C$6:$F$6,1,B69))) -> 32.504079 | D69: =A69*C69 -> 325040.79 | E69: =CEILING(A69/('Break-even'!$C$24*Ipoteze!$C$20),1) -> 3 | F69: =MIN(Ipoteze!$C$20,CEILING(A69/('Break-even'!$C$24*E69),1)) -> 2 | G69: =F69*CEILING(E69/Ipoteze!$C$137,1) -> 4 | H69: =(E69*('Break-even'!$C$17+Ipoteze!$C$118)+'Break-even'!$C$18)/Ipoteze!$C$90+'Break-even'!$C$20+(G69-1)*'Break-even'!$C$21+G69*'Break-even'!$C$19+(E69*Ipoteze!$C$134+Ipoteze!$C$135)*'Break-even'!$C$22+Ipoteze!$C$124*E69*'Break-even'!$C$17+Ipoteze!$C$123*Ipoteze!$C$8+Ipoteze!$C$136 -> 149866.26 | I69: =IF(B69>=4,INDEX('Break-even'!$C$11:$F$11,1,4),INDEX('Break-even'!$C$11:$F$11,1,B69)+(INDEX('Break-even'!$C$11:$F$11,1,B69+1)-INDEX('Break-even'!$C$11:$F$11,1,B69))*LN(A69/INDEX('Break-even'!$C$6:$F$6,1,B69))/LN(INDEX('Break-even'!$C$6:$F$6,1,B69+1)/INDEX('Break-even'!$C$6:$F$6,1,B69))) -> 15.576332 | J69: =H69+A69*I69 -> 305629.59 | K69: =J69/A69 -> 30.562959 | L69: =D69-J69 -> 19411.206 | M69: =IF(J69<D69,1,0) -> 1
A70: 15000 | B70: =MATCH(A70,'Break-even'!$C$6:$F$6,1) -> 3 | C70: =IF(B70>=4,INDEX('Break-even'!$C$10:$F$10,1,4),INDEX('Break-even'!$C$10:$F$10,1,B70)+(INDEX('Break-even'!$C$10:$F$10,1,B70+1)-INDEX('Break-even'!$C$10:$F$10,1,B70))*LN(A70/INDEX('Break-even'!$C$6:$F$6,1,B70))/LN(INDEX('Break-even'!$C$6:$F$6,1,B70+1)/INDEX('Break-even'!$C$6:$F$6,1,B70))) -> 30.368934 | D70: =A70*C70 -> 455534.02 | E70: =CEILING(A70/('Break-even'!$C$24*Ipoteze!$C$20),1) -> 4 | F70: =MIN(Ipoteze!$C$20,CEILING(A70/('Break-even'!$C$24*E70),1)) -> 2 | G70: =F70*CEILING(E70/Ipoteze!$C$137,1) -> 4 | H70: =(E70*('Break-even'!$C$17+Ipoteze!$C$118)+'Break-even'!$C$18)/Ipoteze!$C$90+'Break-even'!$C$20+(G70-1)*'Break-even'!$C$21+G70*'Break-even'!$C$19+(E70*Ipoteze!$C$134+Ipoteze!$C$135)*'Break-even'!$C$22+Ipoteze!$C$124*E70*'Break-even'!$C$17+Ipoteze!$C$123*Ipoteze!$C$8+Ipoteze!$C$136 -> 174433.58 | I70: =IF(B70>=4,INDEX('Break-even'!$C$11:$F$11,1,4),INDEX('Break-even'!$C$11:$F$11,1,B70)+(INDEX('Break-even'!$C$11:$F$11,1,B70+1)-INDEX('Break-even'!$C$11:$F$11,1,B70))*LN(A70/INDEX('Break-even'!$C$6:$F$6,1,B70))/LN(INDEX('Break-even'!$C$6:$F$6,1,B70+1)/INDEX('Break-even'!$C$6:$F$6,1,B70))) -> 15.222752 | J70: =H70+A70*I70 -> 402774.86 | K70: =J70/A70 -> 26.851657 | L70: =D70-J70 -> 52759.154 | M70: =IF(J70<D70,1,0) -> 1
A71: 20000 | B71: =MATCH(A71,'Break-even'!$C$6:$F$6,1) -> 4 | C71: =IF(B71>=4,INDEX('Break-even'!$C$10:$F$10,1,4),INDEX('Break-even'!$C$10:$F$10,1,B71)+(INDEX('Break-even'!$C$10:$F$10,1,B71+1)-INDEX('Break-even'!$C$10:$F$10,1,B71))*LN(A71/INDEX('Break-even'!$C$6:$F$6,1,B71))/LN(INDEX('Break-even'!$C$6:$F$6,1,B71+1)/INDEX('Break-even'!$C$6:$F$6,1,B71))) -> 28.854025 | D71: =A71*C71 -> 577080.5 | E71: =CEILING(A71/('Break-even'!$C$24*Ipoteze!$C$20),1) -> 6 | F71: =MIN(Ipoteze!$C$20,CEILING(A71/('Break-even'!$C$24*E71),1)) -> 2 | G71: =F71*CEILING(E71/Ipoteze!$C$137,1) -> 6 | H71: =(E71*('Break-even'!$C$17+Ipoteze!$C$118)+'Break-even'!$C$18)/Ipoteze!$C$90+'Break-even'!$C$20+(G71-1)*'Break-even'!$C$21+G71*'Break-even'!$C$19+(E71*Ipoteze!$C$134+Ipoteze!$C$135)*'Break-even'!$C$22+Ipoteze!$C$124*E71*'Break-even'!$C$17+Ipoteze!$C$123*Ipoteze!$C$8+Ipoteze!$C$136 -> 252816.85 | I71: =IF(B71>=4,INDEX('Break-even'!$C$11:$F$11,1,4),INDEX('Break-even'!$C$11:$F$11,1,B71)+(INDEX('Break-even'!$C$11:$F$11,1,B71+1)-INDEX('Break-even'!$C$11:$F$11,1,B71))*LN(A71/INDEX('Break-even'!$C$6:$F$6,1,B71))/LN(INDEX('Break-even'!$C$6:$F$6,1,B71+1)/INDEX('Break-even'!$C$6:$F$6,1,B71))) -> 14.971882 | J71: =H71+A71*I71 -> 552254.5 | K71: =J71/A71 -> 27.612725 | L71: =D71-J71 -> 24825.998 | M71: =IF(J71<D71,1,0) -> 1
B72: Primul volum din grilă la care producția proprie e mai ieftină | C72: =IFERROR(INDEX(A59:A71,MATCH(1,M59:M71,0)),"peste 20.000") -> 5000
B73: Volume din grilă unde e mai ieftin (număr din 13) | C73: =SUM(M59:M71) -> 5
A75: 6. Grilă SMT (linie NeoDen4 + AOI) vs EMS România și vs JLCPCB
A76: Volum (plăci/an) | B76: Treaptă | C76: EMS RO €/placă | D76: JLC €/placă | E76: Linii | F76: Schimburi | G76: Tehnicieni | H76: Fix propriu €/an | I76: Variabil propriu €/placă | J76: Propriu €/an | K76: Propriu €/placă | L76: EMS €/an | M76: JLC €/an | N76: Bate EMS? | O76: Bate JLC?
A77: 500 | B77: =MATCH(A77,'Break-even'!$C$6:$F$6,1) -> 1 | C77: =IF(B77>=4,INDEX('Break-even'!$C$12:$F$12,1,4),INDEX('Break-even'!$C$12:$F$12,1,B77)+(INDEX('Break-even'!$C$12:$F$12,1,B77+1)-INDEX('Break-even'!$C$12:$F$12,1,B77))*LN(A77/INDEX('Break-even'!$C$6:$F$6,1,B77))/LN(INDEX('Break-even'!$C$6:$F$6,1,B77+1)/INDEX('Break-even'!$C$6:$F$6,1,B77))) -> 6.40824 | D77: =IF(B77>=4,INDEX('Break-even'!$C$13:$F$13,1,4),INDEX('Break-even'!$C$13:$F$13,1,B77)+(INDEX('Break-even'!$C$13:$F$13,1,B77+1)-INDEX('Break-even'!$C$13:$F$13,1,B77))*LN(A77/INDEX('Break-even'!$C$6:$F$6,1,B77))/LN(INDEX('Break-even'!$C$6:$F$6,1,B77+1)/INDEX('Break-even'!$C$6:$F$6,1,B77))) -> 1.110174 | E77: =CEILING(A77/('Break-even'!$C$26*Ipoteze!$C$20),1) -> 1 | F77: =MIN(Ipoteze!$C$20,CEILING(A77/('Break-even'!$C$26*E77),1)) -> 1 | G77: =E77*F77 -> 1 | H77: =E77*'Break-even'!$C$25/Ipoteze!$C$90+G77*('Break-even'!$C$27+'Break-even'!$C$19)+E77*Ipoteze!$C$155*'Break-even'!$C$22+Ipoteze!$C$124*E77*'Break-even'!$C$25+Ipoteze!$C$154*Ipoteze!$C$16*Ipoteze!$C$15*F77*E77*Ipoteze!$C$101/Ipoteze!$C$7+Ipoteze!$C$156 -> 29356.785 | I77: =IF(B77>=4,INDEX('Break-even'!$C$14:$F$14,1,4),INDEX('Break-even'!$C$14:$F$14,1,B77)+(INDEX('Break-even'!$C$14:$F$14,1,B77+1)-INDEX('Break-even'!$C$14:$F$14,1,B77))*LN(A77/INDEX('Break-even'!$C$6:$F$6,1,B77))/LN(INDEX('Break-even'!$C$6:$F$6,1,B77+1)/INDEX('Break-even'!$C$6:$F$6,1,B77))) -> 0.33632106 | J77: =H77+A77*I77 -> 29524.945 | K77: =J77/A77 -> 59.049891 | L77: =A77*C77 -> 3204.12 | M77: =A77*D77 -> 555.08701 | N77: =IF(J77<L77,1,0) -> 0 | O77: =IF(J77<M77,1,0) -> 0
A78: 1000 | B78: =MATCH(A78,'Break-even'!$C$6:$F$6,1) -> 2 | C78: =IF(B78>=4,INDEX('Break-even'!$C$12:$F$12,1,4),INDEX('Break-even'!$C$12:$F$12,1,B78)+(INDEX('Break-even'!$C$12:$F$12,1,B78+1)-INDEX('Break-even'!$C$12:$F$12,1,B78))*LN(A78/INDEX('Break-even'!$C$6:$F$6,1,B78))/LN(INDEX('Break-even'!$C$6:$F$6,1,B78+1)/INDEX('Break-even'!$C$6:$F$6,1,B78))) -> 4 | D78: =IF(B78>=4,INDEX('Break-even'!$C$13:$F$13,1,4),INDEX('Break-even'!$C$13:$F$13,1,B78)+(INDEX('Break-even'!$C$13:$F$13,1,B78+1)-INDEX('Break-even'!$C$13:$F$13,1,B78))*LN(A78/INDEX('Break-even'!$C$6:$F$6,1,B78))/LN(INDEX('Break-even'!$C$6:$F$6,1,B78+1)/INDEX('Break-even'!$C$6:$F$6,1,B78))) -> 0.94075688 | E78: =CEILING(A78/('Break-even'!$C$26*Ipoteze!$C$20),1) -> 1 | F78: =MIN(Ipoteze!$C$20,CEILING(A78/('Break-even'!$C$26*E78),1)) -> 1 | G78: =E78*F78 -> 1 | H78: =E78*'Break-even'!$C$25/Ipoteze!$C$90+G78*('Break-even'!$C$27+'Break-even'!$C$19)+E78*Ipoteze!$C$155*'Break-even'!$C$22+Ipoteze!$C$124*E78*'Break-even'!$C$25+Ipoteze!$C$154*Ipoteze!$C$16*Ipoteze!$C$15*F78*E78*Ipoteze!$C$101/Ipoteze!$C$7+Ipoteze!$C$156 -> 29356.785 | I78: =IF(B78>=4,INDEX('Break-even'!$C$14:$F$14,1,4),INDEX('Break-even'!$C$14:$F$14,1,B78)+(INDEX('Break-even'!$C$14:$F$14,1,B78+1)-INDEX('Break-even'!$C$14:$F$14,1,B78))*LN(A78/INDEX('Break-even'!$C$6:$F$6,1,B78))/LN(INDEX('Break-even'!$C$6:$F$6,1,B78+1)/INDEX('Break-even'!$C$6:$F$6,1,B78))) -> 0.320843 | J78: =H78+A78*I78 -> 29677.628 | K78: =J78/A78 -> 29.677628 | L78: =A78*C78 -> 4000 | M78: =A78*D78 -> 940.75688 | N78: =IF(J78<L78,1,0) -> 0 | O78: =IF(J78<M78,1,0) -> 0
A79: 2500 | B79: =MATCH(A79,'Break-even'!$C$6:$F$6,1) -> 2 | C79: =IF(B79>=4,INDEX('Break-even'!$C$12:$F$12,1,4),INDEX('Break-even'!$C$12:$F$12,1,B79)+(INDEX('Break-even'!$C$12:$F$12,1,B79+1)-INDEX('Break-even'!$C$12:$F$12,1,B79))*LN(A79/INDEX('Break-even'!$C$6:$F$6,1,B79))/LN(INDEX('Break-even'!$C$6:$F$6,1,B79+1)/INDEX('Break-even'!$C$6:$F$6,1,B79))) -> 3.1460148 | D79: =IF(B79>=4,INDEX('Break-even'!$C$13:$F$13,1,4),INDEX('Break-even'!$C$13:$F$13,1,B79)+(INDEX('Break-even'!$C$13:$F$13,1,B79+1)-INDEX('Break-even'!$C$13:$F$13,1,B79))*LN(A79/INDEX('Break-even'!$C$6:$F$6,1,B79))/LN(INDEX('Break-even'!$C$6:$F$6,1,B79+1)/INDEX('Break-even'!$C$6:$F$6,1,B79))) -> 0.77508729 | E79: =CEILING(A79/('Break-even'!$C$26*Ipoteze!$C$20),1) -> 1 | F79: =MIN(Ipoteze!$C$20,CEILING(A79/('Break-even'!$C$26*E79),1)) -> 1 | G79: =E79*F79 -> 1 | H79: =E79*'Break-even'!$C$25/Ipoteze!$C$90+G79*('Break-even'!$C$27+'Break-even'!$C$19)+E79*Ipoteze!$C$155*'Break-even'!$C$22+Ipoteze!$C$124*E79*'Break-even'!$C$25+Ipoteze!$C$154*Ipoteze!$C$16*Ipoteze!$C$15*F79*E79*Ipoteze!$C$101/Ipoteze!$C$7+Ipoteze!$C$156 -> 29356.785 | I79: =IF(B79>=4,INDEX('Break-even'!$C$14:$F$14,1,4),INDEX('Break-even'!$C$14:$F$14,1,B79)+(INDEX('Break-even'!$C$14:$F$14,1,B79+1)-INDEX('Break-even'!$C$14:$F$14,1,B79))*LN(A79/INDEX('Break-even'!$C$6:$F$6,1,B79))/LN(INDEX('Break-even'!$C$6:$F$6,1,B79+1)/INDEX('Break-even'!$C$6:$F$6,1,B79))) -> 0.31267036 | J79: =H79+A79*I79 -> 30138.461 | K79: =J79/A79 -> 12.055384 | L79: =A79*C79 -> 7865.0371 | M79: =A79*D79 -> 1937.7182 | N79: =IF(J79<L79,1,0) -> 0 | O79: =IF(J79<M79,1,0) -> 0
A80: 5000 | B80: =MATCH(A80,'Break-even'!$C$6:$F$6,1) -> 3 | C80: =IF(B80>=4,INDEX('Break-even'!$C$12:$F$12,1,4),INDEX('Break-even'!$C$12:$F$12,1,B80)+(INDEX('Break-even'!$C$12:$F$12,1,B80+1)-INDEX('Break-even'!$C$12:$F$12,1,B80))*LN(A80/INDEX('Break-even'!$C$6:$F$6,1,B80))/LN(INDEX('Break-even'!$C$6:$F$6,1,B80+1)/INDEX('Break-even'!$C$6:$F$6,1,B80))) -> 2.5 | D80: =IF(B80>=4,INDEX('Break-even'!$C$13:$F$13,1,4),INDEX('Break-even'!$C$13:$F$13,1,B80)+(INDEX('Break-even'!$C$13:$F$13,1,B80+1)-INDEX('Break-even'!$C$13:$F$13,1,B80))*LN(A80/INDEX('Break-even'!$C$6:$F$6,1,B80))/LN(INDEX('Break-even'!$C$6:$F$6,1,B80+1)/INDEX('Break-even'!$C$6:$F$6,1,B80))) -> 0.64976308 | E80: =CEILING(A80/('Break-even'!$C$26*Ipoteze!$C$20),1) -> 1 | F80: =MIN(Ipoteze!$C$20,CEILING(A80/('Break-even'!$C$26*E80),1)) -> 1 | G80: =E80*F80 -> 1 | H80: =E80*'Break-even'!$C$25/Ipoteze!$C$90+G80*('Break-even'!$C$27+'Break-even'!$C$19)+E80*Ipoteze!$C$155*'Break-even'!$C$22+Ipoteze!$C$124*E80*'Break-even'!$C$25+Ipoteze!$C$154*Ipoteze!$C$16*Ipoteze!$C$15*F80*E80*Ipoteze!$C$101/Ipoteze!$C$7+Ipoteze!$C$156 -> 29356.785 | I80: =IF(B80>=4,INDEX('Break-even'!$C$14:$F$14,1,4),INDEX('Break-even'!$C$14:$F$14,1,B80)+(INDEX('Break-even'!$C$14:$F$14,1,B80+1)-INDEX('Break-even'!$C$14:$F$14,1,B80))*LN(A80/INDEX('Break-even'!$C$6:$F$6,1,B80))/LN(INDEX('Break-even'!$C$6:$F$6,1,B80+1)/INDEX('Break-even'!$C$6:$F$6,1,B80))) -> 0.306488 | J80: =H80+A80*I80 -> 30889.225 | K80: =J80/A80 -> 6.177845 | L80: =A80*C80 -> 12500 | M80: =A80*D80 -> 3248.8154 | N80: =IF(J80<L80,1,0) -> 0 | O80: =IF(J80<M80,1,0) -> 0
A81: 7500 | B81: =MATCH(A81,'Break-even'!$C$6:$F$6,1) -> 3 | C81: =IF(B81>=4,INDEX('Break-even'!$C$12:$F$12,1,4),INDEX('Break-even'!$C$12:$F$12,1,B81)+(INDEX('Break-even'!$C$12:$F$12,1,B81+1)-INDEX('Break-even'!$C$12:$F$12,1,B81))*LN(A81/INDEX('Break-even'!$C$6:$F$6,1,B81))/LN(INDEX('Break-even'!$C$6:$F$6,1,B81+1)/INDEX('Break-even'!$C$6:$F$6,1,B81))) -> 2.2952631 | D81: =IF(B81>=4,INDEX('Break-even'!$C$13:$F$13,1,4),INDEX('Break-even'!$C$13:$F$13,1,B81)+(INDEX('Break-even'!$C$13:$F$13,1,B81+1)-INDEX('Break-even'!$C$13:$F$13,1,B81))*LN(A81/INDEX('Break-even'!$C$6:$F$6,1,B81))/LN(INDEX('Break-even'!$C$6:$F$6,1,B81+1)/INDEX('Break-even'!$C$6:$F$6,1,B81))) -> 0.60248089 | E81: =CEILING(A81/('Break-even'!$C$26*Ipoteze!$C$20),1) -> 1 | F81: =MIN(Ipoteze!$C$20,CEILING(A81/('Break-even'!$C$26*E81),1)) -> 1 | G81: =E81*F81 -> 1 | H81: =E81*'Break-even'!$C$25/Ipoteze!$C$90+G81*('Break-even'!$C$27+'Break-even'!$C$19)+E81*Ipoteze!$C$155*'Break-even'!$C$22+Ipoteze!$C$124*E81*'Break-even'!$C$25+Ipoteze!$C$154*Ipoteze!$C$16*Ipoteze!$C$15*F81*E81*Ipoteze!$C$101/Ipoteze!$C$7+Ipoteze!$C$156 -> 29356.785 | I81: =IF(B81>=4,INDEX('Break-even'!$C$14:$F$14,1,4),INDEX('Break-even'!$C$14:$F$14,1,B81)+(INDEX('Break-even'!$C$14:$F$14,1,B81+1)-INDEX('Break-even'!$C$14:$F$14,1,B81))*LN(A81/INDEX('Break-even'!$C$6:$F$6,1,B81))/LN(INDEX('Break-even'!$C$6:$F$6,1,B81+1)/INDEX('Break-even'!$C$6:$F$6,1,B81))) -> 0.30335816 | J81: =H81+A81*I81 -> 31631.971 | K81: =J81/A81 -> 4.2175961 | L81: =A81*C81 -> 17214.473 | M81: =A81*D81 -> 4518.6067 | N81: =IF(J81<L81,1,0) -> 0 | O81: =IF(J81<M81,1,0) -> 0
A82: 10000 | B82: =MATCH(A82,'Break-even'!$C$6:$F$6,1) -> 3 | C82: =IF(B82>=4,INDEX('Break-even'!$C$12:$F$12,1,4),INDEX('Break-even'!$C$12:$F$12,1,B82)+(INDEX('Break-even'!$C$12:$F$12,1,B82+1)-INDEX('Break-even'!$C$12:$F$12,1,B82))*LN(A82/INDEX('Break-even'!$C$6:$F$6,1,B82))/LN(INDEX('Break-even'!$C$6:$F$6,1,B82+1)/INDEX('Break-even'!$C$6:$F$6,1,B82))) -> 2.15 | D82: =IF(B82>=4,INDEX('Break-even'!$C$13:$F$13,1,4),INDEX('Break-even'!$C$13:$F$13,1,B82)+(INDEX('Break-even'!$C$13:$F$13,1,B82+1)-INDEX('Break-even'!$C$13:$F$13,1,B82))*LN(A82/INDEX('Break-even'!$C$6:$F$6,1,B82))/LN(INDEX('Break-even'!$C$6:$F$6,1,B82+1)/INDEX('Break-even'!$C$6:$F$6,1,B82))) -> 0.56893364 | E82: =CEILING(A82/('Break-even'!$C$26*Ipoteze!$C$20),1) -> 1 | F82: =MIN(Ipoteze!$C$20,CEILING(A82/('Break-even'!$C$26*E82),1)) -> 1 | G82: =E82*F82 -> 1 | H82: =E82*'Break-even'!$C$25/Ipoteze!$C$90+G82*('Break-even'!$C$27+'Break-even'!$C$19)+E82*Ipoteze!$C$155*'Break-even'!$C$22+Ipoteze!$C$124*E82*'Break-even'!$C$25+Ipoteze!$C$154*Ipoteze!$C$16*Ipoteze!$C$15*F82*E82*Ipoteze!$C$101/Ipoteze!$C$7+Ipoteze!$C$156 -> 29356.785 | I82: =IF(B82>=4,INDEX('Break-even'!$C$14:$F$14,1,4),INDEX('Break-even'!$C$14:$F$14,1,B82)+(INDEX('Break-even'!$C$14:$F$14,1,B82+1)-INDEX('Break-even'!$C$14:$F$14,1,B82))*LN(A82/INDEX('Break-even'!$C$6:$F$6,1,B82))/LN(INDEX('Break-even'!$C$6:$F$6,1,B82+1)/INDEX('Break-even'!$C$6:$F$6,1,B82))) -> 0.3011375 | J82: =H82+A82*I82 -> 32368.16 | K82: =J82/A82 -> 3.236816 | L82: =A82*C82 -> 21500 | M82: =A82*D82 -> 5689.3364 | N82: =IF(J82<L82,1,0) -> 0 | O82: =IF(J82<M82,1,0) -> 0
A83: 15000 | B83: =MATCH(A83,'Break-even'!$C$6:$F$6,1) -> 3 | C83: =IF(B83>=4,INDEX('Break-even'!$C$12:$F$12,1,4),INDEX('Break-even'!$C$12:$F$12,1,B83)+(INDEX('Break-even'!$C$12:$F$12,1,B83+1)-INDEX('Break-even'!$C$12:$F$12,1,B83))*LN(A83/INDEX('Break-even'!$C$6:$F$6,1,B83))/LN(INDEX('Break-even'!$C$6:$F$6,1,B83+1)/INDEX('Break-even'!$C$6:$F$6,1,B83))) -> 1.9452631 | D83: =IF(B83>=4,INDEX('Break-even'!$C$13:$F$13,1,4),INDEX('Break-even'!$C$13:$F$13,1,B83)+(INDEX('Break-even'!$C$13:$F$13,1,B83+1)-INDEX('Break-even'!$C$13:$F$13,1,B83))*LN(A83/INDEX('Break-even'!$C$6:$F$6,1,B83))/LN(INDEX('Break-even'!$C$6:$F$6,1,B83+1)/INDEX('Break-even'!$C$6:$F$6,1,B83))) -> 0.52165145 | E83: =CEILING(A83/('Break-even'!$C$26*Ipoteze!$C$20),1) -> 1 | F83: =MIN(Ipoteze!$C$20,CEILING(A83/('Break-even'!$C$26*E83),1)) -> 1 | G83: =E83*F83 -> 1 | H83: =E83*'Break-even'!$C$25/Ipoteze!$C$90+G83*('Break-even'!$C$27+'Break-even'!$C$19)+E83*Ipoteze!$C$155*'Break-even'!$C$22+Ipoteze!$C$124*E83*'Break-even'!$C$25+Ipoteze!$C$154*Ipoteze!$C$16*Ipoteze!$C$15*F83*E83*Ipoteze!$C$101/Ipoteze!$C$7+Ipoteze!$C$156 -> 29356.785 | I83: =IF(B83>=4,INDEX('Break-even'!$C$14:$F$14,1,4),INDEX('Break-even'!$C$14:$F$14,1,B83)+(INDEX('Break-even'!$C$14:$F$14,1,B83+1)-INDEX('Break-even'!$C$14:$F$14,1,B83))*LN(A83/INDEX('Break-even'!$C$6:$F$6,1,B83))/LN(INDEX('Break-even'!$C$6:$F$6,1,B83+1)/INDEX('Break-even'!$C$6:$F$6,1,B83))) -> 0.29800766 | J83: =H83+A83*I83 -> 33826.9 | K83: =J83/A83 -> 2.2551266 | L83: =A83*C83 -> 29178.947 | M83: =A83*D83 -> 7824.7717 | N83: =IF(J83<L83,1,0) -> 0 | O83: =IF(J83<M83,1,0) -> 0
A84: 20000 | B84: =MATCH(A84,'Break-even'!$C$6:$F$6,1) -> 4 | C84: =IF(B84>=4,INDEX('Break-even'!$C$12:$F$12,1,4),INDEX('Break-even'!$C$12:$F$12,1,B84)+(INDEX('Break-even'!$C$12:$F$12,1,B84+1)-INDEX('Break-even'!$C$12:$F$12,1,B84))*LN(A84/INDEX('Break-even'!$C$6:$F$6,1,B84))/LN(INDEX('Break-even'!$C$6:$F$6,1,B84+1)/INDEX('Break-even'!$C$6:$F$6,1,B84))) -> 1.8 | D84: =IF(B84>=4,INDEX('Break-even'!$C$13:$F$13,1,4),INDEX('Break-even'!$C$13:$F$13,1,B84)+(INDEX('Break-even'!$C$13:$F$13,1,B84+1)-INDEX('Break-even'!$C$13:$F$13,1,B84))*LN(A84/INDEX('Break-even'!$C$6:$F$6,1,B84))/LN(INDEX('Break-even'!$C$6:$F$6,1,B84+1)/INDEX('Break-even'!$C$6:$F$6,1,B84))) -> 0.4881042 | E84: =CEILING(A84/('Break-even'!$C$26*Ipoteze!$C$20),1) -> 1 | F84: =MIN(Ipoteze!$C$20,CEILING(A84/('Break-even'!$C$26*E84),1)) -> 1 | G84: =E84*F84 -> 1 | H84: =E84*'Break-even'!$C$25/Ipoteze!$C$90+G84*('Break-even'!$C$27+'Break-even'!$C$19)+E84*Ipoteze!$C$155*'Break-even'!$C$22+Ipoteze!$C$124*E84*'Break-even'!$C$25+Ipoteze!$C$154*Ipoteze!$C$16*Ipoteze!$C$15*F84*E84*Ipoteze!$C$101/Ipoteze!$C$7+Ipoteze!$C$156 -> 29356.785 | I84: =IF(B84>=4,INDEX('Break-even'!$C$14:$F$14,1,4),INDEX('Break-even'!$C$14:$F$14,1,B84)+(INDEX('Break-even'!$C$14:$F$14,1,B84+1)-INDEX('Break-even'!$C$14:$F$14,1,B84))*LN(A84/INDEX('Break-even'!$C$6:$F$6,1,B84))/LN(INDEX('Break-even'!$C$6:$F$6,1,B84+1)/INDEX('Break-even'!$C$6:$F$6,1,B84))) -> 0.295787 | J84: =H84+A84*I84 -> 35272.525 | K84: =J84/A84 -> 1.7636262 | L84: =A84*C84 -> 36000 | M84: =A84*D84 -> 9762.084 | N84: =IF(J84<L84,1,0) -> 1 | O84: =IF(J84<M84,1,0) -> 0
A85: 25000 | B85: =MATCH(A85,'Break-even'!$C$6:$F$6,1) -> 4 | C85: =IF(B85>=4,INDEX('Break-even'!$C$12:$F$12,1,4),INDEX('Break-even'!$C$12:$F$12,1,B85)+(INDEX('Break-even'!$C$12:$F$12,1,B85+1)-INDEX('Break-even'!$C$12:$F$12,1,B85))*LN(A85/INDEX('Break-even'!$C$6:$F$6,1,B85))/LN(INDEX('Break-even'!$C$6:$F$6,1,B85+1)/INDEX('Break-even'!$C$6:$F$6,1,B85))) -> 1.8 | D85: =IF(B85>=4,INDEX('Break-even'!$C$13:$F$13,1,4),INDEX('Break-even'!$C$13:$F$13,1,B85)+(INDEX('Break-even'!$C$13:$F$13,1,B85+1)-INDEX('Break-even'!$C$13:$F$13,1,B85))*LN(A85/INDEX('Break-even'!$C$6:$F$6,1,B85))/LN(INDEX('Break-even'!$C$6:$F$6,1,B85+1)/INDEX('Break-even'!$C$6:$F$6,1,B85))) -> 0.4881042 | E85: =CEILING(A85/('Break-even'!$C$26*Ipoteze!$C$20),1) -> 1 | F85: =MIN(Ipoteze!$C$20,CEILING(A85/('Break-even'!$C$26*E85),1)) -> 2 | G85: =E85*F85 -> 2 | H85: =E85*'Break-even'!$C$25/Ipoteze!$C$90+G85*('Break-even'!$C$27+'Break-even'!$C$19)+E85*Ipoteze!$C$155*'Break-even'!$C$22+Ipoteze!$C$124*E85*'Break-even'!$C$25+Ipoteze!$C$154*Ipoteze!$C$16*Ipoteze!$C$15*F85*E85*Ipoteze!$C$101/Ipoteze!$C$7+Ipoteze!$C$156 -> 46005.373 | I85: =IF(B85>=4,INDEX('Break-even'!$C$14:$F$14,1,4),INDEX('Break-even'!$C$14:$F$14,1,B85)+(INDEX('Break-even'!$C$14:$F$14,1,B85+1)-INDEX('Break-even'!$C$14:$F$14,1,B85))*LN(A85/INDEX('Break-even'!$C$6:$F$6,1,B85))/LN(INDEX('Break-even'!$C$6:$F$6,1,B85+1)/INDEX('Break-even'!$C$6:$F$6,1,B85))) -> 0.295787 | J85: =H85+A85*I85 -> 53400.048 | K85: =J85/A85 -> 2.1360019 | L85: =A85*C85 -> 45000 | M85: =A85*D85 -> 12202.605 | N85: =IF(J85<L85,1,0) -> 0 | O85: =IF(J85<M85,1,0) -> 0
A86: 30000 | B86: =MATCH(A86,'Break-even'!$C$6:$F$6,1) -> 4 | C86: =IF(B86>=4,INDEX('Break-even'!$C$12:$F$12,1,4),INDEX('Break-even'!$C$12:$F$12,1,B86)+(INDEX('Break-even'!$C$12:$F$12,1,B86+1)-INDEX('Break-even'!$C$12:$F$12,1,B86))*LN(A86/INDEX('Break-even'!$C$6:$F$6,1,B86))/LN(INDEX('Break-even'!$C$6:$F$6,1,B86+1)/INDEX('Break-even'!$C$6:$F$6,1,B86))) -> 1.8 | D86: =IF(B86>=4,INDEX('Break-even'!$C$13:$F$13,1,4),INDEX('Break-even'!$C$13:$F$13,1,B86)+(INDEX('Break-even'!$C$13:$F$13,1,B86+1)-INDEX('Break-even'!$C$13:$F$13,1,B86))*LN(A86/INDEX('Break-even'!$C$6:$F$6,1,B86))/LN(INDEX('Break-even'!$C$6:$F$6,1,B86+1)/INDEX('Break-even'!$C$6:$F$6,1,B86))) -> 0.4881042 | E86: =CEILING(A86/('Break-even'!$C$26*Ipoteze!$C$20),1) -> 1 | F86: =MIN(Ipoteze!$C$20,CEILING(A86/('Break-even'!$C$26*E86),1)) -> 2 | G86: =E86*F86 -> 2 | H86: =E86*'Break-even'!$C$25/Ipoteze!$C$90+G86*('Break-even'!$C$27+'Break-even'!$C$19)+E86*Ipoteze!$C$155*'Break-even'!$C$22+Ipoteze!$C$124*E86*'Break-even'!$C$25+Ipoteze!$C$154*Ipoteze!$C$16*Ipoteze!$C$15*F86*E86*Ipoteze!$C$101/Ipoteze!$C$7+Ipoteze!$C$156 -> 46005.373 | I86: =IF(B86>=4,INDEX('Break-even'!$C$14:$F$14,1,4),INDEX('Break-even'!$C$14:$F$14,1,B86)+(INDEX('Break-even'!$C$14:$F$14,1,B86+1)-INDEX('Break-even'!$C$14:$F$14,1,B86))*LN(A86/INDEX('Break-even'!$C$6:$F$6,1,B86))/LN(INDEX('Break-even'!$C$6:$F$6,1,B86+1)/INDEX('Break-even'!$C$6:$F$6,1,B86))) -> 0.295787 | J86: =H86+A86*I86 -> 54878.983 | K86: =J86/A86 -> 1.8292994 | L86: =A86*C86 -> 54000 | M86: =A86*D86 -> 14643.126 | N86: =IF(J86<L86,1,0) -> 0 | O86: =IF(J86<M86,1,0) -> 0
A87: 40000 | B87: =MATCH(A87,'Break-even'!$C$6:$F$6,1) -> 4 | C87: =IF(B87>=4,INDEX('Break-even'!$C$12:$F$12,1,4),INDEX('Break-even'!$C$12:$F$12,1,B87)+(INDEX('Break-even'!$C$12:$F$12,1,B87+1)-INDEX('Break-even'!$C$12:$F$12,1,B87))*LN(A87/INDEX('Break-even'!$C$6:$F$6,1,B87))/LN(INDEX('Break-even'!$C$6:$F$6,1,B87+1)/INDEX('Break-even'!$C$6:$F$6,1,B87))) -> 1.8 | D87: =IF(B87>=4,INDEX('Break-even'!$C$13:$F$13,1,4),INDEX('Break-even'!$C$13:$F$13,1,B87)+(INDEX('Break-even'!$C$13:$F$13,1,B87+1)-INDEX('Break-even'!$C$13:$F$13,1,B87))*LN(A87/INDEX('Break-even'!$C$6:$F$6,1,B87))/LN(INDEX('Break-even'!$C$6:$F$6,1,B87+1)/INDEX('Break-even'!$C$6:$F$6,1,B87))) -> 0.4881042 | E87: =CEILING(A87/('Break-even'!$C$26*Ipoteze!$C$20),1) -> 1 | F87: =MIN(Ipoteze!$C$20,CEILING(A87/('Break-even'!$C$26*E87),1)) -> 2 | G87: =E87*F87 -> 2 | H87: =E87*'Break-even'!$C$25/Ipoteze!$C$90+G87*('Break-even'!$C$27+'Break-even'!$C$19)+E87*Ipoteze!$C$155*'Break-even'!$C$22+Ipoteze!$C$124*E87*'Break-even'!$C$25+Ipoteze!$C$154*Ipoteze!$C$16*Ipoteze!$C$15*F87*E87*Ipoteze!$C$101/Ipoteze!$C$7+Ipoteze!$C$156 -> 46005.373 | I87: =IF(B87>=4,INDEX('Break-even'!$C$14:$F$14,1,4),INDEX('Break-even'!$C$14:$F$14,1,B87)+(INDEX('Break-even'!$C$14:$F$14,1,B87+1)-INDEX('Break-even'!$C$14:$F$14,1,B87))*LN(A87/INDEX('Break-even'!$C$6:$F$6,1,B87))/LN(INDEX('Break-even'!$C$6:$F$6,1,B87+1)/INDEX('Break-even'!$C$6:$F$6,1,B87))) -> 0.295787 | J87: =H87+A87*I87 -> 57836.853 | K87: =J87/A87 -> 1.4459213 | L87: =A87*C87 -> 72000 | M87: =A87*D87 -> 19524.168 | N87: =IF(J87<L87,1,0) -> 1 | O87: =IF(J87<M87,1,0) -> 0
A88: 50000 | B88: =MATCH(A88,'Break-even'!$C$6:$F$6,1) -> 4 | C88: =IF(B88>=4,INDEX('Break-even'!$C$12:$F$12,1,4),INDEX('Break-even'!$C$12:$F$12,1,B88)+(INDEX('Break-even'!$C$12:$F$12,1,B88+1)-INDEX('Break-even'!$C$12:$F$12,1,B88))*LN(A88/INDEX('Break-even'!$C$6:$F$6,1,B88))/LN(INDEX('Break-even'!$C$6:$F$6,1,B88+1)/INDEX('Break-even'!$C$6:$F$6,1,B88))) -> 1.8 | D88: =IF(B88>=4,INDEX('Break-even'!$C$13:$F$13,1,4),INDEX('Break-even'!$C$13:$F$13,1,B88)+(INDEX('Break-even'!$C$13:$F$13,1,B88+1)-INDEX('Break-even'!$C$13:$F$13,1,B88))*LN(A88/INDEX('Break-even'!$C$6:$F$6,1,B88))/LN(INDEX('Break-even'!$C$6:$F$6,1,B88+1)/INDEX('Break-even'!$C$6:$F$6,1,B88))) -> 0.4881042 | E88: =CEILING(A88/('Break-even'!$C$26*Ipoteze!$C$20),1) -> 2 | F88: =MIN(Ipoteze!$C$20,CEILING(A88/('Break-even'!$C$26*E88),1)) -> 2 | G88: =E88*F88 -> 4 | H88: =E88*'Break-even'!$C$25/Ipoteze!$C$90+G88*('Break-even'!$C$27+'Break-even'!$C$19)+E88*Ipoteze!$C$155*'Break-even'!$C$22+Ipoteze!$C$124*E88*'Break-even'!$C$25+Ipoteze!$C$154*Ipoteze!$C$16*Ipoteze!$C$15*F88*E88*Ipoteze!$C$101/Ipoteze!$C$7+Ipoteze!$C$156 -> 91710.746 | I88: =IF(B88>=4,INDEX('Break-even'!$C$14:$F$14,1,4),INDEX('Break-even'!$C$14:$F$14,1,B88)+(INDEX('Break-even'!$C$14:$F$14,1,B88+1)-INDEX('Break-even'!$C$14:$F$14,1,B88))*LN(A88/INDEX('Break-even'!$C$6:$F$6,1,B88))/LN(INDEX('Break-even'!$C$6:$F$6,1,B88+1)/INDEX('Break-even'!$C$6:$F$6,1,B88))) -> 0.295787 | J88: =H88+A88*I88 -> 106500.1 | K88: =J88/A88 -> 2.1300019 | L88: =A88*C88 -> 90000 | M88: =A88*D88 -> 24405.21 | N88: =IF(J88<L88,1,0) -> 0 | O88: =IF(J88<M88,1,0) -> 0
A89: 60000 | B89: =MATCH(A89,'Break-even'!$C$6:$F$6,1) -> 4 | C89: =IF(B89>=4,INDEX('Break-even'!$C$12:$F$12,1,4),INDEX('Break-even'!$C$12:$F$12,1,B89)+(INDEX('Break-even'!$C$12:$F$12,1,B89+1)-INDEX('Break-even'!$C$12:$F$12,1,B89))*LN(A89/INDEX('Break-even'!$C$6:$F$6,1,B89))/LN(INDEX('Break-even'!$C$6:$F$6,1,B89+1)/INDEX('Break-even'!$C$6:$F$6,1,B89))) -> 1.8 | D89: =IF(B89>=4,INDEX('Break-even'!$C$13:$F$13,1,4),INDEX('Break-even'!$C$13:$F$13,1,B89)+(INDEX('Break-even'!$C$13:$F$13,1,B89+1)-INDEX('Break-even'!$C$13:$F$13,1,B89))*LN(A89/INDEX('Break-even'!$C$6:$F$6,1,B89))/LN(INDEX('Break-even'!$C$6:$F$6,1,B89+1)/INDEX('Break-even'!$C$6:$F$6,1,B89))) -> 0.4881042 | E89: =CEILING(A89/('Break-even'!$C$26*Ipoteze!$C$20),1) -> 2 | F89: =MIN(Ipoteze!$C$20,CEILING(A89/('Break-even'!$C$26*E89),1)) -> 2 | G89: =E89*F89 -> 4 | H89: =E89*'Break-even'!$C$25/Ipoteze!$C$90+G89*('Break-even'!$C$27+'Break-even'!$C$19)+E89*Ipoteze!$C$155*'Break-even'!$C$22+Ipoteze!$C$124*E89*'Break-even'!$C$25+Ipoteze!$C$154*Ipoteze!$C$16*Ipoteze!$C$15*F89*E89*Ipoteze!$C$101/Ipoteze!$C$7+Ipoteze!$C$156 -> 91710.746 | I89: =IF(B89>=4,INDEX('Break-even'!$C$14:$F$14,1,4),INDEX('Break-even'!$C$14:$F$14,1,B89)+(INDEX('Break-even'!$C$14:$F$14,1,B89+1)-INDEX('Break-even'!$C$14:$F$14,1,B89))*LN(A89/INDEX('Break-even'!$C$6:$F$6,1,B89))/LN(INDEX('Break-even'!$C$6:$F$6,1,B89+1)/INDEX('Break-even'!$C$6:$F$6,1,B89))) -> 0.295787 | J89: =H89+A89*I89 -> 109457.97 | K89: =J89/A89 -> 1.8242994 | L89: =A89*C89 -> 108000 | M89: =A89*D89 -> 29286.252 | N89: =IF(J89<L89,1,0) -> 0 | O89: =IF(J89<M89,1,0) -> 0
B90: Primul volum la care SMT propriu bate EMS România | C90: =IFERROR(INDEX(A77:A89,MATCH(1,N77:N89,0)),"peste 60.000") -> 20000
B91: Primul volum la care SMT propriu bate JLCPCB | C91: =IFERROR(INDEX(A77:A89,MATCH(1,O77:O89,0)),"peste 60.000") -> peste 60.000
B92: Volume din grilă unde SMT propriu bate EMS (număr din 13) | C92: =SUM(N77:N89) -> 2
B93: Volume din grilă unde SMT propriu bate JLCPCB (număr din 13) | C93: =SUM(O77:O89) -> 0

Sheet Capacitate
A1: CAPACITATE: unități pe schimb per stație, necesar de stații și gâtuirea liniei
A2: Unități/schimb = minute productive pe schimb × posturi paralele / timp ciclu. Necesar = volum / (capacitate anuală pe 1 schimb × utilizare țintă), rotunjit în sus. Pentru CNC și SMT necesarul vine din Scenarii (cu 2 schimburi înainte de a cumpăra încă o mașină).
A4: Stație | B4: Timp ciclu (min) | C4: Posturi paralele | D4: Unități / schimb | E4: Unități / an (1 schimb) | F4: Necesar @100 | G4: Necesar @1.000 | H4: Necesar @5.000 | I4: Necesar @20.000 | J4: Utilizare @20.000 | L4: Notă
A5: Banc asamblare (1 operator) | B5: =Ipoteze!D$66 -> 25 | C5: 1 | D5: =Ipoteze!$C$18*C5/B5 -> 16.32 | E5: =D5*Ipoteze!$C$15 -> 3590.4 | F5: =Scenarii!C34 -> 0.05013369 | G5: =Scenarii!D34 -> 0.2785205 | H5: =Scenarii!E34 -> 1.114082 | I5: =Scenarii!F34 -> 3.342246 | J5: =I5/MAX(1,CEILING(I5,1)) -> 0.8355615 | L5: Ciclul = manopera totală la 1.000 buc./an; necesarul folosește minutele per volum (Ipoteze 4). Gâtuirea reală a T0 = oamenii.
A6: Stație flash | B6: =Ipoteze!$C$68 -> 2 | C6: =Ipoteze!$C$69 -> 4 | D6: =Ipoteze!$C$18*C6/B6 -> 816 | E6: =D6*Ipoteze!$C$15 -> 179520 | F6: =MAX(1,CEILING(Ipoteze!C$9/(E6*Ipoteze!$C$21),1)) -> 1 | G6: =MAX(1,CEILING(Ipoteze!D$9/(E6*Ipoteze!$C$21),1)) -> 1 | H6: =MAX(1,CEILING(Ipoteze!E$9/(E6*Ipoteze!$C$21),1)) -> 1 | I6: =MAX(1,CEILING(Ipoteze!F$9/(E6*Ipoteze!$C$21),1)) -> 1 | J6: =Ipoteze!F$9/(E6*IF(I6<1,1,CEILING(I6,1))) -> 0.1114082 | L6: Espressif Flash Download Tool, mod Factory
A7: Jig test funcțional | B7: =Ipoteze!$C$67 -> 4 | C7: 1 | D7: =Ipoteze!$C$18*C7/B7 -> 102 | E7: =D7*Ipoteze!$C$15 -> 22440 | F7: =MAX(1,CEILING(Ipoteze!C$9/(E7*Ipoteze!$C$21),1)) -> 1 | G7: =MAX(1,CEILING(Ipoteze!D$9/(E7*Ipoteze!$C$21),1)) -> 1 | H7: =MAX(1,CEILING(Ipoteze!E$9/(E7*Ipoteze!$C$21),1)) -> 1 | I7: =MAX(1,CEILING(Ipoteze!F$9/(E7*Ipoteze!$C$21),1)) -> 2 | J7: =Ipoteze!F$9/(E7*IF(I7<1,1,CEILING(I7,1))) -> 0.4456328 | L7: Fixturfab; cutie ecranată pentru RSSI
A8: Raft rodaj (burn-in) | B8: =Ipoteze!$C$70 -> 10 | C8: =Ipoteze!$C$71 -> 20 | D8: =Ipoteze!$C$18*C8/B8 -> 816 | E8: =D8*Ipoteze!$C$15 -> 179520 | F8: =MAX(1,CEILING(Ipoteze!C$9/(E8*Ipoteze!$C$21),1)) -> 1 | G8: =MAX(1,CEILING(Ipoteze!D$9/(E8*Ipoteze!$C$21),1)) -> 1 | H8: =MAX(1,CEILING(Ipoteze!E$9/(E8*Ipoteze!$C$21),1)) -> 1 | I8: =MAX(1,CEILING(Ipoteze!F$9/(E8*Ipoteze!$C$21),1)) -> 1 | J8: =Ipoteze!F$9/(E8*IF(I8<1,1,CEILING(I8,1))) -> 0.1114082 | L8: Nesupravegheat
A9: Laser MOPA marcare | B9: =Ipoteze!$C$72 -> 1 | C9: 1 | D9: =Ipoteze!$C$18*C9/B9 -> 408 | E9: =D9*Ipoteze!$C$15 -> 89760 | F9: =MAX(1,CEILING(Ipoteze!C$9/(E9*Ipoteze!$C$21),1)) -> 1 | G9: =MAX(1,CEILING(Ipoteze!D$9/(E9*Ipoteze!$C$21),1)) -> 1 | H9: =MAX(1,CEILING(Ipoteze!E$9/(E9*Ipoteze!$C$21),1)) -> 1 | I9: =MAX(1,CEILING(Ipoteze!F$9/(E9*Ipoteze!$C$21),1)) -> 1 | J9: =Ipoteze!F$9/(E9*IF(I9<1,1,CEILING(I9,1))) -> 0.2228164 | L9: Serie + CE/WEEE după anodizare
A10: CNC mărimea S (1 mașină) | B10: =Ipoteze!$C$125 -> 24 | C10: 1 | D10: =Ipoteze!$C$18*C10/B10 -> 17 | E10: =D10*Ipoteze!$C$15 -> 3740 | F10: =Scenarii!C42 -> 1 | G10: =Scenarii!D42 -> 1 | H10: =Scenarii!E42 -> 1 | I10: =Scenarii!F42 -> 3 | J10: =Scenarii!F45 -> 0.8912656 | L10: Necesar = mașini (cu până la 2 schimburi). Gâtuirea scenariilor C/D.
A11: CNC mărimea M, comparație (1 mașină) | B11: =Ipoteze!$C$126 -> 45 | C11: 1 | D11: =Ipoteze!$C$18*C11/B11 -> 9.0666667 | E11: =D11*Ipoteze!$C$15 -> 1994.6667 | F11: =CEILING(Ipoteze!C$9/(E11*Ipoteze!$C$20),1) -> 1 | G11: =CEILING(Ipoteze!D$9/(E11*Ipoteze!$C$20),1) -> 1 | H11: =CEILING(Ipoteze!E$9/(E11*Ipoteze!$C$20),1) -> 2 | I11: =CEILING(Ipoteze!F$9/(E11*Ipoteze!$C$20),1) -> 6 | J11: =Ipoteze!F$9/(E11*I11*Ipoteze!$C$20) -> 0.8355615 | L11: Comparație M: ciclu de ~1,9× mai lung → ~0,53× seturi pe mașină
A12: Linie SMT (NeoDen4 + reflow + AOI) | B12: =Ipoteze!$C$52/Ipoteze!$C$149*60+Ipoteze!$C$150 -> 4.1 | C12: 1 | D12: =Ipoteze!$C$18*C12/B12 -> 99.512195 | E12: =D12*Ipoteze!$C$15 -> 21892.683 | F12: =Scenarii!C50 -> 1 | G12: =Scenarii!D50 -> 1 | H12: =Scenarii!E50 -> 1 | I12: =Scenarii!F50 -> 1 | J12: =Ipoteze!F$9/(E12*Scenarii!F50*Scenarii!F51) -> 0.91354724 | L12: Reflow-ul NeoDen IN6 nu e gâtuire la aceste volume
A14: Gâtuirea T0 (stația cu cele mai puține unități/schimb) | D14: =MIN(D5:D9) -> 16.32 | E14: =INDEX(A5:A9,MATCH(D14,D5:D9,0)) -> Banc asamblare (1 operator)
A15: Gâtuirea scenariilor C/D (unități/schimb) | D15: =MIN(D5:D10) -> 16.32 | E15: =INDEX(A5:A10,MATCH(D15,D5:D10,0)) -> Banc asamblare (1 operator)
A17: Personal necesar (persoane) | F17: =Ipoteze!C$9 -> 100 | G17: =Ipoteze!D$9 -> 1000 | H17: =Ipoteze!E$9 -> 5000 | I17: =Ipoteze!F$9 -> 20000
A18: Scenariul B (operatori + QC + gestionar) | F18: =Scenarii!C38 -> 1 | G18: =Scenarii!D38 -> 1 | H18: =Scenarii!E38 -> 3 | I18: =Scenarii!F38 -> 6
A19: Scenariul C (+ CNC) | F19: =Scenarii!C55 -> 2 | G19: =Scenarii!D55 -> 2 | H19: =Scenarii!E55 -> 5 | I19: =Scenarii!F55 -> 10
A20: Scenariul D (+ SMT) | F20: =Scenarii!C56 -> 3 | G20: =Scenarii!D56 -> 3 | H20: =Scenarii!E56 -> 6 | I20: =Scenarii!F56 -> 11
